Workbook

Sheet README
A1: Regional Climate & Weather Event Register — Catskills / Hudson Valley / Capital Region
A2: Reference point for the Wind & Tornado sheet: Westerlo, NY hamlet
A3: Westerlo latitude | B3: 42.517
A4: Westerlo longitude | B4: -74.045
A5: Search radius (miles) | B5: 30
A6: Radius note: the 30-mile radius applies ONLY to the Wind & Tornado sheet (localized, small-footprint events). Regional hazards — floods, ice jams, droughts, cold waves, blizzards, heat waves — are NOT radius-limited; they are included wherever they affected the Catskills, Hudson Valley, Mohawk Valley or Capital Region. The CRREL ice-jam sheet uses a 75-mile regional footprint with its own Dist. column.
A8: Sheets
A9: Events | B9: One row per event. ~150 rows. Sort/filter by Category, Confidence, Verified.
A10: Wind & Tornadoes | B10: Every tornado from NCEI (1950–2012 via Tornado Project; 2013+ via NWS ALY surveys/tornadopath) within ~45 mi, plus Grazulis pre-1950 F2+/deadly, plus notable straight-line wind days. Distance from Westerlo is a live haversine formula off the cells above; 'Within radius' flag recalculates if you change the radius.
A11: Summary | B11: COUNTIF roll-ups by category, confidence and century; tornado counts by rating and within-radius.
A12: Sources | B12: Primary sources with URLs and what each is good for.
A14: Confidence grades
A15: A | B15: Instrument-era figure taken directly from NWS Albany, NCEI, USGS, or an NWS storm survey this pass.
A16: B | B16: Well-documented event; figures from secondary sources or from memory of standard references — check before quoting a number.
A17: C | B17: Chronicle/diary-era (pre-~1870) or qualitative; treat as 'it happened and was bad', not as data.
A19: Verified column | B19: Y = checked against a primary source during this build (NWS ALY Past Events page, Tornado Project county tables, NCEI, NWS ALY July 2026 writeup). N = not yet checked; these are the rows to work through first.
A21: Known gaps / to-do
A22: 1 | B22: Pre-1870 growing-season disasters are under-represented; Ludlum and county histories (Beers, Munsell's Annals of Albany) would fill them.
A23: 2 | B23: Albany all-time extremes (104°F Jul 4 1911; –28°F Jan 19 1971) not yet re-checked against weather.gov/media/aly/Climate/ALB_Extremes.pdf.
A24: 3 | B24: Post-2012 tornado coordinates marked 'approx' should be replaced with NCEI begin/end lat-lon.
A25: 4 | B25: April 21, 2021 tornado locations and the July 27, 2014 EF1 location not captured.
A26: 5 | B26: Frost/freeze dates for the Helderberg plateau specifically: pull GHCN daily for the nearest coop (Rensselaerville? Delanson? Albany AP as fallback) rather than trusting valley stations.
A27: 6 | B27: Drought years should be re-graded from the US Drought Monitor archive (2000+) and Palmer indices (pre-2000).
A29: Timeline anchors | B29: Columns Q–V on Events give one anchor date per row for plotting. Precision: day = the date is the date; days = anchored to the first (or peak) day of a ≤10-day event; week/month/season/year = a representative point inside a longer window (mid-point unless the basis column says otherwise). Filter on precision when you build the timeline so you don't plot a drought as if it happened on one afternoon.
A30: Dates before 1900 | B30: Excel cannot store dates before 1900-01-01, so all dates are ISO text and the anchor is split into numeric Year/Month/Day columns — the format TimelineJS and most timeline libraries expect.
A31: Geohazard rows | B31: Categories Ice jam, Landslide, Sinkhole (karst vs infrastructure) added. Two rows are context/pattern rows (precision = year) and should be filtered out of a point timeline. Three Niagara rows are flagged OUT OF REGION in the name.
A32: Cells highlighted yellow are inputs you can change.
A34: --- 2026-09-21 addendum (Claude, atlas session — the original research chat was NOT reopened) ---
A35: Cross-checked this handoff package against the atlas's own copy of the register: the atlas copy was already ahead (293 events / 29 sources / 29 karst features vs 264/24/24 here), so nothing was missing.
A36: Then worked the open-items list as far as web search + the atlas's own station data would go:
A37: #1 Knox Cave month: the 2025 Pomeroy Foundation historic marker independently says March 1975 — now 2 sources for March vs 1 for May vs 1 for 1976. Anchor updated to 1975-03 (month precision; day still not asserted). See Events row 141 and Sources.
A38: #3 Albany extremes: CONFIRMED against the current ALB_Extremes.pdf — 104°F Jul 4 1911 / -28°F Jan 19 1971, exactly as already recorded.
A39: #4 Frost/freeze phenology: built from Alcove Dam's own daily record (already in the atlas repo, no new upload needed) — see the new "Frost & Freeze Phenology" sheet. 70-year and recent-30-year medians, full year-by-year table. Alcove Dam is ~590 ft, ~1,100 ft below Laurie's plateau — the best available regional anchor, not a plateau substitute.
A40: Bonus: Stone (2005 NCKMS) corrects McFail's own death to July 1, 1854 (not the widely repeated 1853 from Roscoe 1882) — logged in Sources. Did NOT find the historic-entrance collapse date (#2) — still open.
A41: STILL OPEN, genuinely unresolved by this pass (need the original chat's archive access or Laurie's own future work, not just web search):
A42: #2 McFails historic-entrance collapse date. #5 Ludlum vol. II (1821-1870) — a physical/scanned book, not found online. #6 Fine-grained LiDAR sinkholes off Laurie's own parcel DEM — her own QGIS work (see the separate Westerlo_land_mapping package, which already ran this on her 25 acres and found NO karst there — see data/hilltowns_poi_lore_notes.md). #7 NYS Museum karst inventory / USGS SIR 2020-5030 Appendix 1 — not ingested. #8 Post-2012 tornado exact coordinates — would need the row-by-row NCEI lookup, not attempted this pass.
A43: The Folklore doc's lore items (Knox Cave legends, Old Skull bone-chamber, Clarksville wall carvings, Barton Hill "hollow hill") were appended to data/hilltowns_poi_lore_notes.md for the Lore Map — kept OUT of this register per the original project's own convention.
A45: --- 2026-09-21 addendum #2 (Claude, atlas session) ---
... A48: v2 did NOT carry my Knox Cave date fix or the 4 new sources forward — those stay atlas-only unless the original chat is refreshed from here.

Sheet Events
A1: ID | B1: Start date | C1: End date | D1: Year | E1: Century | F1: Category | G1: Event name | H1: Area affected | I1: Key measurement | J1: Station / gauge | K1: Impact summary | L1: Primary source | M1: Source URL | N1: Confidence | O1: Verified this pass | P1: Notes / to-do | Q1: Timeline anchor (ISO) | R1: Anchor year | S1: Anchor month | T1: Anchor day | U1: Date precision | V1: Anchor basis | W1: Show on timeline
A2: 1 | B2: 1635-08-25 | C2: 1635-08-25 | D2: =VALUE(LEFT(B2,4)) | E2: =INT((D2-1)/100)+1 | F2: Tropical cyclone | G2: The Great Colonial Hurricane of 1635 | H2: New England; track inland over W. New England / NY State | I2: Trough of low pressure over W. New England or NY State drove the storm north; forests leveled, hundreds of thousands of trees down | J2: Winthrop & Bradford diaries via Ludlum | K2: The greatest NE hurricane of the colonial period; Mather inferred a well-established low-pressure trough over western New England or NY State. Aug 15 Old Style = Aug 25 New Style. | L2: Ludlum, Early American Hurricanes 1492–1870 (AMS, 1963), pp. 8–23 (verified, page images/text) | M2: https://hdl.handle.net/2027/mdp.39015002912718 | N2: C | O2: Y | P2: Track inland of NY State inferred, not observed at Albany; included as the regional-scale storm-of-record for the 17th c. | Q2: 1635-08-25 | R2: =VALUE(LEFT(Q2,4)) | S2: =VALUE(MID(Q2,6,2)) | T2: =VALUE(RIGHT(Q2,2)) | U2: day | V2: Single-day event
A3: 2 | B3: 1645-11-25 | C3: 1645-11-25 | D3: =VALUE(LEFT(B3,4)) | E3: =INT((D3-1)/100)+1 | F3: Early freeze | G3: Hudson closed at Rensselaerwyck, Nov 25, 1645 | H3: Albany (Rensselaerwyck) | I3: North River closed Nov 25 'and remained frozen very late' | J3: Van der Donck, Description of New Netherland (1656) via Ludlum p. 28 | K3: Earliest dated weather observation for the Albany area in the register; van der Donck notes winters above the Highlands begin earlier and last longer than at New Amsterdam. | L3: Ludlum, Early American Winters I (page screenshots, verified) | N3: B | O3: Y | P3: Old Style date as given. | Q3: 1645-11-25 | R3: =VALUE(LEFT(Q3,4)) | S3: =VALUE(MID(Q3,6,2)) | T3: =VALUE(RIGHT(Q3,2)) | U3: day | V3: Single-day event
A4: 3 | B4: 1667-08-27 | C4: 1667-08-27 | D4: =VALUE(LEFT(B4,4)) | E4: =INT((D4-1)/100)+1 | F4: Tropical cyclone | G4: The Dreadful Hurry Cane of 1667 | H4: Virginia; track inland over the Middle Atlantic; Manhattan Aug 29 | I4: Severe storm at Manhattan Aug 29 (Stokes, Iconography); center inland over N. Virginia then up the seaboard | J4: Strange News from Virginia (1667) via Ludlum | K4: Reached Manhattan; the northern edge likely brushed the lower Hudson. 12 days of rain and flooding followed in VA. | L4: Ludlum, Early American Hurricanes 1492–1870 (AMS, 1963), pp. 8–23 (verified, page images/text) | M4: https://hdl.handle.net/2027/mdp.39015002912718 | N4: C | O4: N | P4: Manhattan hit confirmed; Hudson Valley extent inferred. | Q4: 1667-08-27 | R4: =VALUE(LEFT(Q4,4)) | S4: =VALUE(MID(Q4,6,2)) | T4: =VALUE(RIGHT(Q4,2)) | U4: day | V4: Single-day event
A5: 4 | B5: 1683-08-23 | C5: 1683-08-23 | D5: =VALUE(LEFT(B5,4)) | E5: =INT((D5-1)/100)+1 | F5: Tropical cyclone / flood | G5: Hurricane and Connecticut Valley flood of 1683 | H5: Connecticut Valley / Long Island Sound | I5: Connecticut River rose 26 ft at Wethersfield (Aug 13 Old Style); four river towns (Windsor, Hartford, Wethersfield, Middletown) devastated; corn destroyed | J5: Increase Mather, Remarkable Providences (1684) via Ludlum | K5: Major Connecticut Valley freshet from a hurricane; the closest 17th-c. flood to the register's eastern edge. | L5: Ludlum, Early American Hurricanes 1492–1870 (AMS, 1963), pp. 8–23 (verified, page images/text) | M5: https://hdl.handle.net/2027/mdp.39015002912718 | N5: C | O5: Y | P5: CT Valley, ~east of the register core; Aug 13 O.S. = Aug 23 N.S. | Q5: 1683-08-23 | R5: =VALUE(LEFT(Q5,4)) | S5: =VALUE(MID(Q5,6,2)) | T5: =VALUE(RIGHT(Q5,2)) | U5: day | V5: Single-day event
A6: 5 | B6: 1697-12-01 | C6: 1698-04-15 | D6: =VALUE(LEFT(B6,4)) | E6: =INT((D6-1)/100)+1 | F6: Cold winter | G6: Severest winter in memory, 1697–98 | H6: Albany / Schenectady / New England | I6: Snow 'deeper than the height of a man'; 26 snows at Dorchester | J6: Earl of Bellomont to Board of Trade, 28 Oct 1698, via Ludlum p. 18 | K6: Bellomont: had the winter not been so severe 'the French would certainly have destroyed both Albany and Schenectady' – a planned invasion on 1,500 pairs of snowshoes from Montreal was abandoned. Peter Kalm 50 years later: everyone still called it the coldest ever felt. | L6: Ludlum, Early American Winters I (page screenshots, verified) | N6: B | O6: Y | P6: Season row; a military-history cross-reference for the Hilltowns. | Q6: 1698-02-15 | R6: =VALUE(LEFT(Q6,4)) | S6: =VALUE(MID(Q6,6,2)) | T6: =VALUE(RIGHT(Q6,2)) | U6: season | V6: Mid-winter; Bellomont letter gives no days
A7: 6 | B7: 1705-12-30 | C7: 1706-01-02 | D7: =VALUE(LEFT(B7,4)) | E7: =INT((D7-1)/100)+1 | F7: Arctic outbreak / river ice | G7: Christmas 1705 cold wave – Hudson frozen at NYC | H7: NYC / lower Hudson | I7: 'Coldest that was ever felt here'; Hudson froze over completely and stayed fast several days; severest cold lasted 3 days | J7: Boston News-Letter 21 Jan 1706 via Ludlum pp. 42, 77 | K7: Sloop-of-war grounded off Sandy Hook; 132 crew froze to death. | L7: Ludlum, Early American Winters I (page screenshots, verified) | N7: B | O7: Y | P7: Onset Dec 30 New Style (= Christmas Old Style). | Q7: 1705-12-30 | R7: =VALUE(LEFT(Q7,4)) | S7: =VALUE(MID(Q7,6,2)) | T7: =VALUE(RIGHT(Q7,2)) | U7: days | V7: Multi-day event; anchored to first day
A8: 7 | B8: 1706-10-14 | C8: 1706-10-16 | D8: =VALUE(LEFT(B8,4)) | E8: =INT((D8-1)/100)+1 | F8: Rain flood | G8: October 1706 flood at Albany | H8: Albany / Rensselaer / Connecticut Valley | I8: 'The greatest Flood there that ever was known'; Rensselaers Island 6 ft under water, low lands drowned (Boston News-Letter 28 Oct 1706); CT River flood, ~1000 loads of hay lost | J8: Boston News-Letter, 28 Oct 1706, via Ludlum p. 20 | K8: A DIRECT Albany flood record: mid-October 1706 rain + a hard gale caused the greatest flood then known at Albany. Rare early instrumental-adjacent Albany event. | L8: Ludlum, Early American Hurricanes 1492–1870 (AMS, 1963), pp. 8–23 (verified, page images/text) | M8: https://hdl.handle.net/2027/mdp.39015002912718 | N8: B | O8: Y | P8: Genuine Albany flood-of-record notice for its time; the standout row from this batch. | Q8: 1706-10-14 | R8: =VALUE(LEFT(Q8,4)) | S8: =VALUE(MID(Q8,6,2)) | T8: =VALUE(RIGHT(Q8,2)) | U8: days | V8: Rain Oct 14–16; anchored to first day
A9: 8 | B9: 1717-02-27 | C9: 1717-03-07 | D9: =VALUE(LEFT(B9,4)) | E9: =INT((D9-1)/100)+1 | F9: Snowstorm | G9: The Great Snow of 1717 | H9: New England / Hudson Valley (Philadelphia 'a great snow') | I9: Four storms: Feb 27, Mar 1, Mar 4 ('4 foot deep in ye woods on a level', drifts 10–12 ft), Mar 7; cattle and horses dead in the storm | J9: Hempstead diary (New London), Sewall, Mather via Ludlum pp. 42–43 | K9: Northeasters that also reached Philadelphia (river full of ice); no Albany-specific report in Ludlum. | L9: Ludlum, Early American Winters I (page screenshots, verified) | N9: B | O9: Y | P9: Hudson Valley depth not documented – Annals of Albany may have it. | Q9: 1717-03-07 | R9: =VALUE(LEFT(Q9,4)) | S9: =VALUE(MID(Q9,6,2)) | T9: =VALUE(RIGHT(Q9,2)) | U9: days | V9: Final and heaviest storm of the series
A10: 9 | B10: 1740-11-15 | C10: 1741-04-15 | D10: =VALUE(LEFT(B10,4)) | E10: =INT((D10-1)/100)+1 | F10: Cold winter | G10: Hard Winter of 1740–41 | H10: Hudson Valley / New England | I10: Hudson at NYC shut to navigation twice: after the storm of Dec 28, 1740 until Jan 21, 1741, and again the 2nd–3rd weeks of Feb 1741; Stiles estimated ~−8°F; 27–30 distinct snows; snow 3 ft on the level at Newbury Mar 17; ice held to mid-April | J10: Ludlum pp. 50–53 (Hempstead diary, Coffin, Boston News-Letter) | K10: Winter set in Nov 15 (Newbury); Dec 3 rain for three weeks → biggest CT River flood in 50 years; mid-December 'prodigious storm' with eaves not dripping for 30 days; half the cattle, horses and 2/3 of goats died of scarcity in Connecticut. | L10: Ludlum, Early American Winters I (page screenshots, verified) | N10: B | O10: Y | P10: Now day-anchored. Stiles (1780) judged 1780 snowier than 1740/41. | Q10: 1740-12-28 | R10: =VALUE(LEFT(Q10,4)) | S10: =VALUE(MID(Q10,6,2)) | T10: =VALUE(RIGHT(Q10,2)) | U10: day | V10: Storm that closed the Hudson at NYC
A11: 10 | B11: 1741-02-08 | C11: 1741-02-09 | D11: =VALUE(LEFT(B11,4)) | E11: =INT((D11-1)/100)+1 | F11: Nor'easter | G11: Great NE storm of Feb 8–9, 1741 | H11: Boston / New England | I11: 'Snow higher than has been known since the vast snow of Feb 19, 1716/17' (Boston News-Letter) | J11: Ludlum p. 50 | K11: One of two February 1741 storms singled out by the press. | L11: Ludlum, Early American Winters I (page screenshots, verified) | N11: B | O11: Y | P11: Hudson Valley extent not stated. | Q11: 1741-02-08 | R11: =VALUE(LEFT(Q11,4)) | S11: =VALUE(MID(Q11,6,2)) | T11: =VALUE(RIGHT(Q11,2)) | U11: days | V11: Multi-day event; anchored to first day
A12: 11 | B12: 1741-04-01 | C12: 1741-04-01 | D12: =VALUE(LEFT(B12,4)) | E12: =INT((D12-1)/100)+1 | F12: River ice (late) | G12: Hudson at Esopus bearing loaded teams, April 1, 1741 | H12: Kingston (Esopus) | I12: Loaded teams crossed the Hudson on the ice Apr 1; CT River crossed on horseback Apr 11 | J12: Ludlum p. 52 | K12: Latest documented heavy-load ice crossing of the Hudson in the register; sleighs at Deerfield to Apr 10. | L12: Ludlum, Early American Winters I (page screenshots, verified) | N12: B | O12: Y | P12: Directly relevant to Hudson Valley ice phenology. | Q12: 1741-04-01 | R12: =VALUE(LEFT(Q12,4)) | S12: =VALUE(MID(Q12,6,2)) | T12: =VALUE(RIGHT(Q12,2)) | U12: day | V12: Single-day event
A13: 12 | B13: 1764-12-25 | C13: 1764-12-26 | D13: =VALUE(LEFT(B13,4)) | E13: =INT((D13-1)/100)+1 | F13: Coastal storm | G13: Christmas Night storm of 1764 | H13: Entire Atlantic coast incl. NYC | I13: Began ~2000 Dec 25, snow → rain; Philadelphia 'violent windstorm and snow'; NYC strong wind and much snow | J13: Ludlum pp. 60–61 | K13: Opened the severe winter of 1764–65, 'snowiest since 1748, coldest since 1741'; Delaware clogged with ice. | L13: Ludlum, Early American Winters I (page screenshots, verified) | N13: B | O13: Y | Q13: 1764-12-25 | R13: =VALUE(LEFT(Q13,4)) | S13: =VALUE(MID(Q13,6,2)) | T13: =VALUE(RIGHT(Q13,2)) | U13: days | V13: Multi-day event; anchored to first day
A14: 13 | B14: 1765-01-26 | C14: 1765-01-28 | D14: =VALUE(LEFT(B14,4)) | E14: =INT((D14-1)/100)+1 | F14: Arctic outbreak / river ice | G14: January 1765 deep freeze – Hudson nearly solid at NYC | H14: NYC / lower Hudson | I14: Kings College thermometer at or below zero 57 hours until 1400 Jan 28, est. low −6°F; Hudson froze 'almost solid' to the Jersey shore; NYC Feb 11: 'six weeks in Greenland, ground covered near three feet' | J14: Ludlum p. 61 (Watts letter book) | K14: Longest sub-zero spell in NYC history if authentic; a traveller walking to Jersey fell through 350 yd from shore. | L14: Ludlum, Early American Winters I (page screenshots, verified) | N14: B | O14: Y | Q14: 1765-01-26 | R14: =VALUE(LEFT(Q14,4)) | S14: =VALUE(MID(Q14,6,2)) | T14: =VALUE(RIGHT(Q14,2)) | U14: days | V14: Multi-day event; anchored to first day
A15: 14 | B15: 1769-09-08 | C15: 1769-09-08 | D15: =VALUE(LEFT(B15,4)) | E15: =INT((D15-1)/100)+1 | F15: Tropical cyclone | G15: September 1769 hurricane – NYC & Hudson Valley | H15: NYC / New Brunswick NJ / lower Hudson | I15: NYC swept by a violent NE gale continuing past 2000, trees torn up and corn damaged; New Brunswick NJ severe (trees down, bridges carried away) | J15: Ludlum p. 25 (Va. Gaz. & press) | K15: Center tracked up Chesapeake Bay and through eastern PA; the NE edge raked NYC and the lower Hudson. | L15: Ludlum, Early American Hurricanes 1492–1870 (AMS, 1963), pp. 24–40 (verified, page images) | M15: https://hdl.handle.net/2027/mdp.39015002912718 | N15: C | O15: N | P15: NYC hit confirmed; upper-Hudson extent not documented. | Q15: 1769-09-08 | R15: =VALUE(LEFT(Q15,4)) | S15: =VALUE(MID(Q15,6,2)) | T15: =VALUE(RIGHT(Q15,2)) | U15: day | V15: Single-day event
A16: 15 | B16: 1775-09-03 | C16: 1775-09-03 | D16: =VALUE(LEFT(B16,4)) | E16: =INT((D16-1)/100)+1 | F16: Tropical cyclone | G16: The Independence Hurricane of 1775 | H16: Chesapeake / eastern PA; NE edge to NY | I16: Deadliest colonial hurricane (NC to Newfoundland); center up Chesapeake Bay then eastern PA (Hazel-1954 analog) | J16: Ludlum pp. 26–27 | K16: Track inland; the register keeps it as a major regional-adjacent storm. NY-specific damage not documented in these pages. | L16: Ludlum, Early American Hurricanes 1492–1870 (AMS, 1963), pp. 24–40 (verified, page images) | M16: https://hdl.handle.net/2027/mdp.39015002912718 | N16: C | O16: N | P16: Included for scale; no direct NY report. | Q16: 1775-09-03 | R16: =VALUE(LEFT(Q16,4)) | S16: =VALUE(MID(Q16,6,2)) | T16: =VALUE(RIGHT(Q16,2)) | U16: day | V16: Single-day event
A17: 16 | B17: 1775-12-24 | C17: 1775-12-24 | D17: =VALUE(LEFT(B17,4)) | E17: =INT((D17-1)/100)+1 | F17: Snowstorm | G17: Christmas Eve snowstorm 1775 – Knox's cannon train | H17: Albany / upper Hudson | I17: Knox reported a snowfall of two feet by Christmas Day; extreme cold and NW wind Dec 21; same storm system as the Carolina 'Snow Campaign' of Dec 23–25 | J17: Ludlum pp. 96, 147 (Knox letters) | K17: Knox sledded Ticonderoga's guns south along the Hudson; needed to cross the river four times between Lake George and Albany. | L17: Ludlum, Early American Winters I (page screenshots, verified) | N17: B | O17: Y | Q17: 1775-12-24 | R17: =VALUE(LEFT(Q17,4)) | S17: =VALUE(MID(Q17,6,2)) | T17: =VALUE(RIGHT(Q17,2)) | U17: day | V17: Single-day event
A18: 17 | B18: 1776-01-05 | C18: 1776-01-10 | D18: =VALUE(LEFT(B18,4)) | E18: =INT((D18-1)/100)+1 | F18: Thaw then freeze | G18: January 1776 thaw at Albany – Knox delayed, then Hudson bears the guns | H18: Albany / Claverack | I18: Jan 5: 'a cruel thaw hinders from crossing the Hudson'; near-continuous freezing from Jan 10 let the caravan cross and move east via Claverack over the Berkshires (Route 23) | J18: Ludlum pp. 96–97 (Knox to Washington, 5 Jan 1776) | K18: Framingham reached Jan 25; the artillery drove the British out of Boston Mar 17. | L18: Ludlum, Early American Winters I (page screenshots, verified) | N18: B | O18: Y | Q18: 1776-01-05 | R18: =VALUE(LEFT(Q18,4)) | S18: =VALUE(MID(Q18,6,2)) | T18: =VALUE(RIGHT(Q18,2)) | U18: days | V18: Multi-day event; anchored to first day
A19: 18 | B19: 1780-01-02 | C19: 1780-01-04 | D19: =VALUE(LEFT(B19,4)) | E19: =INT((D19-1)/100)+1 | F19: Blizzard | G19: Great Snowstorm of January 1780 (Hard Winter) | H19: NJ / Hudson Valley / New England | I19: 12 in at New Haven Jan 2–3 (Atwater); Washington Jan 6: 'eighteen inches, much drifted, roads impassable'; 42–48 in on the ground in S. CT after the 10-day series; drifts 6–12 ft | J19: Ludlum pp. 114–115 | K19: Second of three great storms (Dec 27–28, Jan 2–3, Jan 10); Stiles: more snow than the hard winter of 1740/41. | L19: Ludlum, Early American Winters I (page screenshots, verified) | M19: https://www.nps.gov/morr/learn/historyculture/hard-winter-news.htm | N19: B | O19: Y | P19: Ludlum: Jan 1780 = most persistently cold month in eastern US history. | Q19: 1780-01-02 | R19: =VALUE(LEFT(Q19,4)) | S19: =VALUE(MID(Q19,6,2)) | T19: =VALUE(RIGHT(Q19,2)) | U19: days | V19: Multi-day event; anchored to first day
A20: 19 | B20: 1780-01-07 | C20: 1780-02-21 | D20: =VALUE(LEFT(B20,4)) | E20: =INT((D20-1)/100)+1 | F20: Cold winter | G20: Hard Winter of 1779–80 – Hudson and harbor frozen | H20: Hudson Valley / NY Harbor | I20: Navigation stopped by ice Jan 7; East River on foot by Jan 14; Hudson on foot Jan 16–20; Staten Island→Manhattan on foot Jan 29; sleighs Feb 1; 86 sleighs with provisions Feb 6; thaw began Feb 11; ice rotting Feb 15; boats through the Narrows Feb 20, docks Feb 21 | J20: Hugh Gaine diary via Ludlum p. 115; Smith & Dohla diaries | K20: Only winter on record with NY waters closed to navigation for weeks; cannon dragged across to Staten Island. | L20: Ludlum, Early American Winters I (page screenshots, verified) | M20: https://www.nps.gov/morr/learn/historyculture/hard-winter-news.htm | N20: B | O20: Y | P20: Day-level chronology now complete for NYC; no Albany-specific dates yet. | Q20: 1780-01-16 | R20: =VALUE(LEFT(Q20,4)) | S20: =VALUE(MID(Q20,6,2)) | T20: =VALUE(RIGHT(Q20,2)) | U20: day | V20: Hudson first walked across at NYC (William Smith diary)
A21: 20 | B21: 1780-01-29 | C21: 1780-01-29 | D21: =VALUE(LEFT(B21,4)) | E21: =INT((D21-1)/100)+1 | F21: Arctic outbreak | G21: Nadir of the Hard Winter – Jan 29, 1780 | H21: Northeast | I21: Sunrise: Hartford −20°F (some sources −22°), Salem −17°F, NYC −16°F (unverified), ALBANY −20°F (Stiles, date not given) | J21: Ludlum pp. 79, 115 (Hartford sunrise table; Stiles register) | K21: Coldest morning of the coldest month on record; five consecutive sub-zero sunrises at Hartford Jan 25–29. | L21: Ludlum, Early American Winters I (page screenshots, verified) | N21: B | O21: Y | Q21: 1780-01-29 | R21: =VALUE(LEFT(Q21,4)) | S21: =VALUE(MID(Q21,6,2)) | T21: =VALUE(RIGHT(Q21,2)) | U21: day | V21: Single-day event
A22: 21 | B22: 1780-11-01 | C22: 1780-11-11 | D22: =VALUE(LEFT(B22,4)) | E22: =INT((D22-1)/100)+1 | F22: Early freeze | G22: Early freeze-up of the Hudson at Albany, Nov 1780 | H22: Albany / Middle States | I22: Deep snow Nov 1 over the Middle States; Hudson frozen at Albany Nov 11 – 'an unusually early date' | J22: Ludlum p. 134 (E. Stiles diary) | K22: Earliest documented freeze-up of the Hudson at Albany in the register. | L22: Ludlum, Early American Winters I (page screenshots, verified) | N22: B | O22: Y | Q22: 1780-11-11 | R22: =VALUE(LEFT(Q22,4)) | S22: =VALUE(MID(Q22,6,2)) | T22: =VALUE(RIGHT(Q22,2)) | U22: day | V22: Freeze-up date at Albany
A23: 22 | B23: 1781-01-22 | C23: 1781-01-23 | D23: =VALUE(LEFT(B23,4)) | E23: =INT((D23-1)/100)+1 | F23: Coastal storm / wind | G23: Great coastal storm of January 1781 | H23: NYC / Hudson Valley / New England | I23: NYC: heavy rain then snow, ~9 in; chimneys and trees blown down, people killed by falling chimneys; 'severest that has been felt here for many years' | J23: Ludlum pp. 134–135 (F. Mackenzie diary) | K23: Four naval vessels wrecked at Gardiners Island; 74-gun ship lost at Newport; prodigious inland snow (8 ft on the level claimed in NE Connecticut, unconfirmed). | L23: Ludlum, Early American Winters I (page screenshots, verified) | N23: B | O23: Y | Q23: 1781-01-22 | R23: =VALUE(LEFT(Q23,4)) | S23: =VALUE(MID(Q23,6,2)) | T23: =VALUE(RIGHT(Q23,2)) | U23: days | V23: Multi-day event; anchored to first day
A24: 23 | B24: 1783-10-18 | C24: 1783-10-19 | D24: =VALUE(LEFT(B24,4)) | E24: =INT((D24-1)/100)+1 | F24: Tropical remnant / snow / flood | G24: October 1783 storms – NY & New England | H24: New Brunswick NJ / New Haven / Goshen CT / VT | I24: 2nd of the Oct 1783 storms: mid-Oct snowfall to the shores of LI Sound; snow in Goshen CT and adjacent towns; VT height-of-land 6–8 in; Windsor VT 'greatest flood ever known since settlement' Oct 22 | J24: Ludlum p. 29 (Penna. papers, Vt. Journal) | K24: A cold-air-charged coastal storm that put snow on the CT Valley hills and caused the worst VT flood to that date; the Helderbergs likely saw the same snow. | L24: Ludlum, Early American Hurricanes 1492–1870 (AMS, 1963), pp. 24–40 (verified, page images) | M24: https://hdl.handle.net/2027/mdp.39015002912718 | N24: C | O24: Y | P24: Snow reached LI Sound hills; western extent (Helderbergs) inferred. | Q24: 1783-10-18 | R24: =VALUE(LEFT(Q24,4)) | S24: =VALUE(MID(Q24,6,2)) | T24: =VALUE(RIGHT(Q24,2)) | U24: days | V24: Second storm Oct 18–19; anchored to first day
A25: 24 | B25: 1783-12-30 | C25: 1783-12-31 | D25: =VALUE(LEFT(B25,4)) | E25: =INT((D25-1)/100)+1 | F25: Coastal storm | G25: Year-end storm of 1783 (Long Winter) | H25: NJ / NYC / Hudson Valley | I25: 20 in at Morristown Dec 30–31 'almost the same date as four years earlier'; Trappe PA 'uncommonly deep' | J25: Ludlum p. 65 (Joseph Lewis diary) | K25: Opened the Long Winter of 1783–84; greatest seasonal snowfall known in northern NJ. | L25: Ludlum, Early American Winters I (page screenshots, verified) | N25: B | O25: Y | Q25: 1783-12-30 | R25: =VALUE(LEFT(Q25,4)) | S25: =VALUE(MID(Q25,6,2)) | T25: =VALUE(RIGHT(Q25,2)) | U25: days | V25: Multi-day event; anchored to first day
A26: 25 | B26: 1784-02-10 | C26: 1784-02-17 | D26: =VALUE(LEFT(B26,4)) | E26: =INT((D26-1)/100)+1 | F26: Arctic outbreak | G26: February 1784 cold – the Long Winter | H26: Interior New England / NYC | I26: Hartford ≤ −12°F on 8 consecutive mornings Feb 10–17 (−20° Feb 14); New Haven −10° Feb 10; the Narrows choked with ice; Baltimore closed Jan 2–Mar 25, 16 days longer than 1780 | J26: Ludlum p. 65 (Webster / Amer. Jour. Sci.) | K26: Longest spell of sub-zero readings on record in southern New England; 1784 remembered by mariners as their toughest ice season. | L26: Ludlum, Early American Winters I (page screenshots, verified) | N26: B | O26: Y | P26: Albany value not given; likely colder. | Q26: 1784-02-10 | R26: =VALUE(LEFT(Q26,4)) | S26: =VALUE(MID(Q26,6,2)) | T26: =VALUE(RIGHT(Q26,2)) | U26: days | V26: Multi-day event; anchored to first day
A27: 26 | B27: 1788-08-19 | C27: 1788-08-19 | D27: =VALUE(LEFT(B27,4)) | E27: =INT((D27-1)/100)+1 | F27: Tropical cyclone / severe wind | G27: The Hurricane of August 19, 1788 – over the Hudson Highlands | H27: Hudson River highlands (Bear Mtn) / Berkshires / Hillsdale, Columbia Co. / Hudson / Poughkeepsie | I27: Small, fast (~45 mph) intense storm; ~50-mi-wide path of 75+ mph winds tracked over the Hudson River highlands near Bear Mountain into the Berkshires; Hillsdale NY first-hand account of a violent NW hurricane, streams to torrents, pines crushing houses; Poughkeepsie oaks down, creeks took bridges; Hudson 48-hr flood, mills carried off between Hudson and Albany | J27: Ludlum pp. 30–34 (Hudson Weekly Gazette, Country Journal, Daily Adv.) | K27: The most directly relevant early storm in the whole volume: its damage swath ran up the Hudson through Columbia and Dutchess counties. Reached to within the register's core. Ludlum debates hurricane vs. tornado vs. squall line and concludes hurricane. | L27: Ludlum, Early American Hurricanes 1492–1870 (AMS, 1963), pp. 24–40 (verified, page images) | M27: https://hdl.handle.net/2027/mdp.39015002912718 | N27: B | O27: Y | P27: Hillsdale (Columbia Co.) is ~20 mi from Westerlo; Hudson & Poughkeepsie flooding documented. Standout row from this batch. | Q27: 1788-08-19 | R27: =VALUE(LEFT(Q27,4)) | S27: =VALUE(MID(Q27,6,2)) | T27: =VALUE(RIGHT(Q27,2)) | U27: day | V27: Single-day event
A28: 27 | B28: 1789-01-30 | C28: 1789-02-02 | D28: =VALUE(LEFT(B28,4)) | E28: =INT((D28-1)/100)+1 | F28: Arctic outbreak | G28: February 2, 1789 – Albany's earliest instrumental extreme | H28: Albany / Hartford / New Haven | I28: Albany −24°F Feb 2, 'colder by 6° than ever known' (weather book at the museum opposite Denniston's tavern, Green Street); Hartford −28°F, 4° below anything known; snow half a foot Jan 30 | J28: The Annual Register (Albany, 1849) p. 329, via Ludlum p. 79 | K28: Earliest dated thermometer reading for Albany in the register; Stiles notes it as one of three notable cold days of his lifetime (Feb 5). | L28: Ludlum, Early American Winters I (page screenshots, verified) | N28: B | O28: Y | P28: Albany had a thermometer by Jan 1772. NB: the 42-year freeze notice (Amer. Quar. Jour. 1845) is headed 'From the Albany Daily Advertiser', not the New York Daily Advertiser as Ludlum's footnote says. | Q28: 1789-01-30 | R28: =VALUE(LEFT(Q28,4)) | S28: =VALUE(MID(Q28,6,2)) | T28: =VALUE(RIGHT(Q28,2)) | U28: days | V28: Multi-day event; anchored to first day
A29: 28 | B29: 1795-08-03 | C29: 1795-08-03 | D29: =VALUE(LEFT(B29,4)) | E29: =INT((D29-1)/100)+1 | F29: Tropical cyclone | G29: August 1795 storm – NYC fringe | H29: NYC / lower Hudson | I29: Henry Laight, NYC: 'a very heavy gale of wind and a great deal of rain from the East' Aug 3 | J29: Ludlum p. 34 (Laight Ms.) | K29: Twin NC hurricanes; only the northern fringe reached NYC. Minor for the region. | L29: Ludlum, Early American Hurricanes 1492–1870 (AMS, 1963), pp. 24–40 (verified, page images) | M29: https://hdl.handle.net/2027/mdp.39015002912718 | N29: C | O29: N | P29: NYC fringe only. | Q29: 1795-08-03 | R29: =VALUE(LEFT(Q29,4)) | S29: =VALUE(MID(Q29,6,2)) | T29: =VALUE(RIGHT(Q29,2)) | U29: day | V29: Single-day event
A30: 29 | B30: 1796-11-28 | C30: 1797-01-12 | D30: =VALUE(LEFT(B30,4)) | E30: =INT((D30-1)/100)+1 | F30: Cold winter | G30: Early severe winter 1796–97 | H30: Albany | I30: River closed Nov 28; intensely cold Dec 23–24, mercury at zero AM | J30: Albany freeze notice | K30: Early hard winter, severe to mid-January. | L30: Albany Daily Advertiser, "Notices of the Winters at New York for the last forty-two years… dates at which the Hudson was frozen or obstructed or closed by ice at Albany," repr. American Quarterly Journal of Agriculture and Science 1 (1845) pp. 347–350 (verified, page images) | M30: https://archive.org/details/americanquarterl00slsn | N30: B | O30: Y | Q30: 1796-12-20 | R30: =VALUE(LEFT(Q30,4)) | S30: =VALUE(MID(Q30,6,2)) | T30: =VALUE(RIGHT(Q30,2)) | U30: month | V30: Anchored to mid-point of a multi-week window
A31: 30 | B31: 1797-11-23 | C31: 1798-02-28 | D31: =VALUE(LEFT(B31,4)) | E31: =INT((D31-1)/100)+1 | F31: Cold winter | G31: Long severe winter 1797–98 | H31: Albany | I31: River closed Nov 23; lowest 2°F above zero | J31: Albany freeze notice | K31: Very early, long and severe; brief January thaw. | L31: Albany Daily Advertiser, "Notices of the Winters at New York for the last forty-two years… dates at which the Hudson was frozen or obstructed or closed by ice at Albany," repr. American Quarterly Journal of Agriculture and Science 1 (1845) pp. 347–350 (verified, page images) | M31: https://archive.org/details/americanquarterl00slsn | N31: B | O31: Y | Q31: 1798-01-10 | R31: =VALUE(LEFT(Q31,4)) | S31: =VALUE(MID(Q31,6,2)) | T31: =VALUE(RIGHT(Q31,2)) | U31: season | V31: Anchored to mid-point of a season-scale window
A32: 31 | B32: 1800-01-01 | C32: 2026-12-31 | D32: =VALUE(LEFT(B32,4)) | E32: =INT((D32-1)/100)+1 | F32: Sinkhole / karst | G32: Helderberg–Cobleskill karst (standing hazard) | H32: Knox, Berne, Clarksville, Cobleskill plateau | I32: Largest karst drainage in the Northeast; Cobleskill Creek loses most flow underground where it crosses the Coeymans Limestone | J32: none | K32: Context row: sinkholes and swallets are a permanent feature of the plateau; discrete collapse events are rarely reported. | L32: NYSGA 1991 field guide | M32: https://www.nysga-online.org/wp-content/uploads/2019/06/NYSGA-1991-A6-Interaction-Between-Karst-and-Glaciation-in-the-Helderberg-Plateau-Schoharie-and-Albany-Counties-New-York.pdf | N32: B | O32: Y | P32: Context row, not an event. | Q32: 1975-05-15 | R32: =VALUE(LEFT(Q32,4)) | S32: =VALUE(MID(Q32,6,2)) | T32: =VALUE(RIGHT(Q32,2)) | U32: year | V32: Context row – do not plot as a point
A33: 32 | B33: 1801-12-01 | C33: 1802-01-31 | D33: =VALUE(LEFT(B33,4)) | E33: =INT((D33-1)/100)+1 | F33: Mild winter | G33: Open winter of 1801–02 | H33: Albany / New Haven | I33: At Albany no ice on the Hudson strong enough to bear a team; only 1.25 in snow Dec–Jan; violets blooming at New Haven in January | J33: Ludlum p. 165 | K33: Least wintry season since the Revolution – a useful counter-example for the timeline. | L33: Ludlum, Early American Winters I (page screenshots, verified) | N33: B | O33: Y | Q33: 1802-01-15 | R33: =VALUE(LEFT(Q33,4)) | S33: =VALUE(MID(Q33,6,2)) | T33: =VALUE(RIGHT(Q33,2)) | U33: season | V33: Mid-winter; counter-example row
A34: 33 | B34: 1802-02-22 | C34: 1802-02-24 | D34: =VALUE(LEFT(B34,4)) | E34: =INT((D34-1)/100)+1 | F34: Nor'easter | G34: Great coastal storm and deep snow of Feb 1802 | H34: Hudson Valley / New England | I34: Snow reached Poughkeepsie 0400 and Albany just before daybreak Feb 22; 4+ ft at Rutland MA, 3.5 ft at Worcester; drifts 6–10 ft at Portsmouth | J34: Ludlum pp. 165–166 (Annals of Albany 3, 319) | K34: Dwight rated it equal to the 1717 storms; three East-Indiamen wrecked at Cape Cod, 9 dead. | L34: Ludlum, Early American Winters I (page screenshots, verified) | N34: B | O34: Y | P34: Albany depth not given – Annals of Albany vol. 3 p. 319 has it. | Q34: 1802-02-22 | R34: =VALUE(LEFT(Q34,4)) | S34: =VALUE(MID(Q34,6,2)) | T34: =VALUE(RIGHT(Q34,2)) | U34: days | V34: Multi-day event; anchored to first day
A35: 34 | B35: 1803-05-06 | C35: 1803-05-08 | D35: =VALUE(LEFT(B35,4)) | E35: =INT((D35-1)/100)+1 | F35: Late-season snow / frost | G35: May 1803 snow and frost | H35: Hudson (Columbia Co.) / Poughkeepsie / cut-off near Albany | I35: Hudson: severe frost Fri night May 6, 'considerable fall of snow' Sun May 8; Poughkeepsie: several inches, sleighs in the streets; snow canopy did not reach northern NY | J35: Ludlum p. 167 (The Balance, Hudson, 10 May 1803) | K35: First measurable May snow at seaboard locations since 1774; trees in leaf, apple in blossom. | L35: Ludlum, Early American Winters I (page screenshots, verified) | N35: B | O35: Y | P35: Cut-off line 'close to Albany' – Helderbergs almost certainly had snow. | Q35: 1803-05-06 | R35: =VALUE(LEFT(Q35,4)) | S35: =VALUE(MID(Q35,6,2)) | T35: =VALUE(RIGHT(Q35,2)) | U35: days | V35: Multi-day event; anchored to first day
A36: 35 | B36: 1804-02-23 | C36: 1804-03-05 | D36: =VALUE(LEFT(B36,4)) | E36: =INT((D36-1)/100)+1 | F36: Snowstorms | G36: Three snowstorms in one week – late winter 1804 | H36: Hudson Valley / Albany / New England | I36: Around Albany snow lay 3 ft on the level March 5; Hudson (Balance): average depth 'upwards of two feet' after the Fri Mar 2 storm; three mails overdue from NYC | J36: Ludlum pp. 168–169 (Annals of Albany 3, 327; Hudson Balance 6 Mar 1804) | K36: 'More snow than since 1780'; fodder scarce after the previous summer's drought and many cattle died in the interior. | L36: Ludlum, Early American Winters I (page screenshots, verified) | N36: B | O36: Y | Q36: 1804-03-02 | R36: =VALUE(LEFT(Q36,4)) | S36: =VALUE(MID(Q36,6,2)) | T36: =VALUE(RIGHT(Q36,2)) | U36: day | V36: Friday storm reported by the Hudson Balance
A37: 36 | B37: 1804-10-09 | C37: 1804-10-09 | D37: =VALUE(LEFT(B37,4)) | E37: =INT((D37-1)/100)+1 | F37: Tropical cyclone / early snow | G37: New England's Snow Hurricane of 1804 (full account) | H37: NYC / Poughkeepsie / Hudson / Catskills / Berkshires | I37: Center passed just W of NYC, S of Poughkeepsie; Hudson Valley lashed at Poughkeepsie & Hudson (main force from the N, 'violence not experienced since settlement'); leaf-on snow: Catskills up to 18 in, Berkshires 24–30 in, Goshen CT 12 in; heavy snow + hurricane wind wrecked orchards and sugar groves | J37: Ludlum pp. 35–38 (NY Post, Md. Gaz., Vt. Journal) | K37: This is the FULL account of the 1804 Snow Hurricane the register already listed. Confirms Catskill 18-inch leaf-on snow and severe Hudson Valley wind. Upgrades the existing row's detail. | L37: Ludlum, Early American Hurricanes 1492–1870 (AMS, 1963), pp. 24–40 (verified, page images) | M37: https://hdl.handle.net/2027/mdp.39015002912718 | N37: A | O37: Y | P37: Supersedes/enriches the existing 1804 Snow Hurricane row; Catskills & Hudson Valley directly documented. | Q37: 1804-10-09 | R37: =VALUE(LEFT(Q37,4)) | S37: =VALUE(MID(Q37,6,2)) | T37: =VALUE(RIGHT(Q37,2)) | U37: day | V37: Single-day event
A38: 37 | B38: 1804-12-13 | C38: 1805-03-01 | D38: =VALUE(LEFT(B38,4)) | E38: =INT((D38-1)/100)+1 | F38: Cold winter | G38: Severe winter 1804–05 at Albany | H38: Albany | I38: River closed Dec 13; lowest 2°F above zero; deep snows, heavy rains, high winds; 'much distress among the poor' | J38: Albany freeze notice | K38: Confirms the Albany side of the 1805 severe winter (register already had the NYC 48-hr snow). | L38: Albany Daily Advertiser, "Notices of the Winters at New York for the last forty-two years… dates at which the Hudson was frozen or obstructed or closed by ice at Albany," repr. American Quarterly Journal of Agriculture and Science 1 (1845) pp. 347–350 (verified, page images) | M38: https://archive.org/details/americanquarterl00slsn | N38: B | O38: Y | Q38: 1805-01-21 | R38: =VALUE(LEFT(Q38,4)) | S38: =VALUE(MID(Q38,6,2)) | T38: =VALUE(RIGHT(Q38,2)) | U38: season | V38: Anchored to mid-point of a season-scale window
A39: 38 | B39: 1805-01-22 | C39: 1805-01-23 | D39: =VALUE(LEFT(B39,4)) | E39: =INT((D39-1)/100)+1 | F39: Cold snap / river ice | G39: Hudson crossed on foot at NYC, Jan 1805 | H39: NYC / lower Hudson | I39: Extreme cold Jan 22 (wood $8/load); 'several persons crossed the Hudson from the State Prison to Hoboken' Jan 22–23 | J39: Ludlum p. 171 (Henry Laight notes) | K39: Winter 1804–05 'the most rigorous as a whole since 1780'. | L39: Ludlum, Early American Winters I (page screenshots, verified) | N39: B | O39: Y | Q39: 1805-01-22 | R39: =VALUE(LEFT(Q39,4)) | S39: =VALUE(MID(Q39,6,2)) | T39: =VALUE(RIGHT(Q39,2)) | U39: days | V39: Multi-day event; anchored to first day
A40: 39 | B40: 1805-01-26 | C40: 1805-01-28 | D40: =VALUE(LEFT(B40,4)) | E40: =INT((D40-1)/100)+1 | F40: Snowstorm | G40: The 48-hour snow at New York, Jan 1805 | H40: NYC / lower Hudson | I40: 20–24 in on top of existing cover; snow Jan 26 evening → Jan 28 evening without interruption; Jan 1805 snowiest month of early record at NYC | J40: Ludlum pp. 170–172 | K40: Streets impassable even for sleighs; Jan 1805 snow 'about three feet deep' (Webster). | L40: Ludlum, Early American Winters I (page screenshots, verified) | N40: B | O40: Y | Q40: 1805-01-26 | R40: =VALUE(LEFT(Q40,4)) | S40: =VALUE(MID(Q40,6,2)) | T40: =VALUE(RIGHT(Q40,2)) | U40: days | V40: Multi-day event; anchored to first day
A41: 40 | B41: 1806-08-23 | C41: 1806-08-23 | D41: =VALUE(LEFT(B41,4)) | E41: =INT((D41-1)/100)+1 | F41: Tropical cyclone | G41: The Great Coastal Hurricane of 1806 – NYC fringe | H41: NYC / Belleville NJ | I41: NYC: NE gale Sat–Sun then NNW, heavy incessant rain, gale till dark; mostly a fringe lashing | J41: Ludlum p. 39 (NY press) | K41: Storm stayed largely offshore; NYC got the western fringe. Rose in Bloom wreck (21 dead) off Barnegat NJ. | L41: Ludlum, Early American Hurricanes 1492–1870 (AMS, 1963), pp. 24–40 (verified, page images) | M41: https://hdl.handle.net/2027/mdp.39015002912718 | N41: C | O41: N | P41: NYC fringe; lower Hudson only. | Q41: 1806-08-23 | R41: =VALUE(LEFT(Q41,4)) | S41: =VALUE(MID(Q41,6,2)) | T41: =VALUE(RIGHT(Q41,2)) | U41: day | V41: Single-day event
A42: 41 | B42: 1807-03-30 | C42: 1807-03-31 | D42: =VALUE(LEFT(B42,4)) | E42: =INT((D42-1)/100)+1 | F42: Late-season snowstorm | G42: End-of-March snowstorm of 1807 | H42: Mississippi Valley to New England; excessive on the hills of western/central NY | I42: 5 ft of snow about Annsville, Oneida Co., Apr 1; 4.5 ft compact snow in the forests Apr 7; St. Lawrence Co. spring 'especially backward'; ice in the Niagara River Jun 4 | J42: Ludlum pp. 230–231 (Pomroy Jones, Annals of Oneida Co.) | K42: Third major event of a long 1806–07 winter; opened a run of cold summers (1807, 1812, 1816) in NY. | L42: Ludlum, Early American Winters I (page screenshots, verified) | N42: B | O42: Y | P42: Hudson Valley depth not given; likely 1–3 ft on the Helderbergs. | Q42: 1807-03-30 | R42: =VALUE(LEFT(Q42,4)) | S42: =VALUE(MID(Q42,6,2)) | T42: =VALUE(RIGHT(Q42,2)) | U42: days | V42: Multi-day event; anchored to first day
A43: 42 | B43: 1810-01-19 | C43: 1810-01-19 | D43: =VALUE(LEFT(B43,4)) | E43: =INT((D43-1)/100)+1 | F43: Cold snap | G43: Cold Friday | H43: New England / eastern NY | I43: ~60°F drop in hours with gale (chronicle) | J43: none | K43: Sudden flash freeze; deaths of travelers and livestock. | L43: Ludlum, Early American Winters I & II / Early American Hurricanes (AMS) – chronicle sources | N43: C | O43: N | Q43: 1810-01-19 | R43: =VALUE(LEFT(Q43,4)) | S43: =VALUE(MID(Q43,6,2)) | T43: =VALUE(RIGHT(Q43,2)) | U43: day | V43: Single-day event
A44: 43 | B44: 1813-12-01 | C44: 1814-02-28 | D44: =VALUE(LEFT(B44,4)) | E44: =INT((D44-1)/100)+1 | F44: Mild winter | G44: Mild winter of 1813–14 | H44: Albany / Champlain Valley | I44: Albany winter minimum only −6°F (Dr. Eights); Middlebury −12°F Jan 31 | J44: Ludlum p. 236 | K44: Counter-example: a mild wartime winter. | L44: Ludlum, Early American Winters I (page screenshots, verified) | N44: B | O44: Y | Q44: 1814-01-31 | R44: =VALUE(LEFT(Q44,4)) | S44: =VALUE(MID(Q44,6,2)) | T44: =VALUE(RIGHT(Q44,2)) | U44: day | V44: Season minimum date at Middlebury
A45: 44 | B45: 1814-12-20 | C45: 1814-12-21 | D45: =VALUE(LEFT(B45,4)) | E45: =INT((D45-1)/100)+1 | F45: Arctic outbreak | G45: December 1814 cold wave | H45: Albany / Champlain | I45: Arctic air Dec 20; Albany December low +2°F; Middlebury −6°F Dec 21 | J45: Ludlum p. 236 | K45: Lake Champlain froze, raising fears of a British attack on the fleet at Whitehall over the ice. | L45: Ludlum, Early American Winters I (page screenshots, verified) | N45: B | O45: Y | Q45: 1814-12-20 | R45: =VALUE(LEFT(Q45,4)) | S45: =VALUE(MID(Q45,6,2)) | T45: =VALUE(RIGHT(Q45,2)) | U45: days | V45: Multi-day event; anchored to first day
A46: 45 | B46: 1815-01-31 | C46: 1815-02-01 | D46: =VALUE(LEFT(B46,4)) | E46: =INT((D46-1)/100)+1 | F46: Arctic outbreak | G46: The severe cold of Jan 31, 1815 | H46: NYC / New England | I46: Salem −9°F; Portsmouth −13°F; Brunswick ME −24°F; Nantucket −11°F; NYC icebound – Hudson and East River choked with ice, southern mail boat sank Jan 30, navigation resumed mid-Feb | J46: Ludlum pp. 188–189 | K46: Coldest day at Salem since records began 1786. | L46: Ludlum, Early American Winters I (page screenshots, verified) | N46: B | O46: Y | P46: Albany value not in these pages. | Q46: 1815-01-31 | R46: =VALUE(LEFT(Q46,4)) | S46: =VALUE(MID(Q46,6,2)) | T46: =VALUE(RIGHT(Q46,2)) | U46: days | V46: Multi-day event; anchored to first day
A47: 46 | B47: 1815-09-23 | C47: 1815-09-23 | D47: =VALUE(LEFT(B47,4)) | E47: =INT((D47-1)/100)+1 | F47: Tropical cyclone | G47: The Great September Gale of 1815 | H47: Southern New England; W. edge to eastern NY | I47: Center cut southern New England in two, up eastern CT / central MA / NH; line of heavy-damage demarcation at Brimfield MA (between Springfield and Worcester) | J47: Ludlum pp. 77–96 (Webster diary, Darling timetable) | K47: The most powerful NE storm between 1635 and 1938. Its damage line ran through central MA, WEST of the register core; eastern NY on the storm's fringe. | L47: Ludlum, Early American Hurricanes 1492–1870 (AMS, 1963), pp. 77–108 (verified, page images) | M47: https://hdl.handle.net/2027/mdp.39015002912718 | N47: C | O47: Y | P47: Included as the era's benchmark; direct Hudson Valley damage not documented — the severe swath stayed east of Albany. | Q47: 1815-09-23 | R47: =VALUE(LEFT(Q47,4)) | S47: =VALUE(MID(Q47,6,2)) | T47: =VALUE(RIGHT(Q47,2)) | U47: day | V47: Single-day event
A48: 47 | B48: 1816-05-12 | C48: 1816-05-14 | D48: =VALUE(LEFT(B48,4)) | E48: =INT((D48-1)/100)+1 | F48: Late frost | G48: 1816 – May frost (Year Without a Summer, episode 1) | H48: Upstate NY / New England | I48: Hard freeze; inch-thick ice on ponds (chronicle) | J48: none | K48: Killed fruit-tree buds; early crops lost. | L48: Ludlum, Early American Winters I & II / Early American Hurricanes (AMS) – chronicle sources | N48: B | O48: N | Q48: 1816-05-12 | R48: =VALUE(LEFT(Q48,4)) | S48: =VALUE(MID(Q48,6,2)) | T48: =VALUE(RIGHT(Q48,2)) | U48: days | V48: Multi-day event; anchored to first day
A49: 48 | B49: 1816-06-06 | C49: 1816-06-08 | D49: =VALUE(LEFT(B49,4)) | E49: =INT((D49-1)/100)+1 | F49: Early-season snow | G49: 1816 – June snow on the Catskills (Year Without a Summer, episode 2) | H49: Catskills / highlands of NY, VT, NH; Hudson Valley fringe | I49: Two snow periods: daytime Thu Jun 6 (rain→snow) and night of Jun 7–8; Catskills 'covered by an inch of white' Jun 6; flakes within 10 mi of Hudson tidewater; NO snow reported at valley stations incl. Albany; 18 in drifts at Cabot VT; Elizabethtown 3-hr snowfall | J49: Ludlum pp. 190–193 (Bennington & N. Turner diaries; Hudson Bay-source cold air) | K49: Frost every morning Jun 7–11 at Bennington; corn killed and replanted; ice inch-thick on water at Danville VT. | L49: Ludlum, Early American Winters I (page screenshots, verified) | M49: https://www.nps.gov/articles/000/1816-the-year-without-summer.htm | N49: B | O49: Y | P49: CORRECTION: the popular 'snow fell in Albany' claim is not supported by Ludlum – snow was on the hills, not the valley floor. On the Helderberg plateau at 1,700 ft, snow is plausible. | Q49: 1816-06-06 | R49: =VALUE(LEFT(Q49,4)) | S49: =VALUE(MID(Q49,6,2)) | T49: =VALUE(RIGHT(Q49,2)) | U49: days | V49: Multi-day event; anchored to first day
A50: 49 | B50: 1816-07-04 | C50: 1816-07-09 | D50: =VALUE(LEFT(B50,4)) | E50: =INT((D50-1)/100)+1 | F50: Late frost | G50: 1816 – July frost (Year Without a Summer, episode 3) | H50: NY / New England | I50: 'Light frosts in July' (Ludlum); popular Jul 4–5 ice claim unverified | J50: Ludlum p. 190 (summary only – July detail is in vol. II) | L50: Ludlum, Early American Winters I & II / Early American Hurricanes (AMS) – chronicle sources | N50: C | O50: N | P50: Ludlum vol. I states no authentic July/August snowfall; frosts only. Day needs vol. II. | Q50: 1816-07-04 | R50: =VALUE(LEFT(Q50,4)) | S50: =VALUE(MID(Q50,6,2)) | T50: =VALUE(RIGHT(Q50,2)) | U50: days | V50: Multi-day event; anchored to first day
A51: 50 | B51: 1816-08-21 | C51: 1816-08-21 | D51: =VALUE(LEFT(B51,4)) | E51: =INT((D51-1)/100)+1 | F51: Late frost | G51: 1816 – August 21 frost (Year Without a Summer, episode 4) | H51: NY / New England, as far south as PA and NJ | I51: Frost | J51: Ludlum p. 193 | K51: Damage to tender crops. | L51: Ludlum, Early American Winters I (page screenshots, verified) | N51: B | O51: Y | Q51: 1816-08-21 | R51: =VALUE(LEFT(Q51,4)) | S51: =VALUE(MID(Q51,6,2)) | T51: =VALUE(RIGHT(Q51,2)) | U51: day | V51: Single-day event
A52: 51 | B52: 1816-08-29 | C52: 1816-08-29 | D52: =VALUE(LEFT(B52,4)) | E52: =INT((D52-1)/100)+1 | F52: Late frost | G52: 1816 – August 29 frost (Year Without a Summer, episode 5) | H52: NY / New England, as far south as PA and NJ | I52: Frost Aug 21 and Aug 29 'did some damage to tender crops' | J52: Ludlum p. 193 | K52: Both months ~5°F below normal in New England. | L52: Ludlum, Early American Winters I (page screenshots, verified) | N52: B | O52: Y | Q52: 1816-08-29 | R52: =VALUE(LEFT(Q52,4)) | S52: =VALUE(MID(Q52,6,2)) | T52: =VALUE(RIGHT(Q52,2)) | U52: day | V52: Single-day event
A53: 52 | B53: 1816-09-27 | C53: 1816-09-27 | D53: =VALUE(LEFT(B53,4)) | E53: =INT((D53-1)/100)+1 | F53: Late frost | G53: 1816 – killing frost of Sept 27 (Year Without a Summer, episode 6) | H53: Northern New England / upland NY | I53: Killing frost | J53: Ludlum p. 193 | K53: Cut off even a small corn crop; 'threat of semi-starvation' through winter 1816–17. | L53: Ludlum, Early American Winters I (page screenshots, verified) | N53: B | O53: Y | Q53: 1816-09-27 | R53: =VALUE(LEFT(Q53,4)) | S53: =VALUE(MID(Q53,6,2)) | T53: =VALUE(RIGHT(Q53,2)) | U53: day | V53: Single-day event
A54: 53 | B54: 1817-01-12 | C54: 1817-01-16 | D54: =VALUE(LEFT(B54,4)) | E54: =INT((D54-1)/100)+1 | F54: Arctic outbreak | G54: January 1817 cold wave | H54: New England / eastern NY | I54: Williamstown −16°F Jan 14, −20°F Jan 15; Cambridge −18°F Jan 15 (coldest in Harvard records to 1790); Brunswick ME −21°F | J54: Ludlum pp. 194–195 | K54: First of four major cold waves in the wintry seven weeks of 1817; followed Jan 17–18 by a four-hour winter thunderstorm with lightning fires in MA/NH. | L54: Ludlum, Early American Winters I (page screenshots, verified) | N54: B | O54: Y | Q54: 1817-01-12 | R54: =VALUE(LEFT(Q54,4)) | S54: =VALUE(MID(Q54,6,2)) | T54: =VALUE(RIGHT(Q54,2)) | U54: days | V54: Multi-day event; anchored to first day
A55: 54 | B55: 1817-02-15 | C55: 1817-02-15 | D55: =VALUE(LEFT(B55,4)) | E55: =INT((D55-1)/100)+1 | F55: Arctic outbreak | G55: February 15, 1817 – mercury freezes in northern NY | H55: Northern NY / New England | I55: Whiteborough (Oneida Co.) −35.5°F at 0300; Sackets Harbor −32°F; Hanover NH −30°F; Gardiner ME −40°F; Feb 1817 coldest February since 1780, not exceeded until 1836 | J55: Ludlum p. 195 | K55: Ludlum: 'no doubt the mercury congealed at many of the cold pockets throughout northern New York… near sunrise on 15 February 1817.' | L55: Ludlum, Early American Winters I (page screenshots, verified) | N55: B | O55: Y | P55: Albany value not given – Hough or the Annual Register should have it. | Q55: 1817-02-15 | R55: =VALUE(LEFT(Q55,4)) | S55: =VALUE(MID(Q55,6,2)) | T55: =VALUE(RIGHT(Q55,2)) | U55: day | V55: Single-day event
A56: 55 | B56: 1817-02-15 | C56: 1817-02-15 | D56: =VALUE(LEFT(B56,4)) | E56: =INT((D56-1)/100)+1 | F56: Arctic outbreak | G56: February 15, 1817 – Albany 6° below zero | H56: Albany | I56: −6°F Feb 15 — 'first time since 1788 it has fallen below zero in this city' | J56: Albany freeze notice | K56: Gives the Albany value for the Feb 15 1817 cold that the register previously had only for northern NY (Whiteboro −35.5°F). River had closed Dec 16. | L56: Albany Daily Advertiser, "Notices of the Winters at New York for the last forty-two years… dates at which the Hudson was frozen or obstructed or closed by ice at Albany," repr. American Quarterly Journal of Agriculture and Science 1 (1845) pp. 347–350 (verified, page images) | M56: https://archive.org/details/americanquarterl00slsn | N56: A | O56: Y | P56: Matches Ludlum's Feb 1817 chapter; this is the missing Albany figure. | Q56: 1817-02-15 | R56: =VALUE(LEFT(Q56,4)) | S56: =VALUE(MID(Q56,6,2)) | T56: =VALUE(RIGHT(Q56,2)) | U56: day | V56: Single-day event
A57: 56 | B57: 1817-02-24 | C57: 1817-02-25 | D57: =VALUE(LEFT(B57,4)) | E57: =INT((D57-1)/100)+1 | F57: Nor'easter | G57: Great northeaster of Feb 24, 1817 | H57: Atlantic seaboard / southern & eastern New England | I57: Lowest barometric pressures observed to that date; 'violent storm from NE and NW' at Baltimore | J57: Ludlum p. 195 (continues p. 196) | K57: Winter's 'most striking blow' after seven weeks of cold. | L57: Ludlum, Early American Winters I (page screenshots, verified) | N57: B | O57: Y | P57: Page 196 not yet read – NY extent unknown. | Q57: 1817-02-24 | R57: =VALUE(LEFT(Q57,4)) | S57: =VALUE(MID(Q57,6,2)) | T57: =VALUE(RIGHT(Q57,2)) | U57: days | V57: Multi-day event; anchored to first day
A58: 57 | B58: 1821-01-25 | C58: 1821-01-25 | D58: =VALUE(LEFT(B58,4)) | E58: =INT((D58-1)/100)+1 | F58: Arctic outbreak / river ice | G58: January 25, 1821 – coldest ever at Albany | H58: Albany | I58: −7°F Jan 25, 'one degree lower than in February 1817; as cold as ever experienced here'; Hudson crossed on the ice Albany↔Powles' Hook several days | J58: Albany freeze notice | K58: The notice states the Hudson was walkable at Albany only four times in the prior century: 1740–41, 1764–65, 1779–80, 1820–21. | L58: Albany Daily Advertiser, "Notices of the Winters at New York for the last forty-two years… dates at which the Hudson was frozen or obstructed or closed by ice at Albany," repr. American Quarterly Journal of Agriculture and Science 1 (1845) pp. 347–350 (verified, page images) | M58: https://archive.org/details/americanquarterl00slsn | N58: A | O58: Y | P58: Directly corroborates the register's 1740–41, 1765 and 1780 ice-crossing rows. | Q58: 1821-01-25 | R58: =VALUE(LEFT(Q58,4)) | S58: =VALUE(MID(Q58,6,2)) | T58: =VALUE(RIGHT(Q58,2)) | U58: day | V58: Single-day event
A59: 58 | B59: 1821-09-03 | C59: 1821-09-03 | D59: =VALUE(LEFT(B59,4)) | E59: =INT((D59-1)/100)+1 | F59: Tropical cyclone | G59: Norfolk–Long Island Hurricane | H59: NYC / lower Hudson | I59: Eye over NYC (chronicle) | J59: none | K59: Wind damage up the lower Hudson Valley. | L59: Ludlum, Early American Winters I & II / Early American Hurricanes (AMS) – chronicle sources | N59: C | O59: N | Q59: 1821-09-03 | R59: =VALUE(LEFT(Q59,4)) | S59: =VALUE(MID(Q59,6,2)) | T59: =VALUE(RIGHT(Q59,2)) | U59: day | V59: Single-day event
A60: 59 | B60: 1821-09-03 | C60: 1821-09-03 | D60: =VALUE(LEFT(B60,4)) | E60: =INT((D60-1)/100)+1 | F60: Tropical cyclone | G60: The Hurricane of September 3, 1821 – over NYC & up the Hudson | H60: NYC (center crossed) / lower & mid Hudson Valley / Westchester | I60: Center crossed part of NYC (only major hurricane to do so in 200 yrs, per Ludlum); North River (Hudson) wharves destroyed, Battery inundated, trees down in the Park; Westchester Herald: strong winds and extremely high tides along the river; damage extended up the Hudson Valley 'some distance' | J60: Ludlum pp. 82, 85 (NY Post, Westchester Herald, Redfield) | K60: The storm that launched American storm science (Redfield's rotary-wind insight). Center over NYC; the Hudson Valley took the western semicircle. Genuinely regional. | L60: Ludlum, Early American Hurricanes 1492–1870 (AMS, 1963), pp. 77–108 (verified, page images) | M60: https://hdl.handle.net/2027/mdp.39015002912718 | N60: B | O60: Y | P60: Center over NYC; Hudson Valley damage documented up-river. Strongest of this batch for the region. | Q60: 1821-09-03 | R60: =VALUE(LEFT(Q60,4)) | S60: =VALUE(MID(Q60,6,2)) | T60: =VALUE(RIGHT(Q60,2)) | U60: day | V60: Single-day event
A61: 60 | B61: 1826-12-14 | C61: 1826-12-14 | D61: =VALUE(LEFT(B61,4)) | E61: =INT((D61-1)/100)+1 | F61: Cold snap | G61: December 14, 1826 cold day | H61: Albany | I61: 3°F at 8 AM, 2°F/9°F later | J61: Albany freeze notice | K61: A single sharp December cold day in an otherwise mild winter. | L61: Albany Daily Advertiser, "Notices of the Winters at New York for the last forty-two years… dates at which the Hudson was frozen or obstructed or closed by ice at Albany," repr. American Quarterly Journal of Agriculture and Science 1 (1845) pp. 347–350 (verified, page images) | M61: https://archive.org/details/americanquarterl00slsn | N61: B | O61: Y | Q61: 1826-12-14 | R61: =VALUE(LEFT(Q61,4)) | S61: =VALUE(MID(Q61,6,2)) | T61: =VALUE(RIGHT(Q61,2)) | U61: day | V61: Single-day event
A62: 61 | B62: 1828-12-01 | C62: 1829-03-29 | D62: =VALUE(LEFT(B62,4)) | E62: =INT((D62-1)/100)+1 | F62: Cold winter | G62: Long severe winter 1828–29 | H62: Albany | I62: River closed Jan 1, opened Mar 29; lowest 6°F below zero; 'much suffering among the poor' | J62: Albany freeze notice | K62: One of the coldest of the series; latest opening date (Mar 29). | L62: Albany Daily Advertiser, "Notices of the Winters at New York for the last forty-two years… dates at which the Hudson was frozen or obstructed or closed by ice at Albany," repr. American Quarterly Journal of Agriculture and Science 1 (1845) pp. 347–350 (verified, page images) | M62: https://archive.org/details/americanquarterl00slsn | N62: B | O62: Y | Q62: 1829-01-29 | R62: =VALUE(LEFT(Q62,4)) | S62: =VALUE(MID(Q62,6,2)) | T62: =VALUE(RIGHT(Q62,2)) | U62: season | V62: Anchored to mid-point of a season-scale window
A63: 62 | B63: 1830-12-23 | C63: 1831-02-28 | D63: =VALUE(LEFT(B63,4)) | E63: =INT((D63-1)/100)+1 | F63: Cold winter | G63: Severe snowy winter 1830–31 | H63: Albany | I63: Ground snow-covered Jan 6–Feb 28 (longest since 1808–09); frost 5+ weeks, only 3 days above freezing; river closed Dec 23, reopened by rains, closed again Jan 16 | J63: Albany freeze notice | L63: Albany Daily Advertiser, "Notices of the Winters at New York for the last forty-two years… dates at which the Hudson was frozen or obstructed or closed by ice at Albany," repr. American Quarterly Journal of Agriculture and Science 1 (1845) pp. 347–350 (verified, page images) | M63: https://archive.org/details/americanquarterl00slsn | N63: B | O63: Y | Q63: 1831-01-25 | R63: =VALUE(LEFT(Q63,4)) | S63: =VALUE(MID(Q63,6,2)) | T63: =VALUE(RIGHT(Q63,2)) | U63: season | V63: Anchored to mid-point of a season-scale window
A64: 63 | B64: 1832-02-15 | C64: 1832-03-31 | D64: =VALUE(LEFT(B64,4)) | E64: =INT((D64-1)/100)+1 | F64: Ice jam | G64: Mohawk breakup flood with ice, 1832 | H64: Lower Mohawk / Schenectady | I64: Listed among major ice-involved breakup floods | J64: Garver chronology | K64: One of ~11 major ice breakup floods on the lower Mohawk 1832–1996; ~80% of severe Mohawk floods involve ice. | L64: Garver (Union College) Mohawk ice-jam chronology | M64: https://minerva.union.edu/garverj/mohawk/1996_ice_jam.html | N64: C | O64: Y | P64: Day not yet pulled – Garver's Mohawk flood table has it. | Q64: 1832-03-08 | R64: =VALUE(LEFT(Q64,4)) | S64: =VALUE(MID(Q64,6,2)) | T64: =VALUE(RIGHT(Q64,2)) | U64: month | V64: Anchored to mid-point of a multi-week window
A65: 64 | B65: 1835-12-16 | C65: 1835-12-17 | D65: =VALUE(LEFT(B65,4)) | E65: =INT((D65-1)/100)+1 | F65: Arctic outbreak | G65: December 1835 cold – Great Fire of New York | H65: NYC / Hudson Valley | I65: ≈ –17°F at NYC; Hudson and East River frozen (hydrants and rivers frozen during the fire) | J65: none | K65: Fire burned 17 blocks because water sources were frozen; marks the start of the long 1835–36 ice closure of the Hudson. | L65: Wikipedia event article (secondary; verify against NCEI/NHC) | M65: https://en.wikipedia.org/wiki/Great_Fire_of_New_York | N65: B | O65: Y | P65: Use as the timeline anchor for the 1835–36 winter. | Q65: 1835-12-16 | R65: =VALUE(LEFT(Q65,4)) | S65: =VALUE(MID(Q65,6,2)) | T65: =VALUE(RIGHT(Q65,2)) | U65: days | V65: Multi-day event; anchored to first day
A66: 65 | B66: 1835-12-16 | C66: 1836-04-15 | D66: =VALUE(LEFT(B66,4)) | E66: =INT((D66-1)/100)+1 | F66: Cold winter | G66: Winter of 1835–36 (season) | H66: Hudson Valley | I66: Hudson closed ~4 months (chronicle) | J66: none | K66: Long ice closure, heavy snow, spring freshet at Albany. | L66: Ludlum, Early American Winters I & II / Early American Hurricanes (AMS) – chronicle sources | N66: C | O66: N | P66: Season row; anchored to Dec 16, 1835. | Q66: 1836-02-14 | R66: =VALUE(LEFT(Q66,4)) | S66: =VALUE(MID(Q66,6,2)) | T66: =VALUE(RIGHT(Q66,2)) | U66: season | V66: Anchored to mid-point of a season-scale window
A67: 66 | B67: 1837-01-01 | C67: 1837-01-01 | D67: =VALUE(LEFT(B67,4)) | E67: =INT((D67-1)/100)+1 | F67: Landslide | G67: Troy Mount Ida clay avalanche | H67: Troy (east end of Washington St.) | I67: Clay slid ~500 ft, covering many acres | J67: none | K67: Two stables (22 horses) and three dwellings with seven people crushed and buried; ~7 PM Sunday. | L67: Young, Troy's One Hundred Years (1891) | M67: https://troyirish.org/troy-area-history/local-history/local-history-articles/avalanche-of-clay | N67: B | O67: Y | P67: Glacial Lake Albany clay. Death toll: confirm. | Q67: 1837-01-01 | R67: =VALUE(LEFT(Q67,4)) | S67: =VALUE(MID(Q67,6,2)) | T67: =VALUE(RIGHT(Q67,2)) | U67: day | V67: Single-day event
A68: 67 | B68: 1839-08-30 | C68: 1839-08-30 | D68: =VALUE(LEFT(B68,4)) | E68: =INT((D68-1)/100)+1 | F68: Tropical cyclone / early snow | G68: Atlantic Coast Hurricane of late August 1839 – snow in the Catskills | H68: Offshore; snow in the Catskills | I68: Storm stayed offshore but cold air behind it dropped snow that 'whitened' the Catskills; snow also fell at Salem MA and along the coast (late-August snow) | J68: Ludlum p. 106 (Genesee Farmer / Gaylord) | K68: Remarkable for late-August snow in the Catskills — a phenology curiosity. High winds confined to the coastal plain ('80 mi inland it was scarcely felt'). | L68: Ludlum, Early American Hurricanes 1492–1870 (AMS, 1963), pp. 77–108 (verified, page images) | M68: https://hdl.handle.net/2027/mdp.39015002912718 | N68: C | O68: Y | P68: Notable only for the Catskill snow; no wind damage inland. | Q68: 1839-08-30 | R68: =VALUE(LEFT(Q68,4)) | S68: =VALUE(MID(Q68,6,2)) | T68: =VALUE(RIGHT(Q68,2)) | U68: day | V68: Single-day event
A69: 68 | B69: 1848-03-29 | C69: 1848-03-31 | D69: =VALUE(LEFT(B69,4)) | E69: =INT((D69-1)/100)+1 | F69: Ice jam | G69: Niagara Falls stops flowing (OUT OF REGION) | H69: Niagara River / Lake Erie outlet | I69: Flow stopped ~30–40 hours | J69: none | K69: Gale-driven Lake Erie ice jammed the river head; people walked the riverbed; flow resumed Mar 31. | L69: Wikipedia event article (secondary; verify against NCEI/NHC) | M69: https://en.wikipedia.org/wiki/Niagara_Falls | N69: B | O69: N | P69: Included at user request; ~280 mi west of Westerlo. | Q69: 1848-03-29 | R69: =VALUE(LEFT(Q69,4)) | S69: =VALUE(MID(Q69,6,2)) | T69: =VALUE(RIGHT(Q69,2)) | U69: days | V69: Multi-day event; anchored to first day
A70: 69 | B70: 1850-07-18 | C70: 1850-07-19 | D70: =VALUE(LEFT(B70,4)) | E70: =INT((D70-1)/100)+1 | F70: Tropical cyclone | G70: July 1850 storm – central NY / PA track | H70: Central NY State / PA / Southern Tier (W of the Catskills) | I70: Track carried westward and northward over Pennsylvania and central New York State; property/crop damage in CT, not in eastern MA; Delaware & Lehigh flooding, 20 lives lost on the Schuylkill | J70: Ludlum p. 113 (Fort Trumbull Medical Corps obs.) | K70: One of the Triple Tropical Storms of 1850. The only storm of the 1849–1869 batch to track inland into NY, but W of the Catskills — it grazes the register footprint's western edge. | L70: Ludlum, Early American Hurricanes 1492–1870 (AMS, 1963), pp. 109–124 (verified, page images/text) | M70: https://hdl.handle.net/2027/mdp.39015002912718 | N70: C | O70: N | P70: Central-NY/Southern-Tier track, W of the Catskills; no eastern-NY damage documented. Included for completeness. | Q70: 1850-07-18 | R70: =VALUE(LEFT(Q70,4)) | S70: =VALUE(MID(Q70,6,2)) | T70: =VALUE(RIGHT(Q70,2)) | U70: days | V70: Jul 18–19; anchored to first day
A71: 70 | B71: 1857-01-18 | C71: 1857-01-19 | D71: =VALUE(LEFT(B71,4)) | E71: =INT((D71-1)/100)+1 | F71: Blizzard / cold | G71: The Cold Storm of 1857 | H71: Northeast | I71: Blizzard after –20s cold (chronicle) | J71: none | K71: Hudson bridged by ice at Manhattan. | L71: Ludlum, Early American Winters I & II / Early American Hurricanes (AMS) – chronicle sources | N71: C | O71: N | Q71: 1857-01-18 | R71: =VALUE(LEFT(Q71,4)) | S71: =VALUE(MID(Q71,6,2)) | T71: =VALUE(RIGHT(Q71,2)) | U71: days | V71: Multi-day event; anchored to first day
A72: 71 | B72: 1857-02-01 | C72: 1857-02-28 | D72: =VALUE(LEFT(B72,4)) | E72: =INT((D72-1)/100)+1 | F72: River flood (ice jam) | G72: February 1857 Albany flood – flood of record | H72: Hudson at Albany | I72: 21.71 ft crest | J72: Hudson R. at Albany | K72: Highest flood ever recorded at Albany; caused by ice jammed on sandbars south of the city. | L72: NWS Albany – Past Weather Events (weather.gov/aly/pastevents) ; The Argus (Albany), Dec 31 1900 ("The Christmas Argus" - retrospective on Albany ice gorges and freshets) [uploaded PDF scan] | M72: https://www.weather.gov/aly/pastevents | N72: A | O72: Y | P72: Still the Albany record. 2026-09-22 (v828, atlas session): ENRICHED from research-chat intake row 354 (same event; merged, not added). In February 1857 a freshet tore away about 200 ft of the embankment running from the mainland to the Island above Albany - a dyke the government had built to throw the river's water into the channel. || Key measurement per that source: ~200 ft of the training embankment torn away || Intake notes: 2026-09-22: added per Laurie (PDF scan). Confidence C - from the 1900 retrospective, not a contemporaneous report; confirm from an 1857 primary source and pin down the day at merge. Candidate Geology pin (coords needed): the training dyke to the Island above Albany. EXISTENCE-GUARD at merge. | Q72: 1857-02-15 | R72: =VALUE(LEFT(Q72,4)) | S72: =VALUE(MID(Q72,6,2)) | T72: =VALUE(RIGHT(Q72,2)) | U72: month | V72: NWS gives month only; ice-jam crest day to pull from Munsell's Annals of Albany
A73: 72 | B73: 1859-03-17 | C73: 1859-03-17 | D73: =VALUE(LEFT(B73,4)) | E73: =INT((D73-1)/100)+1 | F73: Landslide | G73: St. Peters College slide, Troy (Mt. Ida) | H73: Troy — foot of Mt. Ida (Mt. Ida Delta, Poesten Kill) | I73: Rotational slump destroyed the half-built 5-story, 200-ft St. Peters College; NO deaths (children had just left); the building blocked the slide from a residential area downhill | J73: none | K73: The famous 1859 Troy Mt. Ida slide, on St. Patrick's Day evening. On the Mt. Ida Delta (Poesten Kill into Glacial Lake Albany) — same delta-slump mechanism as Schenectady. USGS notes >50 lives lost to Lake Albany clay slides around Troy/Albany over the 19th c. St. Peters College was never rebuilt — a lasting historic loss to Troy. | L73: USGS PP 1183; The Catskill Geologist (Titus) ; Titus, R. & J., 'The St. Peters slide – an unhappy anniversary', The Mountain Eagle, Mar 16 2018 | M73: https://pubs.usgs.gov/pp/p1183/pp1183.html | N73: B | O73: Y | P73: DATE CORRECTED from 1859-02-17 (was 'from memory') to 17 Mar 1859 (St. Patrick's Day) per Titus/Catskill Geologist — the St. Peters College slide. 2026-09-23 (v844, atlas session): Titus confirms the date — evening of St. Patrick's Day, Mar 17 1859 — and adds: the college was half-built (planned five storeys, 200 ft long); no deaths (children playing there had just left); the building took the slide and shielded the housing below; never rebuilt for want of money. Mechanism: Mt. Ida = Poesten Kill delta into Glacial Lake Albany, same failure mode as Nott Terrace 2018. Titus's 'most historically consequential Hudson Valley slide' nominee. DISCREPANCY (flagged, not reconciled): Titus says NO deaths at St. Peters 1859, while this row's impact summary cites USGS '>50 lives lost' — check whether the USGS figure is cumulative for Mt. Ida (1837 clay avalanche, row 66, plus 1859) rather than 1859 alone. | Q73: 1859-03-17 | R73: =VALUE(LEFT(Q73,4)) | S73: =VALUE(MID(Q73,6,2)) | T73: =VALUE(RIGHT(Q73,2)) | U73: day | V73: Single-day event
A74: 73 | B74: 1859-06-04 | C74: 1859-06-05 | D74: =VALUE(LEFT(B74,4)) | E74: =INT((D74-1)/100)+1 | F74: Late frost | G74: June 1859 killing frost | H74: Upstate NY | I74: Killing frost first week of June (chronicle) | J74: none | K74: Destroyed early crops statewide. | L74: Ludlum, Early American Winters I & II / Early American Hurricanes (AMS) – chronicle sources | N74: C | O74: N | Q74: 1859-06-04 | R74: =VALUE(LEFT(Q74,4)) | S74: =VALUE(MID(Q74,6,2)) | T74: =VALUE(RIGHT(Q74,2)) | U74: days | V74: Multi-day event; anchored to first day
A75: 74 | B75: 1865-02-15 | C75: 1865-03-31 | D75: =VALUE(LEFT(B75,4)) | E75: =INT((D75-1)/100)+1 | F75: Ice jam | G75: Mohawk breakup flood with ice, 1865 | H75: Lower Mohawk / Schenectady | I75: Listed among major ice-involved breakup floods | J75: Garver chronology | K75: One of ~11 major ice breakup floods on the lower Mohawk 1832–1996; ~80% of severe Mohawk floods involve ice. | L75: Garver (Union College) Mohawk ice-jam chronology | M75: https://minerva.union.edu/garverj/mohawk/1996_ice_jam.html | N75: C | O75: Y | P75: Day not yet pulled – Garver's Mohawk flood table has it. | Q75: 1865-03-09 | R75: =VALUE(LEFT(Q75,4)) | S75: =VALUE(MID(Q75,6,2)) | T75: =VALUE(RIGHT(Q75,2)) | U75: month | V75: Anchored to mid-point of a multi-week window
A76: 75 | B76: 1869-10-03 | C76: 1869-10-04 | D76: =VALUE(LEFT(B76,4)) | E76: =INT((D76-1)/100)+1 | F76: Rain flood | G76: Great Freshet of October 1869 | H76: Hudson Valley / New England | I76: Extreme rain (chronicle) | J76: none | K76: Mills and bridges lost. | L76: Ludlum, Early American Winters I & II / Early American Hurricanes (AMS) – chronicle sources | N76: C | O76: N | Q76: 1869-10-03 | R76: =VALUE(LEFT(Q76,4)) | S76: =VALUE(MID(Q76,6,2)) | T76: =VALUE(RIGHT(Q76,2)) | U76: days | V76: Multi-day event; anchored to first day
A77: 76 | B77: 1869-10-04 | C77: 1869-10-04 | D77: =VALUE(LEFT(B77,4)) | E77: =INT((D77-1)/100)+1 | F77: Rain flood (tropical remnant) | G77: Saxby's Gale & Great Northeastern Rainstorm of October 1869 | H77: Middle Atlantic to Canada; central & upper Hudson Valley | I77: Greatest single-storm rainfall over the MA/New England area in recorded history to that date: 5 in+ at stations across VA, MD, PA, NJ, NY, CT, MA, VT, NH, ME; heaviest band ran NW from E. Connecticut through Springfield MA into the central & upper Hudson Valley of NY | J77: Ludlum pp. 125–126 (Saxby's Gale chapter) | K77: A landmark rain-and-flood event that directly reached the central and upper Hudson Valley. The offshore hurricane (Saxby's Gale) combined with a stalled continental rainstorm. | L77: Ludlum, Early American Hurricanes 1492–1870 (AMS, 1963), pp. 109–110, 125–126 and Chronological Index pp. 191–195 (verified, page images/text) | M77: https://hdl.handle.net/2027/mdp.39015002912718 | N77: B | O77: Y | P77: Central & upper Hudson Valley named explicitly — the strongest regional event in the whole hurricane volume after 1821. | Q77: 1869-10-04 | R77: =VALUE(LEFT(Q77,4)) | S77: =VALUE(MID(Q77,6,2)) | T77: =VALUE(RIGHT(Q77,2)) | U77: day | V77: Single-day event
A78: 77 | B78: 1870-02-15 | C78: 1870-03-31 | D78: =VALUE(LEFT(B78,4)) | E78: =INT((D78-1)/100)+1 | F78: Ice jam | G78: Mohawk breakup flood with ice, 1870 | H78: Lower Mohawk / Schenectady | I78: Listed among major ice-involved breakup floods | J78: Garver chronology | K78: One of ~11 major ice breakup floods on the lower Mohawk 1832–1996; ~80% of severe Mohawk floods involve ice. | L78: Garver (Union College) Mohawk ice-jam chronology | M78: https://minerva.union.edu/garverj/mohawk/1996_ice_jam.html | N78: C | O78: Y | P78: Day not yet pulled – Garver's Mohawk flood table has it. | Q78: 1870-03-09 | R78: =VALUE(LEFT(Q78,4)) | S78: =VALUE(MID(Q78,6,2)) | T78: =VALUE(RIGHT(Q78,2)) | U78: month | V78: Anchored to mid-point of a multi-week window
A79: 78 | B79: 1878-10-23 | C79: 1878-10-23 | D79: =VALUE(LEFT(B79,4)) | E79: =INT((D79-1)/100)+1 | F79: Tropical cyclone | G79: Gale of 1878 | H79: Eastern NY | I79: Hurricane tracked inland W of Hudson | J79: none | K79: Wind damage at Albany. | L79: Ludlum, Early American Winters I & II / Early American Hurricanes (AMS) – chronicle sources | N79: C | O79: N | Q79: 1878-10-23 | R79: =VALUE(LEFT(Q79,4)) | S79: =VALUE(MID(Q79,6,2)) | T79: =VALUE(RIGHT(Q79,2)) | U79: day | V79: Single-day event
A80: 79 | B80: 1886-02-14 | C80: 1886-02-15 | D80: =VALUE(LEFT(B80,4)) | E80: =INT((D80-1)/100)+1 | F80: Ice jam | G80: February 1886 Mohawk ice jam | H80: Schenectady | I80: Ice piled 30–40 ft high after recession; 1-ft trees snapped | J80: Evening Star, Feb 15 1886 | K80: Among the most violent Mohawk ice events on record. | L80: Garver (Union College) Mohawk ice-jam chronology | M80: https://minerva.union.edu/garverj/mohawk/1996_ice_jam.html | N80: B | O80: Y | Q80: 1886-02-14 | R80: =VALUE(LEFT(Q80,4)) | S80: =VALUE(MID(Q80,6,2)) | T80: =VALUE(RIGHT(Q80,2)) | U80: days | V80: Multi-day event; anchored to first day
A81: 80 | B81: 1887-12-18 | C81: 1887-12-22 | D81: =VALUE(LEFT(B81,4)) | E81: =INT((D81-1)/100)+1 | F81: Snowstorm | G81: December 1887 snowstorm | H81: Capital Region | I81: 3rd greatest December storm; winter 1887–88 = 110.0 in (2nd snowiest) | J81: Albany | K81: One of the greatest storms on record for Albany. | L81: NWS Albany – Past Weather Events (weather.gov/aly/pastevents) | M81: https://www.weather.gov/aly/pastevents | N81: A | O81: Y | Q81: 1887-12-18 | R81: =VALUE(LEFT(Q81,4)) | S81: =VALUE(MID(Q81,6,2)) | T81: =VALUE(RIGHT(Q81,2)) | U81: days | V81: Multi-day event; anchored to first day
A82: 81 | B82: 1888-03-11 | C82: 1888-03-14 | D82: =VALUE(LEFT(B82,4)) | E82: =INT((D82-1)/100)+1 | F82: Blizzard | G82: The Blizzard of 1888 | H82: Entire region | I82: 46.7 in / 60 hr at Albany (storm record); March 1888 2nd snowiest month | J82: Albany | K82: City shut down; no coal deliveries; drifts far higher; ~400 dead regionally. | L82: NWS Albany – Past Weather Events (weather.gov/aly/pastevents) ; The Argus (Albany), Mar 14 1888 ("Deep in Drifts - Several States Buried Beneath Snowy Mantles") [uploaded PDF scan] | M82: https://www.weather.gov/aly/pastevents | N82: A | O82: Y | P82: Benchmark storm. The late-March snowmelt freshet followed: Amsterdam/Port Jackson flood damage (~$10k), a Central-Hudson RR freight blockade, and a clay landslide in the RR cut near Stillwater ('the clay continues to slide in slowly'). [The Argus, 25 Mar 1888] 2026-09-22 (v828, atlas session): ENRICHED from research-chat intake row 343 (same event; merged, not added). The Great Blizzard of March 11-14 1888 ('Blizzard of '88' / Great White Hurricane) buried the Northeast. New York City was paralyzed - ~2 ft of snow with drifts 5-15 ft, elevated roads buried, and seven pilot boats driven ashore (probable total loss); trains ran 3-10 hours late or were abandoned and telegraph service collapsed (NYC loss estimated ~$10 million). Across New York the storm cut off Central NY (Utica's cuts blocked, a Snow-Shoe club's perilous return, Rome and Syracuse hit). North Adams MA got ~34 in and Boston was cut off; the Bergen-hill cut (NJ) filled with 30 ft of snow; ~25 lives were lost with vessels sunk at the Delaware breakwater; and Pittsburg PA saw its first day in 20 || Key measurement per that source: ~2 ft snow, drifts 5-15 ft; NYC loss estimated ~$10 million || Intake notes: 2026-09-22: added per Laurie (PDF scan). ENRICH, DO NOT DUPLICATE: the register almost certainly already carries the iconic Blizzard of '88 - merge this scan's detail into the existing row rather than adding a new one. This scan's detail is NYC/regional/Central-NY; Albany- and Catskills-specific fig | Q82: 1888-03-11 | R82: =VALUE(LEFT(Q82,4)) | S82: =VALUE(MID(Q82,6,2)) | T82: =VALUE(RIGHT(Q82,2)) | U82: days | V82: Multi-day event; anchored to first day
A83: 82 | B83: 1891-02-15 | C83: 1891-03-31 | D83: =VALUE(LEFT(B83,4)) | E83: =INT((D83-1)/100)+1 | F83: Ice jam | G83: Mohawk breakup flood with ice, 1891 | H83: Lower Mohawk / Schenectady | I83: Listed among major ice-involved breakup floods | J83: Garver chronology | K83: One of ~11 major ice breakup floods on the lower Mohawk 1832–1996; ~80% of severe Mohawk floods involve ice. | L83: Garver (Union College) Mohawk ice-jam chronology | M83: https://minerva.union.edu/garverj/mohawk/1996_ice_jam.html | N83: C | O83: Y | P83: Day not yet pulled – Garver's Mohawk flood table has it. | Q83: 1891-03-09 | R83: =VALUE(LEFT(Q83,4)) | S83: =VALUE(MID(Q83,6,2)) | T83: =VALUE(RIGHT(Q83,2)) | U83: month | V83: Anchored to mid-point of a multi-week window
A84: 83 | B84: 1893-02-15 | C84: 1893-03-31 | D84: =VALUE(LEFT(B84,4)) | E84: =INT((D84-1)/100)+1 | F84: Ice jam | G84: Mohawk breakup flood with ice, 1893 | H84: Lower Mohawk / Schenectady | I84: Listed among major ice-involved breakup floods | J84: Garver chronology | K84: One of ~11 major ice breakup floods on the lower Mohawk 1832–1996; ~80% of severe Mohawk floods involve ice. | L84: Garver (Union College) Mohawk ice-jam chronology | M84: https://minerva.union.edu/garverj/mohawk/1996_ice_jam.html | N84: C | O84: Y | P84: Day not yet pulled – Garver's Mohawk flood table has it. | Q84: 1893-03-09 | R84: =VALUE(LEFT(Q84,4)) | S84: =VALUE(MID(Q84,6,2)) | T84: =VALUE(RIGHT(Q84,2)) | U84: month | V84: Anchored to mid-point of a multi-week window
A85: 84 | B85: 1893-08-24 | C85: 1893-08-24 | D85: =VALUE(LEFT(B85,4)) | E85: =INT((D85-1)/100)+1 | F85: Tropical cyclone | G85: Midnight Storm (1893 NYC hurricane) | H85: NYC / lower Hudson | I85: Direct hit on NYC | J85: none | K85: Wind and rain up the valley. | L85: Ludlum, Early American Winters I & II / Early American Hurricanes (AMS) – chronicle sources | N85: C | O85: N | Q85: 1893-08-24 | R85: =VALUE(LEFT(Q85,4)) | S85: =VALUE(MID(Q85,6,2)) | T85: =VALUE(RIGHT(Q85,2)) | U85: day | V85: Single-day event
A86: 85 | B86: 1896-08-04 | C86: 1896-08-13 | D86: =VALUE(LEFT(B86,4)) | E86: =INT((D86-1)/100)+1 | F86: Heat wave | G86: August 1896 heat wave | H86: Northeast | I86: 10 days >90°F with high humidity | J86: NYC | K86: ~1,500 deaths in NYC; deaths in the valley. | L86: Wikipedia event article (secondary; verify against NCEI/NHC) | N86: B | O86: N | P86: The '10 days >90°F' and ~1,500 deaths are NYC/regional — Albany's own record 90°F+ streak is 10 days (Aug–Sep 1953), NOT 1896, so the Albany-specific 1896 figure still needs the NWS-Albany record or the Albany/Altamont newspaper. A landmark tenement-heat disaster (NYC police commissioner Theodore Roosevelt distributed ice to the poor). | Q86: 1896-08-10 | R86: =VALUE(LEFT(Q86,4)) | S86: =VALUE(MID(Q86,6,2)) | T86: =VALUE(RIGHT(Q86,2)) | U86: week | V86: Mid-point of the 10-day wave
A87: 86 | B87: 1899-02-08 | C87: 1899-02-14 | D87: =VALUE(LEFT(B87,4)) | E87: =INT((D87-1)/100)+1 | F87: Arctic outbreak / blizzard | G87: Great Arctic Outbreak of 1899 | H87: Eastern US | I87: Coldest air mass in Eastern record | J87: regional | K87: Record cold then blizzard; Hudson frozen. | L87: Wikipedia event article (secondary; verify against NCEI/NHC) ; The Argus (Albany), Feb 19 1899, editorial page (scan supplied by Laurie) | N87: B | O87: N | P87: Check Albany daily min in NCEI GHCN for exact value. 2026-09-23 (v850, atlas session): ENRICHED (Argus Feb 19 1899): 'the blizzard of last week… unparalleled in many winters' — every railroad centering on Albany was blockaded by the storm, and for the third time since 1882 the Albany Railway (street railway) provided the only transit into and out of the city, keeping every line open and even extending service to Cohoes, Troy, Rensselaer and Kenwood 'between the neighboring storm-bound cities'. Same page: NY State Board of Health 1898 report (121,000 deaths, rate 18.10) and Georgia/Nebraska frost-blighted peach crops — context only. | Q87: 1899-02-10 | R87: =VALUE(LEFT(Q87,4)) | S87: =VALUE(MID(Q87,6,2)) | T87: =VALUE(RIGHT(Q87,2)) | U87: days | V87: Coldest mornings Feb 9–11
A88: 87 | B88: 1900-01-01 | C88: 2023-03-10 | D88: =VALUE(LEFT(B88,4)) | E88: =INT((D88-1)/100)+1 | F88: Sinkhole / karst (event) | G88: McFails Cave historic entrance collapse | H88: Cobleskill plateau (Schoharie Co.) | I88: The historic 110-ft vertical entrance sink became unstable and collapsed; access is now via two other rope drops | J88: Nardacci / NCC | K88: A documented karst-entrance collapse, but UNDATED in the source (years ago). Span is a placeholder, not the event date. | L88: Northeastern Cave Conservancy / NSS; Altamont Enterprise Back Roads Geology (Nardacci), 10 Mar 2023 | M88: https://necaveconservancy.org/preserves/ | N88: C | O88: N | P88: DATE UNKNOWN — do not plot as a point. Collapse is real and documented; needs an NCC/NSS date. Anchored artificially. | Q88: 2023-03-10 | R88: =VALUE(LEFT(Q88,4)) | S88: =VALUE(MID(Q88,6,2)) | T88: =VALUE(RIGHT(Q88,2)) | U88: year | V88: DATE UNKNOWN; collapse happened years ago; do NOT plot as a point
A89: 88 | B89: 1903-01-15 | C89: 1903-03-20 | D89: =VALUE(LEFT(B89,4)) | E89: =INT((D89-1)/100)+1 | F89: Ice jam | G89: Hudson ice gorge below Albany, winter 1902–03 | H89: Albany to Mull's Bar / Castleton | I89: Ice jammed to river bottom, 9–10 ft thick; no tide at Albany until March | J89: HRMM oral history | K89: Water rose to unprecedented height in south Albany; Cornell tugs hired in March 1903 to break the gorge. | L89: Hudson River Maritime Museum – Breaking Ice Gorges | M89: https://www.hrmm.org/history-blog/breaking-ice-gorges | N89: B | O89: Y | Q89: 1903-02-16 | R89: =VALUE(LEFT(Q89,4)) | S89: =VALUE(MID(Q89,6,2)) | T89: =VALUE(RIGHT(Q89,2)) | U89: season | V89: Anchored to mid-point of a season-scale window
A90: 89 | B90: 1903-10-08 | C90: 1903-10-10 | D90: =VALUE(LEFT(B90,4)) | E90: =INT((D90-1)/100)+1 | F90: Rain flood | G90: October 1903 flood | H90: Catskills / lower Hudson / NJ | I90: 10–15 in rain | J90: regional | K90: Record stages on Catskill & lower Hudson tributaries (Passaic record still stands). Central-Hudson RR landslides at Hallenbeck's switch, New Hamburgh & Ossining buried the tracks; the Catskill Creek draw-bridge collapsed, sweeping 5 people into the torrent (1 badly injured, 2 unaccounted); a dam at Kenwood below Albany broke; the Troy D&H bridge shifted 12 in under freshet drift; Stottville mills flooded; Hudson brickyards lost kilns of green brick. | L90: Wikipedia; Columbia Republican (Hudson) 15 Oct 1903 (NYS Historic Newspapers) | N90: B | O90: Y | P90: The Catskill Creek bridge collapse (5 swept away) and the Kenwood dam break are the standout local losses; the RR slides (Hallenbeck's/New Hamburgh/Ossining) are Lake Albany clay failures. Dated ~Oct 8-9 1903 ('storm of last week'). | Q90: 1903-10-08 | R90: =VALUE(LEFT(Q90,4)) | S90: =VALUE(MID(Q90,6,2)) | T90: =VALUE(RIGHT(Q90,2)) | U90: days | V90: Multi-day event; anchored to first day
A91: 90 | B91: 1911-07-03 | C91: 1911-07-13 | D91: =VALUE(LEFT(B91,4)) | E91: =INT((D91-1)/100)+1 | F91: Heat wave | G91: July 1911 heat wave | H91: Northeast | I91: Albany 104°F (Jul 4 1911) — the all-time NY state & Albany record, still standing; 102°F Jul 3; 5 consecutive 90°F+ days (Jul 2–6) | J91: Albany | K91: ~4–6 local heat deaths (4 in Troy, 2 in Albany on the 4th); hundreds dead across the NE. Boston also 104°F, Vernon VT 105°F (state record), Portland ME 103°F — all Jul 4. | L91: NWS Albany ALB_Extremes (VERIFIED); contemporary reports | N91: A | O91: Y | P91: VERIFIED against NWS ALY ALB_Extremes: 104°F Jul 4 1911 is Albany's all-time high (records since 1874) and NY's hottest recorded moment. The 11-day wave ran Jul 4–15. | Q91: 1911-07-03 | R91: =VALUE(LEFT(Q91,4)) | S91: =VALUE(MID(Q91,6,2)) | T91: =VALUE(RIGHT(Q91,2)) | U91: days | V91: Multi-day event; anchored to first day
A92: 91 | B92: 1912-02-04 | C92: 1912-02-04 | D92: =VALUE(LEFT(B92,4)) | E92: =INT((D92-1)/100)+1 | F92: Ice jam | G92: Niagara ice bridge collapse (OUT OF REGION) | H92: Niagara Falls | I92: 3 killed | J92: none | K92: Ice bridge below the falls broke up with visitors on it; ended public access to the ice bridge. | L92: Wikipedia event article (secondary; verify against NCEI/NHC) | N92: B | O92: N | P92: Out of region. | Q92: 1912-02-04 | R92: =VALUE(LEFT(Q92,4)) | S92: =VALUE(MID(Q92,6,2)) | T92: =VALUE(RIGHT(Q92,2)) | U92: day | V92: Single-day event
A93: 92 | B93: 1913-03-25 | C93: 1913-03-28 | D93: =VALUE(LEFT(B93,4)) | E93: =INT((D93-1)/100)+1 | F93: River flood | G93: March 1913 flood | H93: Hudson & Mohawk | I93: Albany 21.45 ft; Troy 29.7 ft; Schenectady 228.9 ft | J93: Hudson at Albany/Troy; Mohawk at Schenectady | K93: Highest water on record Hadley/Glens Falls south through Troy. | L93: NWS Albany – Past Weather Events (weather.gov/aly/pastevents) | M93: https://www.weather.gov/aly/pastevents | N93: A | O93: Y | Q93: 1913-03-25 | R93: =VALUE(LEFT(Q93,4)) | S93: =VALUE(MID(Q93,6,2)) | T93: =VALUE(RIGHT(Q93,2)) | U93: days | V93: Multi-day event; anchored to first day
A94: 93 | B94: 1914-02-14 | C94: 1914-02-14 | D94: =VALUE(LEFT(B94,4)) | E94: =INT((D94-1)/100)+1 | F94: Blizzard | G94: February 1914 blizzard | H94: Eastern/central NY | I94: 23.5 in Albany; 20–30+ in elsewhere | J94: Albany | K94: Greatest February snowstorm for Albany; very cold and windy. | L94: NWS Albany – Past Weather Events (weather.gov/aly/pastevents) ; The Argus (Albany), Feb 15 1914 ("High Wind and Colder To-Day - Twenty-Six Inches of Snow") [uploaded PDF scan] | M94: https://www.weather.gov/aly/pastevents | N94: A | O94: Y | P94: 2026-09-22 (v828, atlas session): ENRICHED from research-chat intake row 347 (same event; merged, not added). A blizzard buried the Capital Region on Feb 13-14 1914, the worst since 1888. Snow began Fri night Feb 13 and fell heavily through Feb 14; the wind blew ~30 mph (later 18-24 mph), piling drifts 8-10 ft. Not a trolley car moved in Troy (collar-shop workers were stranded and a runaway car killed a team of horses); Schenectady was snowbound (GE workers stranded); trains ran 3-10 hours late (railroaders called it the worst since 1888) and Albany's mail was tied up for 3-4 days. At Cohoes ('the Spindle City') the storm was the worst since 1888 with ~30 in, closing the mills; in Albany's South End drifts ran 6-7 ft and an aged woman was briefly trapped in a drift; every hotel was crowded and the r || Key measurement per that source: ~26 in (headline) / ~35 in (body) snow at Albany - figures disagree within the scan; wind ~30 mph; drifts 8-10 ft || Intake notes: 2026-09-22: added per Laurie (PDF scan). In-core blizzard. DISCREPANCY FLAG: the scan gives conflicting Albany snow totals - the headline says 'Twenty-Six Inches' but the body says 'about 35 inches fell in Albany yesterday and Friday night'. Recorded both; confirm the correct total (and add A-grade | Q94: 1914-02-14 | R94: =VALUE(LEFT(Q94,4)) | S94: =VALUE(MID(Q94,6,2)) | T94: =VALUE(RIGHT(Q94,2)) | U94: day | V94: Single-day event
A95: 94 | B95: 1914-03-28 | C95: 1914-03-28 | D95: =VALUE(LEFT(B95,4)) | E95: =INT((D95-1)/100)+1 | F95: River flood (ice jam) | G95: March 1914 Schenectady flood of record | H95: Mohawk at Schenectady | I95: 232.9 ft | J95: Mohawk R. at Schenectady | K95: Ice jam; water reached Broadway, flooded ALCO plant. | L95: NWS Albany – Past Weather Events (weather.gov/aly/pastevents) | M95: https://www.weather.gov/aly/pastevents | N95: A | O95: Y | Q95: 1914-03-28 | R95: =VALUE(LEFT(Q95,4)) | S95: =VALUE(MID(Q95,6,2)) | T95: =VALUE(RIGHT(Q95,2)) | U95: day | V95: Single-day event
A96: 95 | B96: 1915-12-13 | C96: 1915-12-15 | D96: =VALUE(LEFT(B96,4)) | E96: =INT((D96-1)/100)+1 | F96: Snowstorm | G96: December 1915 snowstorm | H96: Eastern/SE NY | I96: 24.7 in Albany; 25–35 in regionally | J96: Albany | K96: 4th greatest storm for Albany; winter 1915–16 = 94.7 in. | L96: NWS Albany – Past Weather Events (weather.gov/aly/pastevents) | M96: https://www.weather.gov/aly/pastevents | N96: A | O96: Y | Q96: 1915-12-13 | R96: =VALUE(LEFT(Q96,4)) | S96: =VALUE(MID(Q96,6,2)) | T96: =VALUE(RIGHT(Q96,2)) | U96: days | V96: Multi-day event; anchored to first day
A97: 96 | B97: 1917-12-01 | C97: 1918-01-31 | D97: =VALUE(LEFT(B97,4)) | E97: =INT((D97-1)/100)+1 | F97: Cold winter | G97: Winter of 1917–18 | H97: Northeast | I97: Prolonged extreme cold | J97: regional | K97: Hudson locked; wartime coal famine. | L97: Wikipedia event article (secondary; verify against NCEI/NHC) | N97: B | O97: N | Q97: 1917-12-30 | R97: =VALUE(LEFT(Q97,4)) | S97: =VALUE(MID(Q97,6,2)) | T97: =VALUE(RIGHT(Q97,2)) | U97: days | V97: Dec 29–31, 1917 cold wave (records at NYC/Albany)
A98: 97 | B98: 1920-02-04 | C98: 1920-02-07 | D98: =VALUE(LEFT(B98,4)) | E98: =INT((D98-1)/100)+1 | F98: Nor'easter | G98: February 1920 storm | H98: NYC / Hudson Valley | I98: ~17 in NYC; heavier north | J98: NYC | K98: Paralyzed rail and river traffic. | L98: Wikipedia event article (secondary; verify against NCEI/NHC) | N98: B | O98: N | Q98: 1920-02-04 | R98: =VALUE(LEFT(Q98,4)) | S98: =VALUE(MID(Q98,6,2)) | T98: =VALUE(RIGHT(Q98,2)) | U98: days | V98: Multi-day event; anchored to first day
A99: 98 | B99: 1927-11-03 | C99: 1927-11-05 | D99: =VALUE(LEFT(B99,4)) | E99: =INT((D99-1)/100)+1 | F99: Rain flood (tropical remnant) | G99: November 1927 flood | H99: VT / eastern NY | I99: Albany 15.96 ft; Batten Kill 17.7 ft (record); Hoosic 18.8 ft | J99: Hudson at Albany | K99: Remains of late-season hurricane; devastation in VT; significant Hudson flood. | L99: NWS Albany – Past Weather Events (weather.gov/aly/pastevents) | M99: https://www.weather.gov/aly/pastevents | N99: A | O99: Y | Q99: 1927-11-03 | R99: =VALUE(LEFT(Q99,4)) | S99: =VALUE(MID(Q99,6,2)) | T99: =VALUE(RIGHT(Q99,2)) | U99: days | V99: Multi-day event; anchored to first day
A100: 99 | B100: 1928-01-31 | C100: 1928-01-31 | D100: =VALUE(LEFT(B100,4)) | E100: =INT((D100-1)/100)+1 | F100: Ice jam | G100: January 1928 Hudson–Mohawk confluence jam | H100: Tribes Hill / Cohoes area | I100: CRREL logged jam at the Hudson–Mohawk confluence | J100: CRREL | K100: One of the earliest 20th-c. records in the regional log. | L100: USACE CRREL Ice Jam Database, New York (Report_Region.csv, retrieved 2026-09-20) | M100: https://icejam.sec.usace.army.mil/ | N100: C | O100: Y | P100: CRREL record; no impact detail. | Q100: 1928-01-31 | R100: =VALUE(LEFT(Q100,4)) | S100: =VALUE(MID(Q100,6,2)) | T100: =VALUE(RIGHT(Q100,2)) | U100: day | V100: Single-day event
...

Sheet Wind & Tornadoes
A1: Date | B1: Time (local) | C1: County | D1: Place / path | E1: Type | F1: Rating / peak wind | G1: Path length (mi) | H1: Width (yd) | I1: Deaths | J1: Injuries | K1: Start lat | L1: Start lon | M1: End lat | N1: End lon | O1: Dist. from Westerlo, start (mi) | P1: Dist. from Westerlo, end (mi) | Q1: Nearest point (mi) | R1: Within radius? | S1: Source | T1: Confidence | U1: Notes
A2: 1821-07-08 | C2: Columbia | D2: Columbia Co. (Grazulis) | E2: Tornado | F2: FU | G2: 5.5 | H2: 100 | I2: 0 | J2: 0 | K2: 42.25 | L2: -73.62 | O2: =IF(OR(K2="",L2=""),"",ROUND(3959*ACOS(MIN(1,SIN(RADIANS(README!$B$3))*SIN(RADIANS(K2))+COS(RADIANS(README!$B$3))*COS(RADIANS(K2))*COS(RADIANS(L2-README!$B$4)))),1)) | P2: =IF(OR(M2="",N2=""),"",ROUND(3959*ACOS(MIN(1,SIN(RADIANS(README!$B$3))*SIN(RADIANS(M2))+COS(RADIANS(README!$B$3))*COS(RADIANS(M2))*COS(RADIANS(N2-README!$B$4)))),1)) | Q2: =IF(O2="","",IF(P2="",O2,MIN(O2,P2))) | R2: =IF(Q2="","n/a",IF(Q2<=README!$B$5,"Yes","No")) | S2: Grazulis via tornadopath | T2: C | U2: County centroid approx; pre-1950 F2+/deadly only
A3: 1867-06-16 | C3: Columbia | D3: Columbia Co. (Grazulis) | E3: Tornado | F3: FU | I3: 0 | J3: 0 | K3: 42.25 | L3: -73.62 | O3: =IF(OR(K3="",L3=""),"",ROUND(3959*ACOS(MIN(1,SIN(RADIANS(README!$B$3))*SIN(RADIANS(K3))+COS(RADIANS(README!$B$3))*COS(RADIANS(K3))*COS(RADIANS(L3-README!$B$4)))),1)) | P3: =IF(OR(M3="",N3=""),"",ROUND(3959*ACOS(MIN(1,SIN(RADIANS(README!$B$3))*SIN(RADIANS(M3))+COS(RADIANS(README!$B$3))*COS(RADIANS(M3))*COS(RADIANS(N3-README!$B$4)))),1)) | Q3: =IF(O3="","",IF(P3="",O3,MIN(O3,P3))) | R3: =IF(Q3="","n/a",IF(Q3<=README!$B$5,"Yes","No")) | S3: Grazulis via tornadopath | T3: C | U3: County centroid approx
A4: 1875-08-22 | B4: 16:56 | C4: Albany | D4: Albany Co. (Grazulis) | E4: Tornado | F4: F1 | I4: 2 | J4: 0 | K4: 42.6 | L4: -73.97 | O4: =IF(OR(K4="",L4=""),"",ROUND(3959*ACOS(MIN(1,SIN(RADIANS(README!$B$3))*SIN(RADIANS(K4))+COS(RADIANS(README!$B$3))*COS(RADIANS(K4))*COS(RADIANS(L4-README!$B$4)))),1)) | P4: =IF(OR(M4="",N4=""),"",ROUND(3959*ACOS(MIN(1,SIN(RADIANS(README!$B$3))*SIN(RADIANS(M4))+COS(RADIANS(README!$B$3))*COS(RADIANS(M4))*COS(RADIANS(N4-README!$B$4)))),1)) | Q4: =IF(O4="","",IF(P4="",O4,MIN(O4,P4))) | R4: =IF(Q4="","n/a",IF(Q4<=README!$B$5,"Yes","No")) | S4: Grazulis via tornadopath | T4: C | U4: 2 fatalities; county centroid approx
A5: 1877-07-16 | B5: 16:56 | C5: Columbia | D5: Columbia Co. (Grazulis) | E5: Tornado | F5: F1 | I5: 0 | J5: 0 | K5: 42.25 | L5: -73.62 | O5: =IF(OR(K5="",L5=""),"",ROUND(3959*ACOS(MIN(1,SIN(RADIANS(README!$B$3))*SIN(RADIANS(K5))+COS(RADIANS(README!$B$3))*COS(RADIANS(K5))*COS(RADIANS(L5-README!$B$4)))),1)) | P5: =IF(OR(M5="",N5=""),"",ROUND(3959*ACOS(MIN(1,SIN(RADIANS(README!$B$3))*SIN(RADIANS(M5))+COS(RADIANS(README!$B$3))*COS(RADIANS(M5))*COS(RADIANS(N5-README!$B$4)))),1)) | Q5: =IF(O5="","",IF(P5="",O5,MIN(O5,P5))) | R5: =IF(Q5="","n/a",IF(Q5<=README!$B$5,"Yes","No")) | S5: Grazulis via tornadopath | T5: C | U5: County centroid approx
A6: 1878-07-21 | B6: 18:20 | C6: Albany | D6: Albany Co. (Grazulis) | E6: Tornado | F6: F2 | G6: 0.5 | H6: 50 | I6: 0 | J6: 0 | K6: 42.6 | L6: -73.97 | O6: =IF(OR(K6="",L6=""),"",ROUND(3959*ACOS(MIN(1,SIN(RADIANS(README!$B$3))*SIN(RADIANS(K6))+COS(RADIANS(README!$B$3))*COS(RADIANS(K6))*COS(RADIANS(L6-README!$B$4)))),1)) | P6: =IF(OR(M6="",N6=""),"",ROUND(3959*ACOS(MIN(1,SIN(RADIANS(README!$B$3))*SIN(RADIANS(M6))+COS(RADIANS(README!$B$3))*COS(RADIANS(M6))*COS(RADIANS(N6-README!$B$4)))),1)) | Q6: =IF(O6="","",IF(P6="",O6,MIN(O6,P6))) | R6: =IF(Q6="","n/a",IF(Q6<=README!$B$5,"Yes","No")) | S6: Grazulis via tornadopath | T6: C | U6: County centroid approx
A7: 1879-07-16 | B7: 19:30 | C7: Greene | D7: Greene Co. (Grazulis) | E7: Tornado | F7: F2 | I7: 0 | J7: 0 | K7: 42.28 | L7: -74.12 | O7: =IF(OR(K7="",L7=""),"",ROUND(3959*ACOS(MIN(1,SIN(RADIANS(README!$B$3))*SIN(RADIANS(K7))+COS(RADIANS(README!$B$3))*COS(RADIANS(K7))*COS(RADIANS(L7-README!$B$4)))),1)) | P7: =IF(OR(M7="",N7=""),"",ROUND(3959*ACOS(MIN(1,SIN(RADIANS(README!$B$3))*SIN(RADIANS(M7))+COS(RADIANS(README!$B$3))*COS(RADIANS(M7))*COS(RADIANS(N7-README!$B$4)))),1)) | Q7: =IF(O7="","",IF(P7="",O7,MIN(O7,P7))) | R7: =IF(Q7="","n/a",IF(Q7<=README!$B$5,"Yes","No")) | S7: Grazulis via tornadopath | T7: C | U7: County centroid approx
A8: 1950-11-24 | B8: 18:30 | C8: Albany | D8: Albany (Great Appalachian Storm) | E8: Synoptic windstorm | F8: 83 mph gust | K8: 42.75 | L8: -73.8 | O8: =IF(OR(K8="",L8=""),"",ROUND(3959*ACOS(MIN(1,SIN(RADIANS(README!$B$3))*SIN(RADIANS(K8))+COS(RADIANS(README!$B$3))*COS(RADIANS(K8))*COS(RADIANS(L8-README!$B$4)))),1)) | P8: =IF(OR(M8="",N8=""),"",ROUND(3959*ACOS(MIN(1,SIN(RADIANS(README!$B$3))*SIN(RADIANS(M8))+COS(RADIANS(README!$B$3))*COS(RADIANS(M8))*COS(RADIANS(N8-README!$B$4)))),1)) | Q8: =IF(O8="","",IF(P8="",O8,MIN(O8,P8))) | R8: =IF(Q8="","n/a",IF(Q8<=README!$B$5,"Yes","No")) | S8: NWS Albany – Past Weather Events (weather.gov/aly/pastevents) | T8: A | U8: Strongest gust ever at Albany
A9: 1960-06-24 | B9: 17:30 | C9: Schenectady | D9: Schenectady Co. | E9: Tornado | F9: F3 | I9: 0 | J9: 9 | K9: 42.8 | L9: -73.88 | M9: 42.92 | N9: -73.73 | O9: =IF(OR(K9="",L9=""),"",ROUND(3959*ACOS(MIN(1,SIN(RADIANS(README!$B$3))*SIN(RADIANS(K9))+COS(RADIANS(README!$B$3))*COS(RADIANS(K9))*COS(RADIANS(L9-README!$B$4)))),1)) | P9: =IF(OR(M9="",N9=""),"",ROUND(3959*ACOS(MIN(1,SIN(RADIANS(README!$B$3))*SIN(RADIANS(M9))+COS(RADIANS(README!$B$3))*COS(RADIANS(M9))*COS(RADIANS(N9-README!$B$4)))),1)) | Q9: =IF(O9="","",IF(P9="",O9,MIN(O9,P9))) | R9: =IF(Q9="","n/a",IF(Q9<=README!$B$5,"Yes","No")) | S9: Tornado Project (Grazulis) NY county list 1950–2012 | T9: A | U9: ~$25M
A10: 1964-12-04 | C10: Region | D10: East-central NY | E10: Ice storm (not wind) | F10: 1.5 in ice | K10: 42.75 | L10: -73.8 | O10: =IF(OR(K10="",L10=""),"",ROUND(3959*ACOS(MIN(1,SIN(RADIANS(README!$B$3))*SIN(RADIANS(K10))+COS(RADIANS(README!$B$3))*COS(RADIANS(K10))*COS(RADIANS(L10-README!$B$4)))),1)) | P10: =IF(OR(M10="",N10=""),"",ROUND(3959*ACOS(MIN(1,SIN(RADIANS(README!$B$3))*SIN(RADIANS(M10))+COS(RADIANS(README!$B$3))*COS(RADIANS(M10))*COS(RADIANS(N10-README!$B$4)))),1)) | Q10: =IF(O10="","",IF(P10="",O10,MIN(O10,P10))) | R10: =IF(Q10="","n/a",IF(Q10<=README!$B$5,"Yes","No")) | S10: NWS Albany – Past Weather Events (weather.gov/aly/pastevents) | T10: A | U10: Listed for tree-damage comparison
A11: 1973-06-30 | B11: 16:15 | C11: Albany | D11: SW Albany Co. – Westerlo/Rensselaerville area | E11: Tornado | F11: F1 | G11: 1.3 | H11: 10 | I11: 0 | J11: 2 | K11: 42.55 | L11: -74.05 | O11: =IF(OR(K11="",L11=""),"",ROUND(3959*ACOS(MIN(1,SIN(RADIANS(README!$B$3))*SIN(RADIANS(K11))+COS(RADIANS(README!$B$3))*COS(RADIANS(K11))*COS(RADIANS(L11-README!$B$4)))),1)) | P11: =IF(OR(M11="",N11=""),"",ROUND(3959*ACOS(MIN(1,SIN(RADIANS(README!$B$3))*SIN(RADIANS(M11))+COS(RADIANS(README!$B$3))*COS(RADIANS(M11))*COS(RADIANS(N11-README!$B$4)))),1)) | Q11: =IF(O11="","",IF(P11="",O11,MIN(O11,P11))) | R11: =IF(Q11="","n/a",IF(Q11<=README!$B$5,"Yes","No")) | S11: Tornado Project (Grazulis) NY county list 1950–2012 | T11: A | U11: Touchdown ~2 mi from Westerlo hamlet
A12: 1973-08-28 | B12: 10:00 | C12: Rensselaer | D12: Rensselaer Co. | E12: Tornado | F12: F2 | G12: 2.3 | H12: 83 | I12: 0 | J12: 1 | K12: 42.9 | L12: -73.55 | M12: 42.92 | N12: -73.48 | O12: =IF(OR(K12="",L12=""),"",ROUND(3959*ACOS(MIN(1,SIN(RADIANS(README!$B$3))*SIN(RADIANS(K12))+COS(RADIANS(README!$B$3))*COS(RADIANS(K12))*COS(RADIANS(L12-README!$B$4)))),1)) | P12: =IF(OR(M12="",N12=""),"",ROUND(3959*ACOS(MIN(1,SIN(RADIANS(README!$B$3))*SIN(RADIANS(M12))+COS(RADIANS(README!$B$3))*COS(RADIANS(M12))*COS(RADIANS(N12-README!$B$4)))),1)) | Q12: =IF(O12="","",IF(P12="",O12,MIN(O12,P12))) | R12: =IF(Q12="","n/a",IF(Q12<=README!$B$5,"Yes","No")) | S12: Tornado Project (Grazulis) NY county list 1950–2012 | T12: A | U12: Same outbreak as Columbia F4
A13: 1973-08-28 | B13: 11:34 | C13: Columbia | D13: Stephentown area → MA | E13: Tornado | F13: F4 | G13: 3.4 | H13: 313 | I13: 0 | J13: 0 | K13: 42.42 | L13: -73.42 | M13: 42.37 | N13: -73.42 | O13: =IF(OR(K13="",L13=""),"",ROUND(3959*ACOS(MIN(1,SIN(RADIANS(README!$B$3))*SIN(RADIANS(K13))+COS(RADIANS(README!$B$3))*COS(RADIANS(K13))*COS(RADIANS(L13-README!$B$4)))),1)) | P13: =IF(OR(M13="",N13=""),"",ROUND(3959*ACOS(MIN(1,SIN(RADIANS(README!$B$3))*SIN(RADIANS(M13))+COS(RADIANS(README!$B$3))*COS(RADIANS(M13))*COS(RADIANS(N13-README!$B$4)))),1)) | Q13: =IF(O13="","",IF(P13="",O13,MIN(O13,P13))) | R13: =IF(Q13="","n/a",IF(Q13<=README!$B$5,"Yes","No")) | S13: Tornado Project (Grazulis) NY county list 1950–2012 | T13: A | U13: First recorded F4 in NY
A14: 1974-06-16 | B14: 11:10 | C14: Greene→Saratoga | D14: Catskill → Saratoga Co. | E14: Tornado | F14: F3 | G14: 49.1 | I14: 0 | J14: 0 | K14: 42.25 | L14: -73.83 | M14: 42.92 | N14: -73.88 | O14: =IF(OR(K14="",L14=""),"",ROUND(3959*ACOS(MIN(1,SIN(RADIANS(README!$B$3))*SIN(RADIANS(K14))+COS(RADIANS(README!$B$3))*COS(RADIANS(K14))*COS(RADIANS(L14-README!$B$4)))),1)) | P14: =IF(OR(M14="",N14=""),"",ROUND(3959*ACOS(MIN(1,SIN(RADIANS(README!$B$3))*SIN(RADIANS(M14))+COS(RADIANS(README!$B$3))*COS(RADIANS(M14))*COS(RADIANS(N14-README!$B$4)))),1)) | Q14: =IF(O14="","",IF(P14="",O14,MIN(O14,P14))) | R14: =IF(Q14="","n/a",IF(Q14<=README!$B$5,"Yes","No")) | S14: Tornado Project (Grazulis) NY county list 1950–2012 | T14: A | U14: Long track through Greene, Albany, Saratoga
A15: 1974-08-27 | B15: 16:00 | C15: Rensselaer | D15: Rensselaer Co. | E15: Tornado | F15: F1 | H15: 33 | I15: 0 | J15: 0 | K15: 42.83 | L15: -73.5 | O15: =IF(OR(K15="",L15=""),"",ROUND(3959*ACOS(MIN(1,SIN(RADIANS(README!$B$3))*SIN(RADIANS(K15))+COS(RADIANS(README!$B$3))*COS(RADIANS(K15))*COS(RADIANS(L15-README!$B$4)))),1)) | P15: =IF(OR(M15="",N15=""),"",ROUND(3959*ACOS(MIN(1,SIN(RADIANS(README!$B$3))*SIN(RADIANS(M15))+COS(RADIANS(README!$B$3))*COS(RADIANS(M15))*COS(RADIANS(N15-README!$B$4)))),1)) | Q15: =IF(O15="","",IF(P15="",O15,MIN(O15,P15))) | R15: =IF(Q15="","n/a",IF(Q15<=README!$B$5,"Yes","No")) | S15: Tornado Project (Grazulis) NY county list 1950–2012 | T15: A
A16: 1975-09-20 | B16: 17:30 | C16: Ulster→Columbia | D16: Kingston area → Columbia Co. | E16: Tornado | F16: F1 | G16: 7.1 | H16: 167 | I16: 0 | J16: 3 | K16: 41.97 | L16: -74.07 | M16: 42.08 | N16: -73.82 | O16: =IF(OR(K16="",L16=""),"",ROUND(3959*ACOS(MIN(1,SIN(RADIANS(README!$B$3))*SIN(RADIANS(K16))+COS(RADIANS(README!$B$3))*COS(RADIANS(K16))*COS(RADIANS(L16-README!$B$4)))),1)) | P16: =IF(OR(M16="",N16=""),"",ROUND(3959*ACOS(MIN(1,SIN(RADIANS(README!$B$3))*SIN(RADIANS(M16))+COS(RADIANS(README!$B$3))*COS(RADIANS(M16))*COS(RADIANS(N16-README!$B$4)))),1)) | Q16: =IF(O16="","",IF(P16="",O16,MIN(O16,P16))) | R16: =IF(Q16="","n/a",IF(Q16<=README!$B$5,"Yes","No")) | S16: Tornado Project (Grazulis) NY county list 1950–2012 | T16: A
A17: 1976-02-02 | C17: Albany | D17: Albany (flash freeze) | E17: Synoptic windstorm | F17: 67 mph gust | I17: 2 | K17: 42.75 | L17: -73.8 | O17: =IF(OR(K17="",L17=""),"",ROUND(3959*ACOS(MIN(1,SIN(RADIANS(README!$B$3))*SIN(RADIANS(K17))+COS(RADIANS(README!$B$3))*COS(RADIANS(K17))*COS(RADIANS(L17-README!$B$4)))),1)) | P17: =IF(OR(M17="",N17=""),"",ROUND(3959*ACOS(MIN(1,SIN(RADIANS(README!$B$3))*SIN(RADIANS(M17))+COS(RADIANS(README!$B$3))*COS(RADIANS(M17))*COS(RADIANS(N17-README!$B$4)))),1)) | Q17: =IF(O17="","",IF(P17="",O17,MIN(O17,P17))) | R17: =IF(Q17="","n/a",IF(Q17<=README!$B$5,"Yes","No")) | S17: NWS Albany – Past Weather Events (weather.gov/aly/pastevents) | T17: A | U17: 2 fatalities regionally
A18: 1977-04-02 | B18: 17:00 | C18: Greene | D18: W. Greene Co. | E18: Tornado | F18: F1 | G18: 1.8 | H18: 33 | I18: 0 | J18: 0 | K18: 42.2 | L18: -74.22 | O18: =IF(OR(K18="",L18=""),"",ROUND(3959*ACOS(MIN(1,SIN(RADIANS(README!$B$3))*SIN(RADIANS(K18))+COS(RADIANS(README!$B$3))*COS(RADIANS(K18))*COS(RADIANS(L18-README!$B$4)))),1)) | P18: =IF(OR(M18="",N18=""),"",ROUND(3959*ACOS(MIN(1,SIN(RADIANS(README!$B$3))*SIN(RADIANS(M18))+COS(RADIANS(README!$B$3))*COS(RADIANS(M18))*COS(RADIANS(N18-README!$B$4)))),1)) | Q18: =IF(O18="","",IF(P18="",O18,MIN(O18,P18))) | R18: =IF(Q18="","n/a",IF(Q18<=README!$B$5,"Yes","No")) | S18: Tornado Project (Grazulis) NY county list 1950–2012 | T18: A
A19: 1978-07-10 | B19: 14:45 | C19: Columbia | D19: Columbia Co. | E19: Tornado | F19: F1 | G19: 0.7 | H19: 53 | I19: 0 | J19: 0 | K19: 42.17 | L19: -73.75 | O19: =IF(OR(K19="",L19=""),"",ROUND(3959*ACOS(MIN(1,SIN(RADIANS(README!$B$3))*SIN(RADIANS(K19))+COS(RADIANS(README!$B$3))*COS(RADIANS(K19))*COS(RADIANS(L19-README!$B$4)))),1)) | P19: =IF(OR(M19="",N19=""),"",ROUND(3959*ACOS(MIN(1,SIN(RADIANS(README!$B$3))*SIN(RADIANS(M19))+COS(RADIANS(README!$B$3))*COS(RADIANS(M19))*COS(RADIANS(N19-README!$B$4)))),1)) | Q19: =IF(O19="","",IF(P19="",O19,MIN(O19,P19))) | R19: =IF(Q19="","n/a",IF(Q19<=README!$B$5,"Yes","No")) | S19: Tornado Project (Grazulis) NY county list 1950–2012 | T19: A
A20: 1980-07-11 | B20: 15:00 | C20: Albany | D20: Albany Co. | E20: Tornado | F20: F0 | G20: 0.2 | H20: 133 | I20: 0 | J20: 0 | K20: 42.57 | L20: -73.97 | O20: =IF(OR(K20="",L20=""),"",ROUND(3959*ACOS(MIN(1,SIN(RADIANS(README!$B$3))*SIN(RADIANS(K20))+COS(RADIANS(README!$B$3))*COS(RADIANS(K20))*COS(RADIANS(L20-README!$B$4)))),1)) | P20: =IF(OR(M20="",N20=""),"",ROUND(3959*ACOS(MIN(1,SIN(RADIANS(README!$B$3))*SIN(RADIANS(M20))+COS(RADIANS(README!$B$3))*COS(RADIANS(M20))*COS(RADIANS(N20-README!$B$4)))),1)) | Q20: =IF(O20="","",IF(P20="",O20,MIN(O20,P20))) | R20: =IF(Q20="","n/a",IF(Q20<=README!$B$5,"Yes","No")) | S20: Tornado Project (Grazulis) NY county list 1950–2012 | T20: A
A21: 1984-05-12 | B21: 13:25 | C21: Albany | D21: N. Albany Co. (Berne/Knox area) | E21: Tornado | F21: F0 | H21: 10 | I21: 0 | J21: 13 | K21: 42.7 | L21: -74.03 | O21: =IF(OR(K21="",L21=""),"",ROUND(3959*ACOS(MIN(1,SIN(RADIANS(README!$B$3))*SIN(RADIANS(K21))+COS(RADIANS(README!$B$3))*COS(RADIANS(K21))*COS(RADIANS(L21-README!$B$4)))),1)) | P21: =IF(OR(M21="",N21=""),"",ROUND(3959*ACOS(MIN(1,SIN(RADIANS(README!$B$3))*SIN(RADIANS(M21))+COS(RADIANS(README!$B$3))*COS(RADIANS(M21))*COS(RADIANS(N21-README!$B$4)))),1)) | Q21: =IF(O21="","",IF(P21="",O21,MIN(O21,P21))) | R21: =IF(Q21="","n/a",IF(Q21<=README!$B$5,"Yes","No")) | S21: Tornado Project (Grazulis) NY county list 1950–2012 | T21: A | U21: 13 injuries
A22: 1986-10-01 | B22: 00:00 | C22: Delaware | D22: NE Delaware Co. | E22: Tornado | F22: F2 | I22: 0 | J22: 0 | K22: 42.28 | L22: -74.57 | O22: =IF(OR(K22="",L22=""),"",ROUND(3959*ACOS(MIN(1,SIN(RADIANS(README!$B$3))*SIN(RADIANS(K22))+COS(RADIANS(README!$B$3))*COS(RADIANS(K22))*COS(RADIANS(L22-README!$B$4)))),1)) | P22: =IF(OR(M22="",N22=""),"",ROUND(3959*ACOS(MIN(1,SIN(RADIANS(README!$B$3))*SIN(RADIANS(M22))+COS(RADIANS(README!$B$3))*COS(RADIANS(M22))*COS(RADIANS(N22-README!$B$4)))),1)) | Q22: =IF(O22="","",IF(P22="",O22,MIN(O22,P22))) | R22: =IF(Q22="","n/a",IF(Q22<=README!$B$5,"Yes","No")) | S22: Tornado Project (Grazulis) NY county list 1950–2012 | T22: A
A23: 1987-10-04 | C23: Region | D23: Leaf-on snowstorm (tree damage) | E23: Snow load (not wind) | K23: 42.75 | L23: -73.8 | O23: =IF(OR(K23="",L23=""),"",ROUND(3959*ACOS(MIN(1,SIN(RADIANS(README!$B$3))*SIN(RADIANS(K23))+COS(RADIANS(README!$B$3))*COS(RADIANS(K23))*COS(RADIANS(L23-README!$B$4)))),1)) | P23: =IF(OR(M23="",N23=""),"",ROUND(3959*ACOS(MIN(1,SIN(RADIANS(README!$B$3))*SIN(RADIANS(M23))+COS(RADIANS(README!$B$3))*COS(RADIANS(M23))*COS(RADIANS(N23-README!$B$4)))),1)) | Q23: =IF(O23="","",IF(P23="",O23,MIN(O23,P23))) | R23: =IF(Q23="","n/a",IF(Q23<=README!$B$5,"Yes","No")) | S23: NWS Albany – Past Weather Events (weather.gov/aly/pastevents) | T23: A | U23: Listed for tree-damage comparison
A24: 1989-07-10 | B24: 12:40 | C24: Montgomery→Greene | D24: Ames → Schoharie → Rensselaerville → East Durham | E24: Tornado family | F24: F4 | G24: 42 | H24: 1320 | I24: 0 | J24: 20 | K24: 42.83 | L24: -74.53 | M24: 42.38 | N24: -74.03 | O24: =IF(OR(K24="",L24=""),"",ROUND(3959*ACOS(MIN(1,SIN(RADIANS(README!$B$3))*SIN(RADIANS(K24))+COS(RADIANS(README!$B$3))*COS(RADIANS(K24))*COS(RADIANS(L24-README!$B$4)))),1)) | P24: =IF(OR(M24="",N24=""),"",ROUND(3959*ACOS(MIN(1,SIN(RADIANS(README!$B$3))*SIN(RADIANS(M24))+COS(RADIANS(README!$B$3))*COS(RADIANS(M24))*COS(RADIANS(N24-README!$B$4)))),1)) | Q24: =IF(O24="","",IF(P24="",O24,MIN(O24,P24))) | R24: =IF(Q24="","n/a",IF(Q24<=README!$B$5,"Yes","No")) | S24: Wikipedia / NWS / Grazulis | T24: A | U24: Only F4 in NY; brief touchdowns near Rensselaerville and Greenville; path within a few miles of Westerlo
A25: 1989-11-16 | B25: 13:30 | C25: Rensselaer | D25: Rensselaer Co. | E25: Tornado | F25: F0 | G25: 0.1 | H25: 17 | I25: 0 | J25: 0 | K25: 42.95 | L25: -73.43 | O25: =IF(OR(K25="",L25=""),"",ROUND(3959*ACOS(MIN(1,SIN(RADIANS(README!$B$3))*SIN(RADIANS(K25))+COS(RADIANS(README!$B$3))*COS(RADIANS(K25))*COS(RADIANS(L25-README!$B$4)))),1)) | P25: =IF(OR(M25="",N25=""),"",ROUND(3959*ACOS(MIN(1,SIN(RADIANS(README!$B$3))*SIN(RADIANS(M25))+COS(RADIANS(README!$B$3))*COS(RADIANS(M25))*COS(RADIANS(N25-README!$B$4)))),1)) | Q25: =IF(O25="","",IF(P25="",O25,MIN(O25,P25))) | R25: =IF(Q25="","n/a",IF(Q25<=README!$B$5,"Yes","No")) | S25: Tornado Project (Grazulis) NY county list 1950–2012 | T25: A | U25: Same day as Coldenham downburst
A26: 1990-04-28 | B26: 12:30 | C26: Greene | D26: Greene Co. | E26: Tornado | F26: F0 | G26: 0.2 | H26: 10 | I26: 0 | J26: 1 | K26: 42.2 | L26: -73.97 | O26: =IF(OR(K26="",L26=""),"",ROUND(3959*ACOS(MIN(1,SIN(RADIANS(README!$B$3))*SIN(RADIANS(K26))+COS(RADIANS(README!$B$3))*COS(RADIANS(K26))*COS(RADIANS(L26-README!$B$4)))),1)) | P26: =IF(OR(M26="",N26=""),"",ROUND(3959*ACOS(MIN(1,SIN(RADIANS(README!$B$3))*SIN(RADIANS(M26))+COS(RADIANS(README!$B$3))*COS(RADIANS(M26))*COS(RADIANS(N26-README!$B$4)))),1)) | Q26: =IF(O26="","",IF(P26="",O26,MIN(O26,P26))) | R26: =IF(Q26="","n/a",IF(Q26<=README!$B$5,"Yes","No")) | S26: Tornado Project (Grazulis) NY county list 1950–2012 | T26: A
A27: 1990-08-28 | B27: 19:30 | C27: Albany | D27: Bozenkill Rd, Knox (Peterson farm) | E27: Tornado | F27: F0 | G27: 0.3 | H27: 7 | I27: 0 | J27: 0 | K27: 42.75 | L27: -74.1 | O27: =IF(OR(K27="",L27=""),"",ROUND(3959*ACOS(MIN(1,SIN(RADIANS(README!$B$3))*SIN(RADIANS(K27))+COS(RADIANS(README!$B$3))*COS(RADIANS(K27))*COS(RADIANS(L27-README!$B$4)))),1)) | P27: =IF(OR(M27="",N27=""),"",ROUND(3959*ACOS(MIN(1,SIN(RADIANS(README!$B$3))*SIN(RADIANS(M27))+COS(RADIANS(README!$B$3))*COS(RADIANS(M27))*COS(RADIANS(N27-README!$B$4)))),1)) | Q27: =IF(O27="","",IF(P27="",O27,MIN(O27,P27))) | R27: =IF(Q27="","n/a",IF(Q27<=README!$B$5,"Yes","No")) | S27: Tornado Project (Grazulis) NY county list 1950–2012 | T27: A | U27: CONFIRMED — the 1990 Bozenkill Rd (Knox) tornado toppled Carl Peterson's silo, per Peterson himself (Altamont Enterprise 4 Mar 2010 & 29 May 2014). Peterson farm = recurring-disaster site: 1990 tornado (silo) + Feb 2010 snow-load barn collapse (70+ cows, 4 lost).
A28: 1992-05-02 | B28: 14:05 | C28: Schoharie | D28: Schoharie Co. | E28: Tornado | F28: F1 | G28: 6 | H28: 73 | I28: 0 | J28: 0 | K28: 42.67 | L28: -74.45 | M28: 42.6 | N28: -74.35 | O28: =IF(OR(K28="",L28=""),"",ROUND(3959*ACOS(MIN(1,SIN(RADIANS(README!$B$3))*SIN(RADIANS(K28))+COS(RADIANS(README!$B$3))*COS(RADIANS(K28))*COS(RADIANS(L28-README!$B$4)))),1)) | P28: =IF(OR(M28="",N28=""),"",ROUND(3959*ACOS(MIN(1,SIN(RADIANS(README!$B$3))*SIN(RADIANS(M28))+COS(RADIANS(README!$B$3))*COS(RADIANS(M28))*COS(RADIANS(N28-README!$B$4)))),1)) | Q28: =IF(O28="","",IF(P28="",O28,MIN(O28,P28))) | R28: =IF(Q28="","n/a",IF(Q28<=README!$B$5,"Yes","No")) | S28: Tornado Project (Grazulis) NY county list 1950–2012 | T28: A
A29: 1992-05-02 | B29: 14:25 | C29: Rensselaer | D29: Rensselaer Co. (2 tornadoes) | E29: Tornado | F29: F1 | G29: 2 | H29: 100 | I29: 0 | J29: 0 | K29: 42.7 | L29: -73.38 | O29: =IF(OR(K29="",L29=""),"",ROUND(3959*ACOS(MIN(1,SIN(RADIANS(README!$B$3))*SIN(RADIANS(K29))+COS(RADIANS(README!$B$3))*COS(RADIANS(K29))*COS(RADIANS(L29-README!$B$4)))),1)) | P29: =IF(OR(M29="",N29=""),"",ROUND(3959*ACOS(MIN(1,SIN(RADIANS(README!$B$3))*SIN(RADIANS(M29))+COS(RADIANS(README!$B$3))*COS(RADIANS(M29))*COS(RADIANS(N29-README!$B$4)))),1)) | Q29: =IF(O29="","",IF(P29="",O29,MIN(O29,P29))) | R29: =IF(Q29="","n/a",IF(Q29<=README!$B$5,"Yes","No")) | S29: Tornado Project (Grazulis) NY county list 1950–2012 | T29: A | U29: Two F1s same time/place
A30: 1992-06-24 | B30: 14:30 | C30: Montgomery | D30: Montgomery Co. | E30: Tornado | F30: F1 | I30: 0 | J30: 0 | K30: 42.93 | L30: -74.18 | O30: =IF(OR(K30="",L30=""),"",ROUND(3959*ACOS(MIN(1,SIN(RADIANS(README!$B$3))*SIN(RADIANS(K30))+COS(RADIANS(README!$B$3))*COS(RADIANS(K30))*COS(RADIANS(L30-README!$B$4)))),1)) | P30: =IF(OR(M30="",N30=""),"",ROUND(3959*ACOS(MIN(1,SIN(RADIANS(README!$B$3))*SIN(RADIANS(M30))+COS(RADIANS(README!$B$3))*COS(RADIANS(M30))*COS(RADIANS(N30-README!$B$4)))),1)) | Q30: =IF(O30="","",IF(P30="",O30,MIN(O30,P30))) | R30: =IF(Q30="","n/a",IF(Q30<=README!$B$5,"Yes","No")) | S30: Tornado Project (Grazulis) NY county list 1950–2012 | T30: A
A31: 1993-09-10 | B31: 13:40 | C31: Ulster | D31: N. Ulster Co. | E31: Tornado | F31: F1 | I31: 0 | J31: 0 | K31: 42.08 | L31: -73.95 | O31: =IF(OR(K31="",L31=""),"",ROUND(3959*ACOS(MIN(1,SIN(RADIANS(README!$B$3))*SIN(RADIANS(K31))+COS(RADIANS(README!$B$3))*COS(RADIANS(K31))*COS(RADIANS(L31-README!$B$4)))),1)) | P31: =IF(OR(M31="",N31=""),"",ROUND(3959*ACOS(MIN(1,SIN(RADIANS(README!$B$3))*SIN(RADIANS(M31))+COS(RADIANS(README!$B$3))*COS(RADIANS(M31))*COS(RADIANS(N31-README!$B$4)))),1)) | Q31: =IF(O31="","",IF(P31="",O31,MIN(O31,P31))) | R31: =IF(Q31="","n/a",IF(Q31<=README!$B$5,"Yes","No")) | S31: Tornado Project (Grazulis) NY county list 1950–2012 | T31: A
A32: 1994-04-27 | B32: 12:30 | C32: Rensselaer | D32: Rensselaer Co. | E32: Tornado | F32: F1 | G32: 1.5 | H32: 25 | I32: 0 | J32: 0 | K32: 42.95 | L32: -73.4 | O32: =IF(OR(K32="",L32=""),"",ROUND(3959*ACOS(MIN(1,SIN(RADIANS(README!$B$3))*SIN(RADIANS(K32))+COS(RADIANS(README!$B$3))*COS(RADIANS(K32))*COS(RADIANS(L32-README!$B$4)))),1)) | P32: =IF(OR(M32="",N32=""),"",ROUND(3959*ACOS(MIN(1,SIN(RADIANS(README!$B$3))*SIN(RADIANS(M32))+COS(RADIANS(README!$B$3))*COS(RADIANS(M32))*COS(RADIANS(N32-README!$B$4)))),1)) | Q32: =IF(O32="","",IF(P32="",O32,MIN(O32,P32))) | R32: =IF(Q32="","n/a",IF(Q32<=README!$B$5,"Yes","No")) | S32: Tornado Project (Grazulis) NY county list 1950–2012 | T32: A
A33: 1995-05-29 | B33: 16:40 | C33: Columbia | D33: Hillsdale → Great Barrington MA | E33: Tornado | F33: F2 | G33: 15 | H33: 300 | I33: 0 | J33: 5 | K33: 42.2 | L33: -73.78 | M33: 42.2 | N33: -73.52 | O33: =IF(OR(K33="",L33=""),"",ROUND(3959*ACOS(MIN(1,SIN(RADIANS(README!$B$3))*SIN(RADIANS(K33))+COS(RADIANS(README!$B$3))*COS(RADIANS(K33))*COS(RADIANS(L33-README!$B$4)))),1)) | P33: =IF(OR(M33="",N33=""),"",ROUND(3959*ACOS(MIN(1,SIN(RADIANS(README!$B$3))*SIN(RADIANS(M33))+COS(RADIANS(README!$B$3))*COS(RADIANS(M33))*COS(RADIANS(N33-README!$B$4)))),1)) | Q33: =IF(O33="","",IF(P33="",O33,MIN(O33,P33))) | R33: =IF(Q33="","n/a",IF(Q33<=README!$B$5,"Yes","No")) | S33: Tornado Project (Grazulis) NY county list 1950–2012 | T33: A
A34: 1995-07-15 | C34: Albany/Adirondacks | D34: Adirondack derecho | E34: Derecho | F34: 100+ mph | I34: 1 | K34: 42.75 | L34: -73.8 | O34: =IF(OR(K34="",L34=""),"",ROUND(3959*ACOS(MIN(1,SIN(RADIANS(README!$B$3))*SIN(RADIANS(K34))+COS(RADIANS(README!$B$3))*COS(RADIANS(K34))*COS(RADIANS(L34-README!$B$4)))),1)) | P34: =IF(OR(M34="",N34=""),"",ROUND(3959*ACOS(MIN(1,SIN(RADIANS(README!$B$3))*SIN(RADIANS(M34))+COS(RADIANS(README!$B$3))*COS(RADIANS(M34))*COS(RADIANS(N34-README!$B$4)))),1)) | Q34: =IF(O34="","",IF(P34="",O34,MIN(O34,P34))) | R34: =IF(Q34="","n/a",IF(Q34<=README!$B$5,"Yes","No")) | S34: NCEI Storm Events Database | T34: A | U34: 1 death in Albany County per NCEI
A35: 1997-07-03 | B35: 15:23 | C35: Columbia | D35: Columbia Co. | E35: Tornado | F35: F1 | G35: 5.3 | H35: 100 | I35: 0 | J35: 0 | K35: 42.12 | L35: -73.6 | M35: 42.15 | N35: -73.48 | O35: =IF(OR(K35="",L35=""),"",ROUND(3959*ACOS(MIN(1,SIN(RADIANS(README!$B$3))*SIN(RADIANS(K35))+COS(RADIANS(README!$B$3))*COS(RADIANS(K35))*COS(RADIANS(L35-README!$B$4)))),1)) | P35: =IF(OR(M35="",N35=""),"",ROUND(3959*ACOS(MIN(1,SIN(RADIANS(README!$B$3))*SIN(RADIANS(M35))+COS(RADIANS(README!$B$3))*COS(RADIANS(M35))*COS(RADIANS(N35-README!$B$4)))),1)) | Q35: =IF(O35="","",IF(P35="",O35,MIN(O35,P35))) | R35: =IF(Q35="","n/a",IF(Q35<=README!$B$5,"Yes","No")) | S35: Tornado Project (Grazulis) NY county list 1950–2012 | T35: A
A36: 1997-07-03 | B36: 17:17 | C36: Columbia | D36: Columbia Co. | E36: Tornado | F36: F1 | G36: 1.2 | H36: 200 | I36: 0 | J36: 0 | K36: 42.4 | L36: -73.43 | M36: 42.4 | N36: -73.42 | O36: =IF(OR(K36="",L36=""),"",ROUND(3959*ACOS(MIN(1,SIN(RADIANS(README!$B$3))*SIN(RADIANS(K36))+COS(RADIANS(README!$B$3))*COS(RADIANS(K36))*COS(RADIANS(L36-README!$B$4)))),1)) | P36: =IF(OR(M36="",N36=""),"",ROUND(3959*ACOS(MIN(1,SIN(RADIANS(README!$B$3))*SIN(RADIANS(M36))+COS(RADIANS(README!$B$3))*COS(RADIANS(M36))*COS(RADIANS(N36-README!$B$4)))),1)) | Q36: =IF(O36="","",IF(P36="",O36,MIN(O36,P36))) | R36: =IF(Q36="","n/a",IF(Q36<=README!$B$5,"Yes","No")) | S36: Tornado Project (Grazulis) NY county list 1950–2012 | T36: A
A37: 1997-07-03 | B37: 17:20 | C37: Columbia | D37: Columbia Co. → MA | E37: Tornado | F37: F2 | G37: 1 | H37: 100 | I37: 0 | J37: 0 | K37: 42.4 | L37: -73.42 | M37: 42.38 | N37: -73.57 | O37: =IF(OR(K37="",L37=""),"",ROUND(3959*ACOS(MIN(1,SIN(RADIANS(README!$B$3))*SIN(RADIANS(K37))+COS(RADIANS(README!$B$3))*COS(RADIANS(K37))*COS(RADIANS(L37-README!$B$4)))),1)) | P37: =IF(OR(M37="",N37=""),"",ROUND(3959*ACOS(MIN(1,SIN(RADIANS(README!$B$3))*SIN(RADIANS(M37))+COS(RADIANS(README!$B$3))*COS(RADIANS(M37))*COS(RADIANS(N37-README!$B$4)))),1)) | Q37: =IF(O37="","",IF(P37="",O37,MIN(O37,P37))) | R37: =IF(Q37="","n/a",IF(Q37<=README!$B$5,"Yes","No")) | S37: Tornado Project (Grazulis) NY county list 1950–2012 | T37: A
A38: 1998-05-31 | B38: 14:22 | C38: Saratoga→Rensselaer | D38: Mechanicville–Stillwater | E38: Tornado | F38: F3 | G38: 20.3 | H38: 970 | I38: 0 | J38: 68 | K38: 42.92 | L38: -73.77 | M38: 42.93 | N38: -73.27 | O38: =IF(OR(K38="",L38=""),"",ROUND(3959*ACOS(MIN(1,SIN(RADIANS(README!$B$3))*SIN(RADIANS(K38))+COS(RADIANS(README!$B$3))*COS(RADIANS(K38))*COS(RADIANS(L38-README!$B$4)))),1)) | P38: =IF(OR(M38="",N38=""),"",ROUND(3959*ACOS(MIN(1,SIN(RADIANS(README!$B$3))*SIN(RADIANS(M38))+COS(RADIANS(README!$B$3))*COS(RADIANS(M38))*COS(RADIANS(N38-README!$B$4)))),1)) | Q38: =IF(O38="","",IF(P38="",O38,MIN(O38,P38))) | R38: =IF(Q38="","n/a",IF(Q38<=README!$B$5,"Yes","No")) | S38: Tornado Project (Grazulis) NY county list 1950–2012 | T38: A | U38: >$60M; part of derecho
A39: 1998-05-31 | B39: 14:37 | C39: Albany | D39: Albany Co. | E39: Tornado | F39: F1 | G39: 3.5 | H39: 75 | I39: 0 | J39: 0 | K39: 42.73 | L39: -73.87 | M39: 42.75 | N39: -73.77 | O39: =IF(OR(K39="",L39=""),"",ROUND(3959*ACOS(MIN(1,SIN(RADIANS(README!$B$3))*SIN(RADIANS(K39))+COS(RADIANS(README!$B$3))*COS(RADIANS(K39))*COS(RADIANS(L39-README!$B$4)))),1)) | P39: =IF(OR(M39="",N39=""),"",ROUND(3959*ACOS(MIN(1,SIN(RADIANS(README!$B$3))*SIN(RADIANS(M39))+COS(RADIANS(README!$B$3))*COS(RADIANS(M39))*COS(RADIANS(N39-README!$B$4)))),1)) | Q39: =IF(O39="","",IF(P39="",O39,MIN(O39,P39))) | R39: =IF(Q39="","n/a",IF(Q39<=README!$B$5,"Yes","No")) | S39: Tornado Project (Grazulis) NY county list 1950–2012 | T39: A
A40: 1998-05-31 | B40: 17:22 | C40: Rensselaer | D40: Rensselaer Co. | E40: Tornado | F40: F2 | G40: 8 | H40: 200 | I40: 0 | J40: 0 | K40: 42.58 | L40: -73.65 | M40: 42.6 | N40: -73.52 | O40: =IF(OR(K40="",L40=""),"",ROUND(3959*ACOS(MIN(1,SIN(RADIANS(README!$B$3))*SIN(RADIANS(K40))+COS(RADIANS(README!$B$3))*COS(RADIANS(K40))*COS(RADIANS(L40-README!$B$4)))),1)) | P40: =IF(OR(M40="",N40=""),"",ROUND(3959*ACOS(MIN(1,SIN(RADIANS(README!$B$3))*SIN(RADIANS(M40))+COS(RADIANS(README!$B$3))*COS(RADIANS(M40))*COS(RADIANS(N40-README!$B$4)))),1)) | Q40: =IF(O40="","",IF(P40="",O40,MIN(O40,P40))) | R40: =IF(Q40="","n/a",IF(Q40<=README!$B$5,"Yes","No")) | S40: Tornado Project (Grazulis) NY county list 1950–2012 | T40: A
A41: 2002-08-14 | C41: Albany | D41: Guilderland — worst in Guilderland Center & Fort Hunter | E41: Thunderstorm wind (microburst) | I41: 0 | J41: 9 | K41: 42.698 | L41: -74.058 | O41: =IF(OR(K41="",L41=""),"",ROUND(3959*ACOS(MIN(1,SIN(RADIANS(README!$B$3))*SIN(RADIANS(K41))+COS(RADIANS(README!$B$3))*COS(RADIANS(K41))*COS(RADIANS(L41-README!$B$4)))),1)) | P41: =IF(OR(M41="",N41=""),"",ROUND(3959*ACOS(MIN(1,SIN(RADIANS(README!$B$3))*SIN(RADIANS(M41))+COS(RADIANS(README!$B$3))*COS(RADIANS(M41))*COS(RADIANS(N41-README!$B$4)))),1)) | Q41: =IF(O41="","",IF(P41="",O41,MIN(O41,P41))) | R41: =IF(Q41="","n/a",IF(Q41<=README!$B$5,"Yes","No")) | S41: NCEI Storm Events Database | T41: A | U41: Microburst ~4pm Wed 14 Aug 2002; state of emergency declared (Supervisor Runion). Worst damage Guilderland Center & Fort Hunter: numerous homes with trees on/through roofs; high school roof damaged; highway-dept roof ripped off; animal-shelter fence torn down; 1 woman injured (tree on her car, hospitalized, 'good condition'). NCEI final tally 9 injuries, 0 deaths. Coords corrected from the NCEI county centroid (42.75,-73.80) to Guilderland Center per Altamont Enterprise 15 Aug 2002 (Matteson & Barr). 2026-09-23 (v853, atlas session): Enterprise Aug 22 2002 — hit ~3:50 p.m. Wed Aug 14, over in 15 min; NWS (Westergard) microburst, pulse-type storm; helicopter survey showed a 'snow cone' path that touched down and skipped; hardest hit Guilderland Center (highway-garage roof off, poles down on Depot Rd) and the Lone Pine area off Carman Rd (E. Lydius St, Lone Pine St, Spawn Rd, Benjamin) — two homes condemned, 12-in limbs as projectiles; also Fort Hunter, Hemboldt/Curry Rds; state of emergency for Fort Hunter and Guilderland Center; no serious injuries.
A42: 2003-07-21 | B42: 18:14 | C42: Greene | D42: Greene Co. | E42: Tornado | F42: F1 | G42: 0.5 | H42: 50 | I42: 0 | J42: 0 | K42: 42.18 | L42: -74.02 | O42: =IF(OR(K42="",L42=""),"",ROUND(3959*ACOS(MIN(1,SIN(RADIANS(README!$B$3))*SIN(RADIANS(K42))+COS(RADIANS(README!$B$3))*COS(RADIANS(K42))*COS(RADIANS(L42-README!$B$4)))),1)) | P42: =IF(OR(M42="",N42=""),"",ROUND(3959*ACOS(MIN(1,SIN(RADIANS(README!$B$3))*SIN(RADIANS(M42))+COS(RADIANS(README!$B$3))*COS(RADIANS(M42))*COS(RADIANS(N42-README!$B$4)))),1)) | Q42: =IF(O42="","",IF(P42="",O42,MIN(O42,P42))) | R42: =IF(Q42="","n/a",IF(Q42<=README!$B$5,"Yes","No")) | S42: Tornado Project (Grazulis) NY county list 1950–2012 | T42: A
A43: 2003-07-21 | B43: 18:23 | C43: Greene | D43: Greene Co. (Coxsackie area) | E43: Tornado | F43: F2 | G43: 1.5 | H43: 150 | I43: 0 | J43: 7 | K43: 42.2 | L43: -73.97 | M43: 42.22 | N43: -73.87 | O43: =IF(OR(K43="",L43=""),"",ROUND(3959*ACOS(MIN(1,SIN(RADIANS(README!$B$3))*SIN(RADIANS(K43))+COS(RADIANS(README!$B$3))*COS(RADIANS(K43))*COS(RADIANS(L43-README!$B$4)))),1)) | P43: =IF(OR(M43="",N43=""),"",ROUND(3959*ACOS(MIN(1,SIN(RADIANS(README!$B$3))*SIN(RADIANS(M43))+COS(RADIANS(README!$B$3))*COS(RADIANS(M43))*COS(RADIANS(N43-README!$B$4)))),1)) | Q43: =IF(O43="","",IF(P43="",O43,MIN(O43,P43))) | R43: =IF(Q43="","n/a",IF(Q43<=README!$B$5,"Yes","No")) | S43: Tornado Project (Grazulis) NY county list 1950–2012 | T43: A | U43: 7 injuries
A44: 2003-07-21 | B44: 18:24 | C44: Greene | D44: Greene Co. | E44: Tornado | F44: F1 | G44: 0.5 | H44: 50 | I44: 0 | J44: 0 | K44: 42.27 | L44: -73.82 | O44: =IF(OR(K44="",L44=""),"",ROUND(3959*ACOS(MIN(1,SIN(RADIANS(README!$B$3))*SIN(RADIANS(K44))+COS(RADIANS(README!$B$3))*COS(RADIANS(K44))*COS(RADIANS(L44-README!$B$4)))),1)) | P44: =IF(OR(M44="",N44=""),"",ROUND(3959*ACOS(MIN(1,SIN(RADIANS(README!$B$3))*SIN(RADIANS(M44))+COS(RADIANS(README!$B$3))*COS(RADIANS(M44))*COS(RADIANS(N44-README!$B$4)))),1)) | Q44: =IF(O44="","",IF(P44="",O44,MIN(O44,P44))) | R44: =IF(Q44="","n/a",IF(Q44<=README!$B$5,"Yes","No")) | S44: Tornado Project (Grazulis) NY county list 1950–2012 | T44: A
A45: 2003-07-21 | B45: 18:30 | C45: Greene | D45: Greene Co. | E45: Tornado | F45: F1 | G45: 0.5 | H45: 150 | I45: 0 | J45: 0 | K45: 42.35 | L45: -73.8 | O45: =IF(OR(K45="",L45=""),"",ROUND(3959*ACOS(MIN(1,SIN(RADIANS(README!$B$3))*SIN(RADIANS(K45))+COS(RADIANS(README!$B$3))*COS(RADIANS(K45))*COS(RADIANS(L45-README!$B$4)))),1)) | P45: =IF(OR(M45="",N45=""),"",ROUND(3959*ACOS(MIN(1,SIN(RADIANS(README!$B$3))*SIN(RADIANS(M45))+COS(RADIANS(README!$B$3))*COS(RADIANS(M45))*COS(RADIANS(N45-README!$B$4)))),1)) | Q45: =IF(O45="","",IF(P45="",O45,MIN(O45,P45))) | R45: =IF(Q45="","n/a",IF(Q45<=README!$B$5,"Yes","No")) | S45: Tornado Project (Grazulis) NY county list 1950–2012 | T45: A
A46: 2003-07-21 | B46: 18:32 | C46: Columbia | D46: Columbia Co. | E46: Tornado | F46: F1 | G46: 1.8 | H46: 90 | I46: 0 | J46: 0 | K46: 42.43 | L46: -73.67 | O46: =IF(OR(K46="",L46=""),"",ROUND(3959*ACOS(MIN(1,SIN(RADIANS(README!$B$3))*SIN(RADIANS(K46))+COS(RADIANS(README!$B$3))*COS(RADIANS(K46))*COS(RADIANS(L46-README!$B$4)))),1)) | P46: =IF(OR(M46="",N46=""),"",ROUND(3959*ACOS(MIN(1,SIN(RADIANS(README!$B$3))*SIN(RADIANS(M46))+COS(RADIANS(README!$B$3))*COS(RADIANS(M46))*COS(RADIANS(N46-README!$B$4)))),1)) | Q46: =IF(O46="","",IF(P46="",O46,MIN(O46,P46))) | R46: =IF(Q46="","n/a",IF(Q46<=README!$B$5,"Yes","No")) | S46: Tornado Project (Grazulis) NY county list 1950–2012 | T46: A
A47: 2003-07-21 | B47: 18:35 | C47: Columbia | D47: Columbia Co. | E47: Tornado | F47: F0 | G47: 0.4 | H47: 125 | I47: 0 | J47: 0 | K47: 42.35 | L47: -73.78 | O47: =IF(OR(K47="",L47=""),"",ROUND(3959*ACOS(MIN(1,SIN(RADIANS(README!$B$3))*SIN(RADIANS(K47))+COS(RADIANS(README!$B$3))*COS(RADIANS(K47))*COS(RADIANS(L47-README!$B$4)))),1)) | P47: =IF(OR(M47="",N47=""),"",ROUND(3959*ACOS(MIN(1,SIN(RADIANS(README!$B$3))*SIN(RADIANS(M47))+COS(RADIANS(README!$B$3))*COS(RADIANS(M47))*COS(RADIANS(N47-README!$B$4)))),1)) | Q47: =IF(O47="","",IF(P47="",O47,MIN(O47,P47))) | R47: =IF(Q47="","n/a",IF(Q47<=README!$B$5,"Yes","No")) | S47: Tornado Project (Grazulis) NY county list 1950–2012 | T47: A
A48: 2003-07-21 | B48: 18:38 | C48: Columbia | D48: Columbia Co. | E48: Tornado | F48: F0 | G48: 0.5 | H48: 60 | I48: 0 | J48: 0 | K48: 42.38 | L48: -73.78 | O48: =IF(OR(K48="",L48=""),"",ROUND(3959*ACOS(MIN(1,SIN(RADIANS(README!$B$3))*SIN(RADIANS(K48))+COS(RADIANS(README!$B$3))*COS(RADIANS(K48))*COS(RADIANS(L48-README!$B$4)))),1)) | P48: =IF(OR(M48="",N48=""),"",ROUND(3959*ACOS(MIN(1,SIN(RADIANS(README!$B$3))*SIN(RADIANS(M48))+COS(RADIANS(README!$B$3))*COS(RADIANS(M48))*COS(RADIANS(N48-README!$B$4)))),1)) | Q48: =IF(O48="","",IF(P48="",O48,MIN(O48,P48))) | R48: =IF(Q48="","n/a",IF(Q48<=README!$B$5,"Yes","No")) | S48: Tornado Project (Grazulis) NY county list 1950–2012 | T48: A
A49: 2003-07-21 | B49: 18:40 | C49: Columbia | D49: Columbia Co. | E49: Tornado | F49: F0 | G49: 4 | H49: 50 | I49: 0 | J49: 0 | K49: 42.38 | L49: -73.78 | O49: =IF(OR(K49="",L49=""),"",ROUND(3959*ACOS(MIN(1,SIN(RADIANS(README!$B$3))*SIN(RADIANS(K49))+COS(RADIANS(README!$B$3))*COS(RADIANS(K49))*COS(RADIANS(L49-README!$B$4)))),1)) | P49: =IF(OR(M49="",N49=""),"",ROUND(3959*ACOS(MIN(1,SIN(RADIANS(README!$B$3))*SIN(RADIANS(M49))+COS(RADIANS(README!$B$3))*COS(RADIANS(M49))*COS(RADIANS(N49-README!$B$4)))),1)) | Q49: =IF(O49="","",IF(P49="",O49,MIN(O49,P49))) | R49: =IF(Q49="","n/a",IF(Q49<=README!$B$5,"Yes","No")) | S49: Tornado Project (Grazulis) NY county list 1950–2012 | T49: A
A50: 2003-07-21 | B50: 18:40 | C50: Columbia | D50: Columbia Co. | E50: Tornado | F50: F0 | G50: 0.5 | H50: 60 | I50: 0 | J50: 0 | K50: 42.4 | L50: -73.7 | O50: =IF(OR(K50="",L50=""),"",ROUND(3959*ACOS(MIN(1,SIN(RADIANS(README!$B$3))*SIN(RADIANS(K50))+COS(RADIANS(README!$B$3))*COS(RADIANS(K50))*COS(RADIANS(L50-README!$B$4)))),1)) | P50: =IF(OR(M50="",N50=""),"",ROUND(3959*ACOS(MIN(1,SIN(RADIANS(README!$B$3))*SIN(RADIANS(M50))+COS(RADIANS(README!$B$3))*COS(RADIANS(M50))*COS(RADIANS(N50-README!$B$4)))),1)) | Q50: =IF(O50="","",IF(P50="",O50,MIN(O50,P50))) | R50: =IF(Q50="","n/a",IF(Q50<=README!$B$5,"Yes","No")) | S50: Tornado Project (Grazulis) NY county list 1950–2012 | T50: A
A51: 2003-07-21 | B51: 18:43 | C51: Columbia | D51: Columbia Co. | E51: Tornado | F51: F2 | G51: 1.3 | H51: 50 | I51: 0 | J51: 1 | K51: 42.4 | L51: -73.7 | O51: =IF(OR(K51="",L51=""),"",ROUND(3959*ACOS(MIN(1,SIN(RADIANS(README!$B$3))*SIN(RADIANS(K51))+COS(RADIANS(README!$B$3))*COS(RADIANS(K51))*COS(RADIANS(L51-README!$B$4)))),1)) | P51: =IF(OR(M51="",N51=""),"",ROUND(3959*ACOS(MIN(1,SIN(RADIANS(README!$B$3))*SIN(RADIANS(M51))+COS(RADIANS(README!$B$3))*COS(RADIANS(M51))*COS(RADIANS(N51-README!$B$4)))),1)) | Q51: =IF(O51="","",IF(P51="",O51,MIN(O51,P51))) | R51: =IF(Q51="","n/a",IF(Q51<=README!$B$5,"Yes","No")) | S51: Tornado Project (Grazulis) NY county list 1950–2012 | T51: A
A52: 2003-07-21 | B52: 18:45 | C52: Rensselaer | D52: Rensselaer Co. (long track N) | E52: Tornado | F52: F1 | G52: 4.8 | H52: 90 | I52: 0 | J52: 0 | K52: 42.52 | L52: -73.62 | M52: 42.9 | N52: -73.58 | O52: =IF(OR(K52="",L52=""),"",ROUND(3959*ACOS(MIN(1,SIN(RADIANS(README!$B$3))*SIN(RADIANS(K52))+COS(RADIANS(README!$B$3))*COS(RADIANS(K52))*COS(RADIANS(L52-README!$B$4)))),1)) | P52: =IF(OR(M52="",N52=""),"",ROUND(3959*ACOS(MIN(1,SIN(RADIANS(README!$B$3))*SIN(RADIANS(M52))+COS(RADIANS(README!$B$3))*COS(RADIANS(M52))*COS(RADIANS(N52-README!$B$4)))),1)) | Q52: =IF(O52="","",IF(P52="",O52,MIN(O52,P52))) | R52: =IF(Q52="","n/a",IF(Q52<=README!$B$5,"Yes","No")) | S52: Tornado Project (Grazulis) NY county list 1950–2012 | T52: A
A53: 2010-11-17 | B53: 04:18 | C53: Columbia | D53: Columbia Co. | E53: Tornado | F53: EF1 | G53: 1.9 | H53: 300 | I53: 0 | J53: 0 | K53: 42.27 | L53: -73.66 | M53: 42.29 | N53: -73.65 | O53: =IF(OR(K53="",L53=""),"",ROUND(3959*ACOS(MIN(1,SIN(RADIANS(README!$B$3))*SIN(RADIANS(K53))+COS(RADIANS(README!$B$3))*COS(RADIANS(K53))*COS(RADIANS(L53-README!$B$4)))),1)) | P53: =IF(OR(M53="",N53=""),"",ROUND(3959*ACOS(MIN(1,SIN(RADIANS(README!$B$3))*SIN(RADIANS(M53))+COS(RADIANS(README!$B$3))*COS(RADIANS(M53))*COS(RADIANS(N53-README!$B$4)))),1)) | Q53: =IF(O53="","",IF(P53="",O53,MIN(O53,P53))) | R53: =IF(Q53="","n/a",IF(Q53<=README!$B$5,"Yes","No")) | S53: Tornado Project (Grazulis) NY county list 1950–2012 | T53: A | U53: Nocturnal November tornado
A54: 2011-09-04 | B54: 15:20 | C54: Montgomery→Schenectady | D54: Cranesville | E54: Tornado | F54: EF1 | I54: 0 | J54: 0 | K54: 42.9 | L54: -74.17 | M54: 42.95 | N54: -74.05 | O54: =IF(OR(K54="",L54=""),"",ROUND(3959*ACOS(MIN(1,SIN(RADIANS(README!$B$3))*SIN(RADIANS(K54))+COS(RADIANS(README!$B$3))*COS(RADIANS(K54))*COS(RADIANS(L54-README!$B$4)))),1)) | P54: =IF(OR(M54="",N54=""),"",ROUND(3959*ACOS(MIN(1,SIN(RADIANS(README!$B$3))*SIN(RADIANS(M54))+COS(RADIANS(README!$B$3))*COS(RADIANS(M54))*COS(RADIANS(N54-README!$B$4)))),1)) | Q54: =IF(O54="","",IF(P54="",O54,MIN(O54,P54))) | R54: =IF(Q54="","n/a",IF(Q54<=README!$B$5,"Yes","No")) | S54: Tornado Project (Grazulis) NY county list 1950–2012 | T54: A
A55: 2013-05-29 | B55: 17:57 | C55: Schoharie | D55: Summit / East Jefferson | E55: Tornado | F55: EF1 | G55: 1.6 | H55: 200 | I55: 0 | J55: 0 | K55: 42.57 | L55: -74.55 | O55: =IF(OR(K55="",L55=""),"",ROUND(3959*ACOS(MIN(1,SIN(RADIANS(README!$B$3))*SIN(RADIANS(K55))+COS(RADIANS(README!$B$3))*COS(RADIANS(K55))*COS(RADIANS(L55-README!$B$4)))),1)) | P55: =IF(OR(M55="",N55=""),"",ROUND(3959*ACOS(MIN(1,SIN(RADIANS(README!$B$3))*SIN(RADIANS(M55))+COS(RADIANS(README!$B$3))*COS(RADIANS(M55))*COS(RADIANS(N55-README!$B$4)))),1)) | Q55: =IF(O55="","",IF(P55="",O55,MIN(O55,P55))) | R55: =IF(Q55="","n/a",IF(Q55<=README!$B$5,"Yes","No")) | S55: NWS ALY survey | T55: B | U55: Coords approximate (hamlet)
A56: 2013-05-29 | C56: Montgomery→Schenectady | D56: Mariaville → Schenectady | E56: Tornado | F56: EF2 | H56: 1760 | I56: 0 | J56: 0 | K56: 42.85 | L56: -74.07 | M56: 42.81 | N56: -73.94 | O56: =IF(OR(K56="",L56=""),"",ROUND(3959*ACOS(MIN(1,SIN(RADIANS(README!$B$3))*SIN(RADIANS(K56))+COS(RADIANS(README!$B$3))*COS(RADIANS(K56))*COS(RADIANS(L56-README!$B$4)))),1)) | P56: =IF(OR(M56="",N56=""),"",ROUND(3959*ACOS(MIN(1,SIN(RADIANS(README!$B$3))*SIN(RADIANS(M56))+COS(RADIANS(README!$B$3))*COS(RADIANS(M56))*COS(RADIANS(N56-README!$B$4)))),1)) | Q56: =IF(O56="","",IF(P56="",O56,MIN(O56,P56))) | R56: =IF(Q56="","n/a",IF(Q56<=README!$B$5,"Yes","No")) | S56: NWS ALY survey | T56: B | U56: Widest tornado near Albany (1,760 yd); coords approx
A57: 2013-05-29 | C57: Saratoga | D57: Vischer Ferry | E57: Tornado | F57: EF1 | I57: 0 | J57: 0 | K57: 42.79 | L57: -73.8 | O57: =IF(OR(K57="",L57=""),"",ROUND(3959*ACOS(MIN(1,SIN(RADIANS(README!$B$3))*SIN(RADIANS(K57))+COS(RADIANS(README!$B$3))*COS(RADIANS(K57))*COS(RADIANS(L57-README!$B$4)))),1)) | P57: =IF(OR(M57="",N57=""),"",ROUND(3959*ACOS(MIN(1,SIN(RADIANS(README!$B$3))*SIN(RADIANS(M57))+COS(RADIANS(README!$B$3))*COS(RADIANS(M57))*COS(RADIANS(N57-README!$B$4)))),1)) | Q57: =IF(O57="","",IF(P57="",O57,MIN(O57,P57))) | R57: =IF(Q57="","n/a",IF(Q57<=README!$B$5,"Yes","No")) | S57: NWS ALY survey | T57: B | U57: Coords approx
A58: 2014-05-22 | C58: Albany | D58: Bozenkill Rd, Knox (Albany Co. NW) | E58: Tornado | F58: EF1 | G58: 0.5 | H58: 440 | I58: 0 | J58: 0 | K58: 42.78 | L58: -74.13 | O58: =IF(OR(K58="",L58=""),"",ROUND(3959*ACOS(MIN(1,SIN(RADIANS(README!$B$3))*SIN(RADIANS(K58))+COS(RADIANS(README!$B$3))*COS(RADIANS(K58))*COS(RADIANS(L58-README!$B$4)))),1)) | P58: =IF(OR(M58="",N58=""),"",ROUND(3959*ACOS(MIN(1,SIN(RADIANS(README!$B$3))*SIN(RADIANS(M58))+COS(RADIANS(README!$B$3))*COS(RADIANS(M58))*COS(RADIANS(N58-README!$B$4)))),1)) | Q58: =IF(O58="","",IF(P58="",O58,MIN(O58,P58))) | R58: =IF(Q58="","n/a",IF(Q58<=README!$B$5,"Yes","No")) | S58: NCEI via tornadopath / NWS ALY survey | T58: B | U58: Coords approx; same storm as Duanesburg EF3. Bozenkill Rd, Knox: Guernsey (Loss Cause Farm) & Burian farms — hand-hewn barn (orig. Milton Barber's) collapsed, ~100-yr standing-seam roof peeled, tin thrown 200+ yds, 9 windows imploded. Prior sheet time 14:54 was erroneous (before the 3:33pm start); exact EF1 touchdown time needs NCEI. Rain-wrapped, 2 vortices; 3,300 without power. Altamont Enterprise 29 May 2014
A59: 2014-05-22 | B59: 15:33 | C59: Schenectady | D59: Duanesburg / Delanson | E59: Tornado | F59: EF3 (140 mph) | I59: 0 | J59: 0 | K59: 42.85 | L59: -74.13 | O59: =IF(OR(K59="",L59=""),"",ROUND(3959*ACOS(MIN(1,SIN(RADIANS(README!$B$3))*SIN(RADIANS(K59))+COS(RADIANS(README!$B$3))*COS(RADIANS(K59))*COS(RADIANS(L59-README!$B$4)))),1)) | P59: =IF(OR(M59="",N59=""),"",ROUND(3959*ACOS(MIN(1,SIN(RADIANS(README!$B$3))*SIN(RADIANS(M59))+COS(RADIANS(README!$B$3))*COS(RADIANS(M59))*COS(RADIANS(N59-README!$B$4)))),1)) | Q59: =IF(O59="","",IF(P59="",O59,MIN(O59,P59))) | R59: =IF(Q59="","n/a",IF(Q59<=README!$B$5,"Yes","No")) | S59: NWS ALY survey | T59: B | U59: Coords approx. EF3 at a Route 20 home (leveled); Delanson motel roof + Duanesburg volunteer-ambulance-HQ wall gone; I-88 tractor-trailers tipped; rain-wrapped. Max wind 140 mph; ~7-mi path (EF0-EF1 elsewhere); 0 casualties; 3:33-3:55pm. NWS ALY survey (DiRienzo/Koleci). Altamont Enterprise 29 May 2014
A60: 2014-06-17 | C60: Region | D60: Widespread thunderstorm wind damage | E60: Thunderstorm wind | K60: 42.75 | L60: -73.8 | O60: =IF(OR(K60="",L60=""),"",ROUND(3959*ACOS(MIN(1,SIN(RADIANS(README!$B$3))*SIN(RADIANS(K60))+COS(RADIANS(README!$B$3))*COS(RADIANS(K60))*COS(RADIANS(L60-README!$B$4)))),1)) | P60: =IF(OR(M60="",N60=""),"",ROUND(3959*ACOS(MIN(1,SIN(RADIANS(README!$B$3))*SIN(RADIANS(M60))+COS(RADIANS(README!$B$3))*COS(RADIANS(M60))*COS(RADIANS(N60-README!$B$4)))),1)) | Q60: =IF(O60="","",IF(P60="",O60,MIN(O60,P60))) | R60: =IF(Q60="","n/a",IF(Q60<=README!$B$5,"Yes","No")) | S60: NWS Albany – Past Weather Events (weather.gov/aly/pastevents) | T60: A
A61: 2015-06-09 | C61: Schenectady | D61: Scotia | E61: Tornado | F61: EF0 | I61: 0 | J61: 0 | K61: 42.83 | L61: -73.96 | O61: =IF(OR(K61="",L61=""),"",ROUND(3959*ACOS(MIN(1,SIN(RADIANS(README!$B$3))*SIN(RADIANS(K61))+COS(RADIANS(README!$B$3))*COS(RADIANS(K61))*COS(RADIANS(L61-README!$B$4)))),1)) | P61: =IF(OR(M61="",N61=""),"",ROUND(3959*ACOS(MIN(1,SIN(RADIANS(README!$B$3))*SIN(RADIANS(M61))+COS(RADIANS(README!$B$3))*COS(RADIANS(M61))*COS(RADIANS(N61-README!$B$4)))),1)) | Q61: =IF(O61="","",IF(P61="",O61,MIN(O61,P61))) | R61: =IF(Q61="","n/a",IF(Q61<=README!$B$5,"Yes","No")) | S61: NWS ALY survey | T61: B | U61: Also a microburst same day
A62: 2016-04-07 | C62: Albany/Saratoga | D62: Capital District damaging wind | E62: Synoptic windstorm | K62: 42.75 | L62: -73.8 | O62: =IF(OR(K62="",L62=""),"",ROUND(3959*ACOS(MIN(1,SIN(RADIANS(README!$B$3))*SIN(RADIANS(K62))+COS(RADIANS(README!$B$3))*COS(RADIANS(K62))*COS(RADIANS(L62-README!$B$4)))),1)) | P62: =IF(OR(M62="",N62=""),"",ROUND(3959*ACOS(MIN(1,SIN(RADIANS(README!$B$3))*SIN(RADIANS(M62))+COS(RADIANS(README!$B$3))*COS(RADIANS(M62))*COS(RADIANS(N62-README!$B$4)))),1)) | Q62: =IF(O62="","",IF(P62="",O62,MIN(O62,P62))) | R62: =IF(Q62="","n/a",IF(Q62<=README!$B$5,"Yes","No")) | S62: NWS Albany – Past Weather Events (weather.gov/aly/pastevents) | T62: A
A63: 2017-05-18 | C63: Region | D63: Severe thunderstorms | E63: Thunderstorm wind | K63: 42.75 | L63: -73.8 | O63: =IF(OR(K63="",L63=""),"",ROUND(3959*ACOS(MIN(1,SIN(RADIANS(README!$B$3))*SIN(RADIANS(K63))+COS(RADIANS(README!$B$3))*COS(RADIANS(K63))*COS(RADIANS(L63-README!$B$4)))),1)) | P63: =IF(OR(M63="",N63=""),"",ROUND(3959*ACOS(MIN(1,SIN(RADIANS(README!$B$3))*SIN(RADIANS(M63))+COS(RADIANS(README!$B$3))*COS(RADIANS(M63))*COS(RADIANS(N63-README!$B$4)))),1)) | Q63: =IF(O63="","",IF(P63="",O63,MIN(O63,P63))) | R63: =IF(Q63="","n/a",IF(Q63<=README!$B$5,"Yes","No")) | S63: NWS Albany – Past Weather Events (weather.gov/aly/pastevents) | T63: A | U63: NWS case study
A64: 2018-05-04 | C64: Region | D64: Damaging wind event | E64: Thunderstorm wind | K64: 42.75 | L64: -73.8 | O64: =IF(OR(K64="",L64=""),"",ROUND(3959*ACOS(MIN(1,SIN(RADIANS(README!$B$3))*SIN(RADIANS(K64))+COS(RADIANS(README!$B$3))*COS(RADIANS(K64))*COS(RADIANS(L64-README!$B$4)))),1)) | P64: =IF(OR(M64="",N64=""),"",ROUND(3959*ACOS(MIN(1,SIN(RADIANS(README!$B$3))*SIN(RADIANS(M64))+COS(RADIANS(README!$B$3))*COS(RADIANS(M64))*COS(RADIANS(N64-README!$B$4)))),1)) | Q64: =IF(O64="","",IF(P64="",O64,MIN(O64,P64))) | R64: =IF(Q64="","n/a",IF(Q64<=README!$B$5,"Yes","No")) | S64: NWS Albany – Past Weather Events (weather.gov/aly/pastevents) | T64: A | U64: NWS case study
A65: 2018-08-03 | B65: 11:24 | C65: Greene | D65: Greene Co. | E65: Tornado | F65: EF0 | G65: 1.9 | H65: 67 | I65: 0 | J65: 0 | K65: 42.28 | L65: -74.12 | O65: =IF(OR(K65="",L65=""),"",ROUND(3959*ACOS(MIN(1,SIN(RADIANS(README!$B$3))*SIN(RADIANS(K65))+COS(RADIANS(README!$B$3))*COS(RADIANS(K65))*COS(RADIANS(L65-README!$B$4)))),1)) | P65: =IF(OR(M65="",N65=""),"",ROUND(3959*ACOS(MIN(1,SIN(RADIANS(README!$B$3))*SIN(RADIANS(M65))+COS(RADIANS(README!$B$3))*COS(RADIANS(M65))*COS(RADIANS(N65-README!$B$4)))),1)) | Q65: =IF(O65="","",IF(P65="",O65,MIN(O65,P65))) | R65: =IF(Q65="","n/a",IF(Q65<=README!$B$5,"Yes","No")) | S65: NCEI via tornadopath | T65: B | U65: County centroid approx
A66: 2019-02-25 | C66: Region | D66: Damaging winds | E66: Synoptic windstorm | K66: 42.75 | L66: -73.8 | O66: =IF(OR(K66="",L66=""),"",ROUND(3959*ACOS(MIN(1,SIN(RADIANS(README!$B$3))*SIN(RADIANS(K66))+COS(RADIANS(README!$B$3))*COS(RADIANS(K66))*COS(RADIANS(L66-README!$B$4)))),1)) | P66: =IF(OR(M66="",N66=""),"",ROUND(3959*ACOS(MIN(1,SIN(RADIANS(README!$B$3))*SIN(RADIANS(M66))+COS(RADIANS(README!$B$3))*COS(RADIANS(M66))*COS(RADIANS(N66-README!$B$4)))),1)) | Q66: =IF(O66="","",IF(P66="",O66,MIN(O66,P66))) | R66: =IF(Q66="","n/a",IF(Q66<=README!$B$5,"Yes","No")) | S66: NWS Albany – Past Weather Events (weather.gov/aly/pastevents) | T66: A
A67: 2019-10-31 | C67: Region | D67: Halloween storm winds | E67: Synoptic windstorm | F67: 63 mph | K67: 42.75 | L67: -73.8 | O67: =IF(OR(K67="",L67=""),"",ROUND(3959*ACOS(MIN(1,SIN(RADIANS(README!$B$3))*SIN(RADIANS(K67))+COS(RADIANS(README!$B$3))*COS(RADIANS(K67))*COS(RADIANS(L67-README!$B$4)))),1)) | P67: =IF(OR(M67="",N67=""),"",ROUND(3959*ACOS(MIN(1,SIN(RADIANS(README!$B$3))*SIN(RADIANS(M67))+COS(RADIANS(README!$B$3))*COS(RADIANS(M67))*COS(RADIANS(N67-README!$B$4)))),1)) | Q67: =IF(O67="","",IF(P67="",O67,MIN(O67,P67))) | R67: =IF(Q67="","n/a",IF(Q67<=README!$B$5,"Yes","No")) | S67: NWS Albany – Past Weather Events (weather.gov/aly/pastevents) | T67: A | U67: Thousands of outages
A68: 2020-08-04 | C68: Region | D68: Tropical Storm Isaias | E68: Tropical wind | K68: 42.75 | L68: -73.8 | O68: =IF(OR(K68="",L68=""),"",ROUND(3959*ACOS(MIN(1,SIN(RADIANS(README!$B$3))*SIN(RADIANS(K68))+COS(RADIANS(README!$B$3))*COS(RADIANS(K68))*COS(RADIANS(L68-README!$B$4)))),1)) | P68: =IF(OR(M68="",N68=""),"",ROUND(3959*ACOS(MIN(1,SIN(RADIANS(README!$B$3))*SIN(RADIANS(M68))+COS(RADIANS(README!$B$3))*COS(RADIANS(M68))*COS(RADIANS(N68-README!$B$4)))),1)) | Q68: =IF(O68="","",IF(P68="",O68,MIN(O68,P68))) | R68: =IF(Q68="","n/a",IF(Q68<=README!$B$5,"Yes","No")) | S68: NWS Albany – Past Weather Events (weather.gov/aly/pastevents) | T68: A
A69: 2020-08-23 | C69: Albany | D69: Albany Co. | E69: Thunderstorm wind | I69: 0 | J69: 0 | K69: 42.75 | L69: -73.8 | O69: =IF(OR(K69="",L69=""),"",ROUND(3959*ACOS(MIN(1,SIN(RADIANS(README!$B$3))*SIN(RADIANS(K69))+COS(RADIANS(README!$B$3))*COS(RADIANS(K69))*COS(RADIANS(L69-README!$B$4)))),1)) | P69: =IF(OR(M69="",N69=""),"",ROUND(3959*ACOS(MIN(1,SIN(RADIANS(README!$B$3))*SIN(RADIANS(M69))+COS(RADIANS(README!$B$3))*COS(RADIANS(M69))*COS(RADIANS(N69-README!$B$4)))),1)) | Q69: =IF(O69="","",IF(P69="",O69,MIN(O69,P69))) | R69: =IF(Q69="","n/a",IF(Q69<=README!$B$5,"Yes","No")) | S69: NCEI Storm Events Database | T69: A | U69: $7.5M; barn roof torn off
A70: 2020-08-27 | B70: 13:11 | C70: Greene | D70: Greene Co. | E70: Tornado | F70: EF1 | G70: 0.3 | H70: 25 | I70: 0 | J70: 0 | K70: 42.28 | L70: -74.12 | O70: =IF(OR(K70="",L70=""),"",ROUND(3959*ACOS(MIN(1,SIN(RADIANS(README!$B$3))*SIN(RADIANS(K70))+COS(RADIANS(README!$B$3))*COS(RADIANS(K70))*COS(RADIANS(L70-README!$B$4)))),1)) | P70: =IF(OR(M70="",N70=""),"",ROUND(3959*ACOS(MIN(1,SIN(RADIANS(README!$B$3))*SIN(RADIANS(M70))+COS(RADIANS(README!$B$3))*COS(RADIANS(M70))*COS(RADIANS(N70-README!$B$4)))),1)) | Q70: =IF(O70="","",IF(P70="",O70,MIN(O70,P70))) | R70: =IF(Q70="","n/a",IF(Q70<=README!$B$5,"Yes","No")) | S70: NCEI via tornadopath | T70: B | U70: County centroid approx
A71: 2020-08-29 | B71: 16:42 | C71: Rensselaer | D71: Schaghticoke | E71: Tornado | F71: EF1 | G71: 2.2 | H71: 100 | I71: 0 | J71: 0 | K71: 42.9 | L71: -73.59 | O71: =IF(OR(K71="",L71=""),"",ROUND(3959*ACOS(MIN(1,SIN(RADIANS(README!$B$3))*SIN(RADIANS(K71))+COS(RADIANS(README!$B$3))*COS(RADIANS(K71))*COS(RADIANS(L71-README!$B$4)))),1)) | P71: =IF(OR(M71="",N71=""),"",ROUND(3959*ACOS(MIN(1,SIN(RADIANS(README!$B$3))*SIN(RADIANS(M71))+COS(RADIANS(README!$B$3))*COS(RADIANS(M71))*COS(RADIANS(N71-README!$B$4)))),1)) | Q71: =IF(O71="","",IF(P71="",O71,MIN(O71,P71))) | R71: =IF(Q71="","n/a",IF(Q71<=README!$B$5,"Yes","No")) | S71: NCEI via tornadopath | T71: A
A72: 2020-10-07 | C72: Region | D72: October 2020 derecho | E72: Derecho | K72: 42.75 | L72: -73.8 | O72: =IF(OR(K72="",L72=""),"",ROUND(3959*ACOS(MIN(1,SIN(RADIANS(README!$B$3))*SIN(RADIANS(K72))+COS(RADIANS(README!$B$3))*COS(RADIANS(K72))*COS(RADIANS(L72-README!$B$4)))),1)) | P72: =IF(OR(M72="",N72=""),"",ROUND(3959*ACOS(MIN(1,SIN(RADIANS(README!$B$3))*SIN(RADIANS(M72))+COS(RADIANS(README!$B$3))*COS(RADIANS(M72))*COS(RADIANS(N72-README!$B$4)))),1)) | Q72: =IF(O72="","",IF(P72="",O72,MIN(O72,P72))) | R72: =IF(Q72="","n/a",IF(Q72<=README!$B$5,"Yes","No")) | S72: NWS Albany – Past Weather Events (weather.gov/aly/pastevents) | T72: A | U72: High-end severe wind event
A73: 2021-04-21 | C73: NWS ALY CWA | D73: April 2021 tornadoes | E73: Tornado | O73: =IF(OR(K73="",L73=""),"",ROUND(3959*ACOS(MIN(1,SIN(RADIANS(README!$B$3))*SIN(RADIANS(K73))+COS(RADIANS(README!$B$3))*COS(RADIANS(K73))*COS(RADIANS(L73-README!$B$4)))),1)) | P73: =IF(OR(M73="",N73=""),"",ROUND(3959*ACOS(MIN(1,SIN(RADIANS(README!$B$3))*SIN(RADIANS(M73))+COS(RADIANS(README!$B$3))*COS(RADIANS(M73))*COS(RADIANS(N73-README!$B$4)))),1)) | Q73: =IF(O73="","",IF(P73="",O73,MIN(O73,P73))) | R73: =IF(Q73="","n/a",IF(Q73<=README!$B$5,"Yes","No")) | S73: NWS Albany – Past Weather Events (weather.gov/aly/pastevents) | T73: B | U73: Locations not captured; see NWS writeup
A74: 2022-07-12 | C74: Region | D74: Severe thunderstorms | E74: Thunderstorm wind | K74: 42.75 | L74: -73.8 | O74: =IF(OR(K74="",L74=""),"",ROUND(3959*ACOS(MIN(1,SIN(RADIANS(README!$B$3))*SIN(RADIANS(K74))+COS(RADIANS(README!$B$3))*COS(RADIANS(K74))*COS(RADIANS(L74-README!$B$4)))),1)) | P74: =IF(OR(M74="",N74=""),"",ROUND(3959*ACOS(MIN(1,SIN(RADIANS(README!$B$3))*SIN(RADIANS(M74))+COS(RADIANS(README!$B$3))*COS(RADIANS(M74))*COS(RADIANS(N74-README!$B$4)))),1)) | Q74: =IF(O74="","",IF(P74="",O74,MIN(O74,P74))) | R74: =IF(Q74="","n/a",IF(Q74<=README!$B$5,"Yes","No")) | S74: NWS Albany – Past Weather Events (weather.gov/aly/pastevents) | T74: A
A75: 2024-07-16 | C75: Region | D75: Severe thunderstorms | E75: Thunderstorm wind | K75: 42.75 | L75: -73.8 | O75: =IF(OR(K75="",L75=""),"",ROUND(3959*ACOS(MIN(1,SIN(RADIANS(README!$B$3))*SIN(RADIANS(K75))+COS(RADIANS(README!$B$3))*COS(RADIANS(K75))*COS(RADIANS(L75-README!$B$4)))),1)) | P75: =IF(OR(M75="",N75=""),"",ROUND(3959*ACOS(MIN(1,SIN(RADIANS(README!$B$3))*SIN(RADIANS(M75))+COS(RADIANS(README!$B$3))*COS(RADIANS(M75))*COS(RADIANS(N75-README!$B$4)))),1)) | Q75: =IF(O75="","",IF(P75="",O75,MIN(O75,P75))) | R75: =IF(Q75="","n/a",IF(Q75<=README!$B$5,"Yes","No")) | S75: NWS Albany – Past Weather Events (weather.gov/aly/pastevents) | T75: A
A76: 2026-08-28 | C76: Saratoga | D76: Wilton | E76: Tornado | F76: EF1 (110 mph) + EF0 | I76: 0 | J76: 0 | K76: 43.15 | L76: -73.72 | O76: =IF(OR(K76="",L76=""),"",ROUND(3959*ACOS(MIN(1,SIN(RADIANS(README!$B$3))*SIN(RADIANS(K76))+COS(RADIANS(README!$B$3))*COS(RADIANS(K76))*COS(RADIANS(L76-README!$B$4)))),1)) | P76: =IF(OR(M76="",N76=""),"",ROUND(3959*ACOS(MIN(1,SIN(RADIANS(README!$B$3))*SIN(RADIANS(M76))+COS(RADIANS(README!$B$3))*COS(RADIANS(M76))*COS(RADIANS(N76-README!$B$4)))),1)) | Q76: =IF(O76="","",IF(P76="",O76,MIN(O76,P76))) | R76: =IF(Q76="","n/a",IF(Q76<=README!$B$5,"Yes","No")) | S76: CBS6 Albany / NWS ALY PNS | T76: B | U76: Date approximate (late Aug 2026); ~45 mi N
A78: Nearest-point column uses start/end points only; a long-track tornado (e.g., 1989 F4, 1974 F3) can pass closer than either endpoint. Region-wide wind days are pinned to Albany AP coordinates for the formula.

Sheet Summary
A1: Events by category | D1: Events by confidence | G1: Events by century | J1: Tornadoes (Wind & Tornadoes sheet)
A2: Category | B2: Count | D2: A | E2: =COUNTIF(Events!$N$2:$N$265,D2) | G2: 18th | H2: =COUNTIF(Events!$E$2:$E$265,18) | J2: All tornado rows | K2: =COUNTIF('Wind & Tornadoes'!$E$2:$E$76,"Tornado*")
A3: Arctic outbreak | B3: =COUNTIF(Events!$F$2:$F$265,A3) | D3: B | E3: =COUNTIF(Events!$N$2:$N$265,D3) | G3: 19th | H3: =COUNTIF(Events!$E$2:$E$265,19) | J3: Tornado rows within radius | K3: =COUNTIFS('Wind & Tornadoes'!$E$2:$E$76,"Tornado*",'Wind & Tornadoes'!$R$2:$R$76,"Yes")
A4: Arctic outbreak / blizzard | B4: =COUNTIF(Events!$F$2:$F$265,A4) | D4: C | E4: =COUNTIF(Events!$N$2:$N$265,D4) | G4: 20th | H4: =COUNTIF(Events!$E$2:$E$265,20) | J4: F/EF2+ within radius | K4: =SUMPRODUCT((LEFT('Wind & Tornadoes'!$E$2:$E$76,7)="Tornado")*('Wind & Tornadoes'!$R$2:$R$76="Yes")*(ISNUMBER(SEARCH("F2",'Wind & Tornadoes'!$F$2:$F$76))+ISNUMBER(SEARCH("F3",'Wind & Tornadoes'!$F$2:$F$76))+ISNUMBER(SEARCH("F4",'Wind & Tornadoes'!$F$2:$F$76))))
A5: Arctic outbreak / ice | B5: =COUNTIF(Events!$F$2:$F$265,A5) | G5: 21st | H5: =COUNTIF(Events!$E$2:$E$265,21) | J5: Closest tornado (mi) | K5: =MIN('Wind & Tornadoes'!$Q$2:$Q$76)
A6: Arctic outbreak / river ice | B6: =COUNTIF(Events!$F$2:$F$265,A6) | D6: Verified = Y | E6: =COUNTIF(Events!$O$2:$O$265,"Y") | J6: Total tornado injuries within radius | K6: =SUMIFS('Wind & Tornadoes'!$J$2:$J$76,'Wind & Tornadoes'!$E$2:$E$76,"Tornado*",'Wind & Tornadoes'!$R$2:$R$76,"Yes")
A7: Blizzard | B7: =COUNTIF(Events!$F$2:$F$265,A7) | D7: Verified = N | E7: =COUNTIF(Events!$O$2:$O$265,"N")
A8: Blizzard / cold | B8: =COUNTIF(Events!$F$2:$F$265,A8)
A9: Coastal storm | B9: =COUNTIF(Events!$F$2:$F$265,A9)
A10: Coastal storm / wind | B10: =COUNTIF(Events!$F$2:$F$265,A10)
A11: Cold month / snow | B11: =COUNTIF(Events!$F$2:$F$265,A11)
A12: Cold snap | B12: =COUNTIF(Events!$F$2:$F$265,A12)
A13: Cold snap / river ice | B13: =COUNTIF(Events!$F$2:$F$265,A13)
A14: Cold winter | B14: =COUNTIF(Events!$F$2:$F$265,A14)
A15: Derecho | B15: =COUNTIF(Events!$F$2:$F$265,A15)
A16: Downburst / tornado | B16: =COUNTIF(Events!$F$2:$F$265,A16)
A17: Drought | B17: =COUNTIF(Events!$F$2:$F$265,A17)
A18: Drought / heat | B18: =COUNTIF(Events!$F$2:$F$265,A18)
A19: Drought / wildfire | B19: =COUNTIF(Events!$F$2:$F$265,A19)
... A83: Windstorm | B83: =COUNTIF(Events!$F$2:$F$265,A83)
A85: Total | B85: =SUM(B3:B84)

Sheet Sources
A1: Source | B1: URL | C1: Best for
A2: NWS Albany – Past Weather Events (weather.gov/aly/pastevents) | B2: https://www.weather.gov/aly/pastevents | C2: Authoritative local recap: flood crests at Albany/Troy/Schenectady, Albany snow totals, ice storms, outages, 2011–2026 event writeups.
A3: NWS Albany July 2026 flash flood writeup | B3: https://www.weather.gov/aly/july2026flashflood | C3: Rainfall by station incl. Medusa, South Berne, Voorheesville; LSR list; recurrence intervals.
A4: NWS Albany climate extremes (ALB_Extremes.pdf) | B4: https://www.weather.gov/media/aly/Climate/ALB_Extremes.pdf | C4: Albany all-time records; verify 104°F / –28°F rows.
A5: Tornado Project (Grazulis) NY county list 1950–2012 | B5: https://www.tornadoproject.com/alltorns/nytorn.htm | C5: Every NY tornado 1950–2012 with begin/end lat-lon, F-scale, deaths, injuries.
A6: NCEI Storm Events Database | B6: https://www.ncei.noaa.gov/stormevents/ | C6: 2013+ tornadoes, thunderstorm wind, flash flood, hail by county; damage $ and narratives.
A7: NWS Albany storm surveys (PNS PDFs linked from Past Events page) | B7: https://www.weather.gov/aly/pastevents | C7: EF ratings, path length/width, exact coords for 2011+ tornadoes and microbursts.
A8: July 1989 outbreak (Wikipedia, citing Grazulis & SPC) | B8: https://en.wikipedia.org/wiki/July_1989_Northeastern_United_States_tornado_outbreak | C8: F4 path description incl. Rensselaerville/Greenville touchdowns.
A9: Ludlum, Early American Hurricanes 1492–1870 (AMS, 1963), pp. 8–23 (verified, page images/text) | B9: https://hdl.handle.net/2027/mdp.39015002912718 | C9: Early hurricanes 1492–1870. NY-relevant rows verified from pp. 8–40 and 77–108: 1635, 1667, 1683, 1706 Albany flood, 1769, 1775, 1783, 1788 Hudson Highlands storm, 1795, 1804 Snow Hurricane (full), 1806, 1815 Great September Gale, 1821 NYC/Hudson hurricane, 1839 Catskill snow, 1850 central-NY track, and the Oct 1869 Saxby’s Gale rainstorm (upper Hudson Valley). Whole-volume Chronological Index (1528–1870, pp. 191–195) checked: no other storm reached eastern NY.
A10: USGS Reddy/Kappel/Root 2020 LiDAR Closed-Depression Database (doi:10.5066/P9HGN5IJ) | B10: https://www.sciencebase.gov/catalog/item/5b9ab009e4b0d966b485dea2 | C10: INGESTED (KMZ): 514 statewide depressions, 191 within 75 mi of Westerlo, classified by bedrock & origin (own LiDAR Depressions sheet). Pull the LiDAR .gdb for finer county-scale data.
A11: USGS Kappel et al. 2020 (SIR 2020-5030) & SIR 2021-5094; SUNY Brockport (Richards) LiDAR karst study; Cornell karst/manure-mgmt database | B11: https://pubs.usgs.gov/sir/2020/5030/sir20205030.pdf | C11: SYSTEMATIC karst inventory for NY/Albany Co.: LiDAR-mapped sinkholes & closed depressions, karst-prone bedrock, thinly-soiled soils. The way to find collapses no newspaper reported. NOT YET fully ingested - PDFs/GIS to pull.
A12: Northeastern Cave Conservancy preserve management plans & board minutes; Altamont Enterprise "Back Roads Geology" (Nardacci); NSS 1991 Knox writeup | B12: https://necaveconservancy.org/preserves/ | C12: Helderberg karst inventory: cave entrance sinks with dimensions, hydrology, and a few dated collapses (own Subsidence & Karst sheet). Management-plan PDFs are the primary source.
... A14: Albany Daily Advertiser, "Notices of the Winters at New York for the last forty-two years… dates at which the Hudson was frozen or obstructed or closed by ice at Albany," repr. American Quarterly Journal of Agriculture and Science 1 (1845) pp. 347–350 (verified, page images) | B14: https://archive.org/details/americanquarterl00slsn | C14: Hudson-at-Albany freeze/open dates and lowest temps, winter by winter, 1789–90 to 1831–32 (own sheet). VERIFIED.
A15: The Annual Register (Albany, Munsell) 1849–1850 – Albany weather notes incl. the Green Street museum weather book (1789) and Albany Gazette 13 Jan 1772 | C15: Ludlum cites vol. 1849 p. 329 and vol. 1850 vol. 2 p. 192; HathiTrust/Google Books.
A16: E. T. Turner, The Climate of the State of New York (Albany, 1894, 440 pp.) | C16: Cited by Ludlum; state-level climatology with historical extremes – HathiTrust.
A17: "Notices of the winters at New York for the last 42 years" (1789–1831), Albany Daily Advertiser, reprinted Amer. Quar. Jour. Agri. & Sci. 1 (1845) 347 | C17: Year-by-year Albany-area winter notices 1789–1831 – exactly the gap between Ludlum and Hough. Google Books / HathiTrust.
A18: Grazulis, Significant Tornadoes 1680–1991 (via tornadopath.com county pages) | B18: https://www.tornadopath.com/new-york | C18: Pre-1950 F2+ and deadly tornadoes by county (approx coords).
A19: Ludlum, Early American Winters I & II; Early American Hurricanes 1492–1870 (AMS) | C19: Chronicle-era winters, hurricanes, 1816; the only systematic pre-instrument source. Vol. I pp. 114–115, 134–135, 164–171, 182–183, 188–193, 228–229, 236–237 read via screenshots 2026-09-20.
A20: USGS NWIS peak-flow data | B20: https://waterdata.usgs.gov/nwis/peak | C20: Annual peak stage/flow for Schoharie Cr., Esopus Cr., Catskill Cr., Hudson at Albany — the honest way to rank floods.
A21: NCEI GHCN-Daily (Albany AP, coop stations) | B21: https://www.ncei.noaa.gov/access/search/data-search/daily-summaries | C21: Daily max/min/precip/snow; needed for frost dates, cold snaps, heat waves on the plateau.
A22: NRCC (Cornell) Northeast drought & climate tools | B22: https://www.nrcc.cornell.edu/ | C22: Drought indices, growing-degree-day and frost-date climatologies.
A23: US Drought Monitor archive (2000–) | B23: https://droughtmonitor.unl.edu/ | C23: Weekly drought categories by county.
A24: NESIS (Northeast Snowfall Impact Scale) | B24: https://www.ncei.noaa.gov/access/monitoring/nesis/ | C24: Objective ranking of Northeast snowstorms 1956+.
A25: Mylroie, J.E. 1977, Speleogenesis & Karst Geomorphology of the Helderberg Plateau, Schoharie Co. (NY Cave Survey Bulletin 2, 336 pp.; RPI doctoral thesis) | C25: FOUNDATIONAL systematic speleogenesis / karst-geomorphology survey of the plateau — the likely source for coordinates & dimensions of the Barton Hill caves (Caboose, Single X, Joober Hole) and possibly the McFails historic-entrance collapse & Knox-collapse dates. PRINT-ONLY (not online): NSS / NY Cave Survey, or a library copy (Butler Cave Conservation Society holds one). NOT YET ingested.
A26: Cooper, M.P. & Mylroie, J.E. 2015, 'Caves and Karst of the Helderberg Plateau' in Glaciation and Speleogenesis (Springer) | B26: https://link.springer.com/chapter/10.1007/978-3-319-16534-9_5 | C26: Modern synthesis distilling Mylroie 1977: names the major systems (Barrack Zourie, Howe, McFails, Skull, Thunder Hole) and gives U/Th dates showing the caves are pre-glacial (>=350 ka). Reachable now (Springer/ResearchGate) — the accessible proxy for Bulletin 2. Check it for the McFails collapse date and any Barton Hill coordinates.
A27: FEMA National Flood Insurance Program (NFIP) flood maps — Map Service Center | B27: https://msc.fema.gov/portal/search | C27: Official 100-year (1% annual) floodplains by address. The 2015-04-01 Albany Co. remap designated FEMA floodplains along Vly Creek (Voorheesville), Vlomankill, Normanskill, Hungerkill, Bozenkill, Switzkill, Basic Creek Reservoir, Ten Mile Creek (Rensselaerville) and tributaries to Warners/Thompsons/Myosotis Lakes — the region's formally flood-prone waterways. NFIP was >$20B in debt (Sept 2011) after Irene/Lee/Sandy; premium hikes capped 20%/yr. Per Altamont Enterprise 9 Apr 2015.
A28: Albany County Multi-Jurisdictional Hazard Mitigation Plan (2025, ~200 pp.) & Guilderland annex (~65 pp.), FEMA-required | C28: SYSTEMATIC local hazard inventory (5-yr update cycle; adopted Guilderland 2025-07-15). Guilderland: flooding vulnerability HIGH — 515 parcels in the 1% annual (100-yr) floodplain (284 residential / 45 park / 32 agricultural / 21 commercial / 8 community / 7 public / 2 industrial); severe-storm & erosion vulnerability HIGH, landslide MODERATE; one HIGH-HAZARD dam (Watervliet Reservoir, blocking the Normans Kill — failure threatens life & extensive loss). Every county/town has one; the register-grade way to catch hazards no newspaper reported. Per Altamont Enterprise 31 Jul 2025 & 6 Dec 2018. Lineage: a 2007 county-only plan failed to win municipal adoption; the multi-jurisdictional plan was adopted 2018 (all Albany Co. municipalities EXCEPT Rensselaerville & Colonie village), updated 2025. Hazards assessed: extreme temp, severe storm/tornado, tropical, flood, drought, landslide, EARTHQUAKE (a register gap), winter storm, wildfire, ice jam.
A29: NWS Albany 'ALB_Extremes' + xmACIS annual-highest-temperature record (Albany airport, 1874-present) | B29: https://www.weather.gov/media/aly/Climate/ALB_Extremes.pdf | C29: Albany's OWN daily temperature record: all-time high 104°F (Jul 4 1911); 100°F+ in only 3 years (1933/1936/1953) and NONE since 1953; year-by-year hottest day. The local yardstick for grading any heat wave — e.g. 1936 hit 100°F+ for 3 days but 1972 topped out at 91°F despite ~900 NYC deaths.
A30: William G. Pomeroy Foundation — Knox Cave historic marker (2025) | B30: https://www.wgpfoundation.org/historic-markers/knox-cave/
A31: William G. Pomeroy Foundation — Knox Cave historic marker (2025) | B31: https://www.wgpfoundation.org/historic-markers/knox-cave/ | C31: Knox Cave 1975 collapse — 2nd independent source for March (see Events row 141 note).
A32: Stone, S. — McFails Cave (2005 National Cave & Karst Management Symposium) | B32: https://caves.org/wp-content/uploads/2023/03/2005_Stone-McFails.pdf | C32: Corrects McFail's death to July 1, 1854 (not Roscoe 1882's oft-repeated 1853); traces the pit's early history 1854-1958. Historic-entrance collapse date STILL not found in this pass.
A33: albanyhilltowns.com (Helderberg Hilltowns local-history wiki) | B33: https://albanyhilltowns.com/Knox_Cave | C33: Transcribed period newspaper articles (1933-1991) on Knox Cave — a rich primary-adjacent source not yet systematically mined beyond the 1975 date question.
A34: NWS Albany — ALB_Extremes.pdf (confirmed 2026-09-21) | B34: https://www.weather.gov/media/aly/Climate/ALB_Extremes.pdf | C34: CONFIRMS open item #3: record high 104°F Jul 4 1911, record low -28°F Jan 19 1971 — exactly as the register already had them. Also carries the full extremes table (earliest/latest frost, growing-season length, heat/cold streaks) if useful later.
A35: USGS — Landslide Inventories across the United States (ver. 3.0, Feb 2025) | B35: https://doi.org/10.5066/P14AJF8I (ScienceBase item 671eef1fd34ed0f827ea9f12; ArcGIS feature service e.g. services.arcgis.com/v01gqwM5QqNysAAi/ArcGIS/rest/services/US_Landslide_poly_v2/FeatureServer) | C35: SYSTEMATIC national landslide point/polygon compilation (5,687 records from 131 constituent inventories as of this release), with Date_Min/Max, Fatalities, Confidence (1-8 scale), LS_Type, Lat/Lon per entry. Exactly the kind of authoritative catch-all source the register's README flags as the way to find slides no newspaper covered. NOT YET QUERIED for our region — Laurie's upload was the FGDC metadata record only, no actual data rows; the real point data lives in a GeoPackage/CSV/ArcGIS feature service not included in this upload. To pull entries for the Hilltowns/Capital Region footprint, either (a) download US_Landslide_v3_csv from the ScienceBase item and upload it here, or (b) supply a working ArcGIS REST query URL (this session can't construct one against an un-visited domain).
A36: The Argus (Albany, N.Y.) — daily newspaper | B36: (uploaded PDF scans) | C36: Capital Region & Hudson Valley news, 1880s–1910s; landslide/flood briefs. Scans used this pass: Mar 17 1886 (Kingston feared slide), Nov 21 1886 (Highland West Shore slide), Feb 28 1903 (Highland Central-Hudson slide), May 1 1915 (Rensselaer sand-bank fatality). Also carried foreign geohazard wire items reviewed but not added (Spain 1907, Vesuvius 1911). Batch 2 scans added: Mar 25 1888 (Amsterdam freshet + Stillwater slide), Sep 25 1890 (Hudson Bartlett brickyard slide, repr. Kingston Freeman), Dec 27 1893 (Richmondville D&H slate-cut slide), Mar 24 1902 (Troy & Rensselaer recurring slide), Jan 31 1903 (Glen ice jam + Schenectady slide). Foreign/out-of-core wire items reviewed but not staged: French Alps 1886, Michigan sinkhole 1893, Ireland 1896, Apr 1901 Ohio/CT/MA flood, Austria 1902, Buffalo/Ithaca Jan 1903.
A37: The Cohoes Republican (Cohoes, N.Y.) | B37: (uploaded PDF scans) | C37: Capital Region news. Scans used: Mar 11 1903 (Mohawk freshet at Fonda + 50-ft FJ&G track slide), Jan 10 1906 (Haverstraw landslide disaster). Batch 2 scans added: Feb 3 1902 (Feb 1902 blizzard — Mohawk Valley/Capital Region/N NY).
A38: The News-Herald (Ravena, N.Y.; Southern Albany & Northern Greene Cos.) | B38: (uploaded PDF scans) | C38: Local Ravena/Coeymans-area news. Scans reviewed: Feb 5 1937 (1937 Ohio/Mississippi flood, national — PENDING Laurie's call on out-of-core national events), Jan 17 1947 (NY Telephone winter-operations feature — no discrete event). Batch 3: Nov 9 1923 (West Shore slide near Milton, staged); Jul 5 1940 & Mar 4 1976 reviewed — only tourism/out-of-region 'sinkhole' mentions (Whiteface slide scar; Arecibo, PR), nothing staged.
A39: The Altamont Enterprise (Altamont, N.Y.) | B39: (uploaded PDF scans) | C39: Helderberg Hilltowns local news. Scan used: Jun 1 2000, "Does erosion threaten area roadways?" (W.M. Leight) — Bozenkill Rd erosion (Knox), New Scotland items (Meads Corners limestone slab, La Grange Lane ditch), and a reference enriching the 2000 Delaware Ave / Delmar slide. Batch 4 (highest-signal, local): May 13 1949 (2 new Schoharie caves → Karst; early-May 1949 heat/frost swing → Events); Aug 4 1988 (Normanskill Blue Cross/Rte 85 slide, undated → Events); 1992 (Fox Creek ~50 m sinkhole → Karst); Jun 15 2000 (May 2000 Delaware Ave slide — SBA disaster declaration — ENRICHMENT). Planning-context scans reviewed (no event): Jul 14 1988 (Guilderland GEPOD geohazard districts), Nov 10 1988 (Berne Rte 157A sinkhole), Nov 16 1989 (New Scotland master-plan sinkhole/landslide mapping); Jul 22 1977 (Ward-Gregory cave-rescue drill — enrichment of the existing Clarksville pin). Batch 5 (2001–2005): May 24 2001 (Clarksville cave-diving fatality → Events; 2000 Delaware Ave slide Rte-443/veg-stand ENRICHMENT); Oct 21 2004 letter (new Berne Rte-443 sinkhole → Events). Mike Nardacci's recurring "Backroads geology" column is a KARST goldmine — batch-5 columns ENRICH existing pins: Knox Cave (Jul/Oct 2004: Manlius ls, gaping-sinkhole entrance, Knox Roller Rink built 1937, Robinson House ~1810, owner Ada Robinson d.1964, Organa Industries, arson fires, 1970s entrance falling-ice fatality = the 1975 ice fall, 1970s staircase-boulder fall, 13+ mi mapped), Onesquethaw Cave (Oct 2003: Lawson's Lake overflow, flash-flood danger, Rte 32 resurgence, prehistoric fault), Skull/New Skull/Old Skull (Jan 2005: New Skull ~5 mi mapped; Old Skull bone-chamber / giant ground-sloth legend), Clarksville (Ward-Gregory) pin (2001 fatality/recovery). Jul 24 2003: Beaverdam Rd natural bridge → Karst. Flag: SW Bethlehem 'broad shallow sinkhole' on the Frueh mine site (Jun 26 2003) — minor/permit-context.
A40: The Catskill Mountain News (Margaretville, N.Y.) | B40: (uploaded PDF scans) | C40: Central/western Catskills local news. Batch 3 scans (Apr 20 1917; Jul 9 1981 x2) REVIEWED but nothing staged — all 'sinkhole'/'landslide' hits were out-of-region or metaphorical (Port Said 'Sinkhole of the East'; Winter Park FL 1981 sinkhole as a vacation stop; Whiteface ancient slide scar). Flag: later-era CMN/Argus scans skew heavily to metaphorical/tourism keyword hits.
A41: Helderberg Escarpment Planning Guide (co-eds Driscoll & Lindsay Childs) | B41: (regional land-use/karst guide; cited in Altamont Enterprise 2002–2004) | C41: A comprehensive Helderberg-escarpment land-use + geology guide for municipal boards, landowners and developers. Rich on KARST: caves, sinking streams, sinkholes, limestone pavement, complex underground drainage in the Helderberg-group and Onondaga limestones; karst-aquifer contamination risk; wastewater-district recommendations for the Thompsons Lake / Helderberg Lake / Warners Lake and karst areas; Clarksville Cave (ceiling-to-surface 0–32 ft); a flora/fauna inventory. A LOCAL analogue to the USGS Kappel 2020 karst assessment — worth pulling in full for a systematic Hilltowns karst/slide inventory. Cited in Altamont Enterprise, Jun 27 2002 ("Karst reality"), Jun 26 2003, Oct 21 2004. Also referenced: Paul Rubin's 1994–95 Bethlehem terrain guidebook (karst hydrogeology).
A42: USGS Landslide Inventories across the United States, v3.0 | B42: https://doi.org/10.5066/P14AJF8I (us_ls_v3_point.csv / us_ls_v3_poly.csv) | C42: SYSTEMATIC national landslide point/polygon compilation from 131 constituent inventories. QUERIED 2026-09-22 for the 6 counties Laurie named (Albany, Greene, Columbia, Ulster, Schoharie, Schenectady) by point-in-polygon against Census county boundaries: 15 records total (all points; 0 polygons). Of the 15: 5 new NASA-catalog events staged (Events 328-332) + 8 undated 'USGS Conterminous' debris-flow inventory points staged as pins; 2 NASA entries were DUPLICATES of existing records (2015 Normanside CC slide; 2018 Barney St/Nott Terrace Schenectady — coords/detail sent to the cartographer merge notes). Constituent sub-sources seen here: NASA Global Landslide Catalog (media-report events, incl. NYS DEC contributions) and the USGS conterminous debris-flow compilation (MF-2329, 1999). NY coverage in v3 is sparse — this is close to the region's full v3 footprint. Filtered subset saved as six_county_landslides.csv.

Sheet Frost & Freeze Phenology
A1: Frost & Freeze Phenology — Alcove Dam (Coeymans, Albany Co., NOAA co-op station, ~590 ft)
A2: Computed 2026-09-21 by Claude in the atlas session, from the station's own GHCN daily record (already in the atlas repo as data/stations/alcove_dam.csv — this answers the register's open item #4). NOT the plateau itself: Alcove Dam sits ~1,100 ft below Laurie's Westerlo land, so its frost dates run measurably earlier-to-thaw / later-to-freeze than the 1,700-ft plateau will actually experience — treat as the best available regional anchor, not a substitute for an on-site logger.
A3: Threshold: 32°F daily minimum. Last spring frost = latest such day on/before Jul 1; first fall frost = earliest such day on/after Jul 2.
A6: Period | B6: Years used | C6: Median last spring frost | D6: Median first fall frost | E6: Median frost-free season (days)
A7: Full record | B7: 70 (1943-2025) | C7: May 13 | D7: Oct 05 | E7: 146
A8: Recent 30 yrs | B8: 29 (1996-2025) | C8: May 07 | D8: Oct 14 | E8: 161
A10: Year-by-year (last spring frost / first fall frost / season length, days):
A11: Year | B11: Last spring frost | C11: First fall frost | D11: Season length (days)
A12: 1943 | B12: May 15 | C12: Oct 06 | D12: 144
A13: 1944 | B13: May 21 | C13: Sep 25 | D13: 127
A14: 1945 | B14: May 11 | C14: Sep 30 | D14: 142
A15: 1946 | B15: May 09 | C15: Oct 03 | D15: 147
A16: 1947 | B16: May 31 | C16: Sep 23 | D16: 115
A17: 1952 | B17: May 18 | C17: Oct 09 | D17: 144
A18: 1953 | B18: Jun 03 | C18: Sep 14 | D18: 103
A19: 1955 | B19: Apr 24 | C19: Sep 23 | D19: 152
A20: 1956 | B20: May 30 | C20: Sep 11 | D20: 104
A21: 1957 | B21: May 17 | C21: Sep 27 | D21: 133
A22: 1958 | B22: May 24 | C22: Oct 02 | D22: 131
A23: 1959 | B23: May 18 | C23: Sep 18 | D23: 123
... A81: 2025 | B81: Apr 22 | C81: Oct 10 | D81: 171

Sheet Hudson Freeze Dates
A1: Winter | B1: Hudson closed at Albany | C1: Opened | D1: Lowest temp (°F) | E1: Character (as recorded)
A2: 1789-90 | B2: open till Feb 3 | E2: Very mild; mildest January since 1781; occasionally obstructed by ice before
A3: 1790-91 | B3: Dec 8 | D3: 5 | E3: Very severe December, milder Jan–Feb
A4: 1791-92 | B4: Dec 9 | D4: 1 | E4: Very severe; uninterrupted severe frost 4 weeks
A5: 1792-93 | B5: Dec 12 | E5: Very mild; open all winter to Poughkeepsie, closed only at Albany
A6: 1793-94 | B6: Dec 26 | E6: Mild, little snow
A7: 1794-95 | B7: Jan 12 | E7: Very mild autumn/December; no ice till Jan 3
A8: 1795-96 | B8: Dec 21 | C8: open till Jan 23 | E8: Very mild autumn/December
A9: 1796-97 | B9: Nov 28 | E9: Early, severe to Jan 12; intensely cold Dec 23–24
A10: 1797-98 | B10: Nov 23 | D10: 2 | E10: Very early, long and severe; brief Jan thaw
A11: 1798-99 | B11: Nov 23 | D11: 2 | E11: Early, long, severe; moderate ~3 weeks in Jan
A12: 1799-1800 | B12: Jan 6 | E12: Mild; obstructed by ice before closing
A13: 1800-01 | B13: Jan 3 | E13: Mild, little snow; very mild December
A14: 1801-02 | B14: open till Feb 3 | E14: Remarkably mild; Jan mercury 40–50°F; no real snow till Feb 22
A15: 1802-03 | B15: Dec 16 | E15: Mild and variable, little snow
A16: 1803-04 | B16: Jan 12 | D16: 42 | E16: Very mild December; severe weather + deep snows Jan/late Feb
A17: 1804-05 | B17: Dec 13 | D17: 2 | E17: Remarkably cold and variable; deep snows, heavy rains, high winds; distress among the poor
A18: 1805-06 | B18: Jan 9 | C18: Feb 23 | E18: Cold in January, mild Dec and Feb
A19: 1806-07 | B19: Dec 11 | D19: 4 | E19: Severe winter
A20: 1807-08 | B20: Jan 4 | E20: Mild; very mild December
A21: 1808-09 | B21: Dec 9 | D21: 6 | E21: Long and severe, much snow
A22: 1809-10 | B22: Jan 19 | D22: 1 | E22: Remarkably mild till Jan 19, then intensely cold; little snow
A23: 1810-11 | B23: Dec 14 | E23: Much snow Feb; severe snowstorm Nov 2
A24: 1811-12 | B24: Dec 20 | D24: 2 | E24: Severe winter
A25: 1812-13 | B25: Dec 21 | D25: 4 | E25: Severe winter
A26: 1813-14 | B26: Dec 22 | D26: 8 | E26: Severe winter
A27: 1814-15 | B27: Dec 10 | D27: 1 | E27: Very severe though variable
A28: 1815-16 | B28: Dec 2 | E28: Variable, not severe
A29: 1816-17 | B29: Dec 16 | D29: -6 | E29: Very severe from mid-Jan; −6°F Feb 15, first sub-zero at Albany since 1788
A30: 1817-18 | B30: Dec 7 (opened 14th, closed again 21st) | D30: 0 | E30: Moderate Dec/Jan, severe February
A31: 1818-19 | B31: Dec 14 | E31: Severe 2 weeks in Dec; very mild Jan/Feb
A32: 1819-20 | B32: Dec 13 | D32: 3 | E32: Severe; several deep snows; obstructed by ice before
A33: 1820-21 | B33: Nov 13 (opened 20th, closed again Dec 1) | D33: -7 | E33: Intensely severe most of January; −7°F Jan 25 (coldest ever here); Hudson crossed on the ice at Albany
A34: 1821-22 | B34: Dec 13 | D34: -1 | E34: Severe, little snow
A35: 1822-23 | B35: Dec 24 | D35: 3 | E35: No severe weather till Feb/Mar
A36: 1823-24 | B36: Dec 16 | C36: open in Jan briefly | E36: Very mild
A37: 1824-25 | B37: Jan 3 | E37: Mild, little snow
A38: 1825-26 | B38: Dec 13 | E38: Generally very mild; cold Dec 14 (3°F at 8 AM)
A39: 1826-27 | B39: Dec 24 | D39: 3 | E39: Severe winter
A40: 1827-28 | B40: closed ~3 weeks total | E40: Very cold blustering Nov, then mildest winter since 1801–2; mildest Feb since 1778–9 (peach blossom)
A41: 1828-29 | B41: Jan 1 | C41: Mar 29 | D41: -6 | E41: Long severe winter; much suffering among the poor
A42: 1829-30 | B42: late Jan | D42: 3 | E42: Mild till Jan 23 then very severe several weeks
A43: 1830-31 | B43: Dec 23 (reopened, closed again Jan 16) | D43: 5 | E43: Severe, several deep snows; ground snow-covered Jan 6–Feb 28
A44: 1831-32 | B44: Dec 3 | D44: 14 | E44: Coldest December since 1786 (as of Dec 10)
A46: Source: Albany Daily Advertiser, "Notices of the Winters at New York for the last forty-two years… dates at which the Hudson was frozen or obstructed or closed by ice at Albany," repr. American Quarterly Journal of Agriculture and Science 1 (1845) pp. 347–350 (verified, page images)
A47: Verified against page images of pp. 347–350, https://archive.org/details/americanquarterl00slsn

Sheet CRREL Ice Jams (regional)
A1: Jam date | B1: City | C1: River | D1: Type | E1: Dist. from Westerlo (mi) | F1: Description
A2: 2026-03-11 | B2: Johnsburg | C2: Hudson River | D2: Break-up | E2: 74.4 | F2: Break-up jam formed at the confluence of Glen Creek and the Hudson River southeast of Johnsburg, NY, near the Rt 28 bridge across the Hudson. Local EM say the river has routed around the jam.
A3: 2026-03-09 | B3: Schenectady | C3: Mohawk River | D3: Break-up | E3: 24.3 | F3: A series of ice jams is affecting the reach of the Mohawk River from approximately Scotia to Lock and Dam 7, including Schenectady.
A4: 2026-01-26 | B4: Newport | C4: West Canada Creek | D4: Freeze-up | E4: 68.1 | F4: Freeze-up jam formed on West Canada Creek in Newport, NY.
A5: 2022-02-20 | B5: Warrensburg | C5: Hudson River | D5: Unknown | E5: 67.5 | F5: 212 WGUS81 KALY 201524 FLSALY Flood Advisory National Weather Servi_c_e Albany NY 1024 AM EST Sun Feb 20 2022 NYC113-201730- /O.EXT.KALY.FA.Y.0002.000000T0000Z-220220T1730Z/ /00000.N.IJ.000000T0000Z.000000T0000Z.000000T0000Z.OO/ Warren NY- 1024 AM EST Sun Feb 20 2022 ...FLOOD ADVISORY FOR AN ICE JAM NOW IN EFFECT UNTIL 1230 PM EST THIS AFTERNOON... * WHAT...Flooding caused by an ice jam continues. * WHERE...A portion of eastern New York, including the following county, Warren. * WHEN...Until 1230 PM EST. * IMPACTS...Minor flooding in low-lying and poor drainage areas. * ADDITIONAL DETAILS... - At 1020 AM EST, local emergency manager reported that the Route 418 (River Street) between Hickory Hill Road and River Road remains closed in both directions in the adjoining towns of Warrensburg and Thurman due to flooding from an ice jam. - Some locations that will experience flooding include... Warrensburg, Thurman Station and Athol. - http://www.weather.gov/safety/flood PRECAUTIONARY/PREPAREDNESS ACTIONS... Turn around, don't drown when encountering flooded roads. Most flood deaths occur in vehicles. &amp;&amp; LAT...LON 4350 7385 4349 7378 4346 7379 4347 7385 $$ CS
A6: 2022-02-18 | B6: Dolgeville | C6: East Canada Creek | D6: Break-up | E6: 54.2 | F6: Reported ice jam and flooding in Dolgeville. https://cbs6albany.com/news/local/flooding-from-ice-jams-prompts-evacuations-in-dolgeville Dolgeville, NY (WRGB)  At least 10 homes in the Village of Dolgeville were evacuated on Friday after ice jams caused the East Canada Creek to overflow its banks, turning yards and roads into waterways. As of 11:00 pm Friday night, a section of Van Biden Street remains closed as crews work to get the water back into the channel. Four homes on Van Buren St were evacuated, with residents still unable to return as of Friday night. MORE: Ice Jams, Flooding, The surge of water after the big thaw around the Capital District On the other side of the creek, six homes on Dolge Ave were evacuated. So far, residents to five of the homes were able to return. One of the residents spoke with CBS6 Briana Supardi about the wrath Mother Nature brought. It just kept coming. There was a loud roar. Very scary. It was taking trees down, punching down trees and all these icebergs you see, and then after that the flooding of course, and water pouring into peoples basements and into their garage. Its just a terrible, terrible mess, said Rob Hall, Dolgeville resident. Rob Hall and his family were one of the ten told to evacuate their homes along the East Cananda Creek Friday. Unfortunately, now our yard and our homes have become the creek, said Hall. Its been an hours-long mess. He says the flooding started around 1:30 pm this afternoon, with what looked like a wall of ice barreling down the creek. Hall and his family were able to return to their home Friday afternoon, but his next-door neighbor wasnt so lucky. He says his neighbors home had it the worst after the creek completely consumed it. Ice chunks from the creek litter the property. Flooding from ice jams prompts evacuations in Dolgeville Dolgeville residents are no strangers to flooding, but Friday was different, according to the villages Fire Chief Dave Jaquay. Jaquay tells CBSs Briana Supardi that he has never seen an ice jam this bad, dumping at the worst he has ever seen in the 16 years on the job. The fire chief says its still touch and go for the remaining five homes still evacuated. He doesnt know how long crews on Van Buren St will be working overtime to get the water back into the creek and families back into their homes.
A7: 2022-02-10 | B7: Schenectady | C7: Mohawk River | D7: Freeze-up | E7: 21.5 | F7: Ice jam occurred on the Mohawk River at Schenectady, NY. Minor flooding was reported, but tugboats have been used to carve channels and mitigate the effects of the jam. Release as of 24 Feb.
A8: 2019-02-09 | B8: Ballston Spa | C8: Kayaderosseras Creek | D8: Break-up | E8: 35.5
A9: 2019-02-08 | B9: Rotterdam | C9: Mohawk River | D9: Break-up | E9: 23
A10: 2019-01-25 | B10: Albany | C10: Hudson River | D10: Break-up | E10: 18.1
A11: 2019-01-24 | B11: Delhi | C11: West Branch Delaware River | D11: Break-up | E11: 45.2
A12: 2019-01-24 | B12: Schenectady | C12: Mohawk River | D12: Break-up | E12: 22.4
A13: 2019-01-24 | B13: Eagle Bridge | C13: Hoosic River | D13: Break-up | E13: 44.7
A14: 2018-01-23 | B14: Pittstown | C14: Sunkauissia Creek | D14: Break-up | E14: 34.9
A15: 2018-01-13 | B15: Sidney | C15: Susquehanna River | D15: Break-up | E15: 71.5
A16: 2018-01-13 | B16: Schenectady | C16: Mohawk River | D16: Break-up | E16: 24.4
A17: 2018-01-13 | B17: Warrensburg | C17: Hudson River | D17: Break-up | E17: 66.4
A18: 2018-01-13 | B18: Buskirk | C18: Hoosic River | D18: Break-up | E18: 43.5
A19: 2018-01-12 | B19: Ilion | C19: Steele Creek | D19: Break-up | E19: 61.4
... A23: 2015-04-01 | B23: Schenectady | C23: Mohawk River | D23: Break-up | E23: 21.7
A24: 2015-01-19 | B24: Eagle Bridge | C24: Hoosic River | D24: Freeze-up | E24: 44.7 | F24: Jan 21: THE EAGLE BRIDGE GAGE ON THE HOOSIC RIVER CONTINUES TO BE HAMPERED BY ICE EFFECTS AND RECENTLY HAS EXHIBITED A DECREASE IN GAGE LEVELS /BELOW FLOOD STAGE/. Jan 19: AN ICE JAM CAUSED MINOR FLOODING FOR EAGLE BRIDGE ON THE HOOSIC RIVER. THE FLOOD WARNING CONTINUES FOR THE HOOSIC RIVER AT EAGLE BRIDGE. UNTIL THIS EVENING. AT 12 PM MONDAY THE STAGE WAS 12.5 FEET DUE TO AN ICE JAM NEAR THE GAGE. FLOOD STAGE IS 11.0 FEET. MINOR FLOODING IS OCCURRING AND MINOR FLOODING IS FORECAST.
A25: 2014-03-30 | B25: Danube | C25: Nowadaga Creek | D25: Break-up | E25: 50.5 | F25: On 30 March 2014 AT 1217 PM EDT...EMERGENCY MANAGEMENT REPORTS FLOODING FROM AN ICE JAM ON THE NOWADAGA CREEK IN DANUBE. CREEK ROAD IS CLOSED DUE TO WATER AND ICE. AT 623 AM EDT...EMERGENCY MANAGEMENT REPORTS FLOODING FROM AN ICE JAM ON THE NOWADAGA CREEK IN DANUBE. CREEK ROAD IS CLOSED DUE TO WATER AND ICE.
A26: 2014-03-05 | B26: Callicoon | C26: Delaware River | D26: Break-up | E26: 73.2 | F26: HYDROLOGIC STATEMENT NATIONAL WEATHER SERVICE BINGHAMTON, NY 1206 PM EDT TUE MAR 11 2014 DATE OF OBSERVATION: 3/5/2014 ID: 159 LOCATION: DELAWARE RIVER FROM CALLICOON TO TENMILE RIVER PA REPORT: SOLID ICE COVERS THE RIVER AND STARTED ON 2/19/2014. THE SOLID ICE COVER BEGINS AT BEGINS APPROXIMATELY 2 MILES ABOVE CALLICOON BRIDGE. AND ENDS AT ENDS BELOW THE NARROWSBURG POOL. COMMENT: THIS IS THE MOST SIGNIFICANT ICE AREA. THERE IS SIGNIFICANT ICE BUILDUP IN THE FLOOD PLAIN UP TO 15' THICK OF HUMMOCK ICE FROM THE LAST FREEZE UP JAM. THE ENTIRE AREA IS SHEET ICE WITH A FEW OPEN LEADS.
A27: 2014-01-14 | B27: Herkimer | C27: Bellinger Brook | D27: Break-up | E27: 59.8 | F27: FLOOD ADVISORY NATIONAL WEATHER SERVICE ALBANY NY 429 PM EST TUE JAN 14 2014 ...THE FLOOD ADVISORY FOR ICE JAM FLOODING HAS BEEN CANCELLED FOR SOUTH CENTRAL HERKIMER COUNTY... THE ICE JAM WHICH WAS IN PLACE ON THE BELLINGER BROOK HAS BROKEN AND THE WATER WAS FLOWING FREELY. THEREFORE THE THREAT OF FLOODING HAS ENDED. LAT...LON 4307 7503 4305 7492 4299 7494 4302 7504 $$ FLOOD ADVISORY NATIONAL WEATHER SERVICE ALBANY NY 159 PM EST TUE JAN 14 2014 THE NATIONAL WEATHER SERVICE IN ALBANY HAS ISSUED A * FLOOD ADVISORY FOR ICE JAM FLOODING IN... SOUTH CENTRAL HERKIMER COUNTY IN EASTERN NEW YORK... THIS INCLUDES THE CITY OF HERKIMER... * UNTIL 145 AM EST WEDNESDAY * AT 151 PM EST...LAW ENFORCEMENT OFFICIALS REPORTED ICE JAM FLOODING ALONG THE BELLINGER BROOK...CLOSING THE ROADS NEAR THE INTERSECTION OF CHURCH STREET AND WEST GERMAN STREET. ICE ALONG THE BRIDGE IN THE AREA IS BACKING UP WATER ON THESE STREETS AND THE FLOODING IS EXPECTED TO CONTINUE THROUGH THIS EVENING. LIGHT RAIN RUNNING OFF INTO THE BROOK COULD ALSO CONTRIBUTE TO THE WATER ON THE ROADS. PRECAUTIONARY/PREPAREDNESS ACTIONS... A FLOOD ADVISORY MEANS RIVER OR STREAM FLOWS ARE ELEVATED OR PONDING OF WATER IN URBAN OR OTHER AREAS IS OCCURRING OR IS IMMINENT. && LAT...LON 4307 7503 4305 7492 4299 7494 4302 7504 $$ Central Paving, Herkimer County and others brought in excavators to take out the ice, working on both sides of the bridge, according to Herkimer Police Capt. Scott Scherer. Later in the afternoon, a utility pole was brought in and used to ram the ice, finally breaking up the jam, he said. Cement barriers and sandbags were used to divert the flow of the water down Graham Street. Scherer said the Herkimer Department of Public Works would be on the scene into the evening cleaning up the chunks of ice that were dumped in the park area along the creek between Church and German streets.
A28: 2014-01-13 | B28: Ballston Spa | C28: Kayaderosseras Creek | D28: Break-up | E28: 35.6 | F28: An ice jam had caused the Kayaderosseras Creek to flood Kelley Park in Ballston Spa, NY on Monday 13 Jan 2014, according to the Saratogian.com. The bridge on Ralph Street was shut down due to flooding concerns and water and sewer lines which run under the bridge. Homes affected by flood waters were located on Liberty, Kent and Mechanic Streets.
A29: 2014-01-12 | B29: Thurman | C29: Glen Creek | D29: Break-up | E29: 72.5 | F29: The poststar.com reported that 'weather causes issues in Johnsburg, Thurman' on Sunday 12 Jan 14 in NY. "Claude Straight Road had water hitting the bridge beams Saturday afternoon because of the heavy rains, according to Highway Superintendent Dan Hitchcock. Hitchcock said Harrington Road also had ice up to scraper banks in some locations and Glen Creek Road was closed early Sunday morning because of an ice jam and flooding." "In Thurman, an ice jam on the Hudson River shut down a road in the town. River Road closed Sunday evening because of the issue, according to the Warren County Sheriffs Office."
A30: 2014-01-11 | B30: Eagle Bridge | C30: Hoosic River | D30: Break-up | E30: 44.7 | F30: Authorities in Rensselaer County reported an ice jam on the Hoosic River caused minor flooding late Saturday on County Route 103 in the Town of Hoosick. A section of the roadway, near the Buskirk Bridge, was closed. NWS reported road closures in southern WAshing county in Cambridge at King Road and Cty Rte 59 with ice bakcing up and minor flooding. NWS gages peak at 11.99 ft. Minor flooding occurs at 11ft. Location is estimated based on descriptions of flooding upstream of jam.
A31: 2014-01-10 | B31: Starkville | C31: Otsquago Creek | D31: Break-up | E31: 46.3 | F31: According to Fox23 News on 10 Jan 2014, heavy machinery was brought in to remove ice from under the Route 80 bridge on the Otsquago Creek, in Starkville, NY in order to avoid flooding. Sub-zero temps, resulting in ice accumulation on area rivers was followed by warm, rainy conditions on 11 Jan 2014, leading to ice jam breakup flooding across the region.
A32: 2014-01-08 | B32: Poughkeepsie | C32: Wappingers Creek | D32: Break-up | E32: 60.6 | F32: 1113 AM EST WED JAN 8 2014 THE NATIONAL WEATHER SERVICE IN ALBANY HAS ISSUED A * FLOOD ADVISORY FOR ICE JAM FLOODING IN... WEST CENTRAL DUTCHESS COUNTY IN EAST CENTRAL NEW YORK... THIS INCLUDES THE CITY OF POUGHKEEPSIE... * UNTIL 515 PM EST WEDNESDAY * AT 1109 AM EST EMERGENCY MANAGEMENT IS REPORTING AN ICE JAM WAS IN PROGRESS IN THE VICINITY OF WAPPINGERS CREEK BETWEEN JACKSON ROAD AND RED OAKS NEAR ROUTE 346. COUNTY POLICE ALONG WITH EMERGENCY MANAGEMENT CONTINUE TO CLOSELY EVALUATE THE SITUATION. ICE JAMS CAN DEVELOP VERY QUICKLY AS MOTORISTS AND RESIDENTS ARE URGED TO SEEK HIGHER GROUND IF WATER LEVELS INCREASE. PRECAUTIONARY/PREPAREDNESS ACTIONS... DO NOT DRIVE YOUR VEHICLE INTO AREAS WHERE THE WATER COVERS THE ROADWAY. THE WATER DEPTH MAY BE TOO GREAT TO ALLOW YOUR CAR TO CROSS SAFELY. MOVE TO HIGHER GROUND. A FLOOD ADVISORY MEANS RIVER OR STREAM FLOWS ARE ELEVATED OR PONDING OF WATER IN URBAN OR OTHER AREAS IS OCCURRING 1000 PM EST Thu Jan 9 2014 ... The Flood Advisory for ice jam flooding remains in effect until 100 PM EST Friday for southwestern Dutchess County... At 959 PM EST... emergency management... law enforcement and public continue to indicate an ice jam on the wappingers creek. This ice jam was between Walker Road and Maloney Road that is parallel to Route 376. At this time... no Road closures or a threat to property have been observed. However... residents and motorists are highly encouraged to monitor water levels and listen for further statements. Precautionary/preparedness actions... Do not drive your vehicle into areas where the water covers the roadway. The water depth may be too great to allow your car to cross safely. Move to higher ground. Lat... Lon 4167 7389 4167 7384 4159 7388 4159 7394 1103 AM EST SUN JAN 12 2014 ...THE FLOOD ADVISORY HAS BEEN CANCELLED FOR SOUTHWESTERN DUTCHESS COUNTY... COUNTY EMERGENCY MANAGEMENT HAS INDICATED THE ICE JAM ALONG WAPPINGERS CREEK IS NO LONGER RESULTING IN FLOODING. THEREFORE...THE FLOOD ADVISORY HAS BEEN CANCELLED.
A33: 2014-01-07 | B33: Buskirk | C33: Hoosick River | D33: Break-up | E33: 41.8 | F33: THE NATIONAL WEATHER SERVICE IN ALBANY HAS ISSUED A FLOOD ADVISORY at 536 AM EST TUE JAN 7 2014: * FLOOD ADVISORY FOR ICE JAM FLOODING IN... EXTREME NORTH CENTRAL RENSSELAER COUNTY IN EAST CENTRAL NEW YORK... SOUTH CENTRAL WASHINGTON COUNTY IN EAST CENTRAL NEW YORK... * UNTIL 1130 AM EST * AT 530 AM EST...POLICE REPORTED THAT AN ICE JAM ON THE HOOSICK RIVER NEAR BUSKIRK WAS CAUSING FLOODING ALONG COUNTY ROUTE 103...WHICH IS ALSO KNOWN AS BUSKIRK-WEST HOOSICK ROAD. THE ROAD WAS CLOSED DUE TO THE FLOODING.
A34: 2013-02-01 | B34: Thurman | C34: Hudson River | D34: Break-up | E34: 68.1 | F34: As was reported in "Hudson River ice jam causing problems", by Jon Alexander [jalexander@poststar.com] massive ice chunks up to 10 ft thick in spots, apparently broke off near North Creek, following unseasonably warm days, creating a jam on the upper Hudson River near Thurman NY on Fri 1 Feb 2013. As the ice chunks became lodged they caused the water behind them to jump the banks, with more than one hundred yards of River Road in Thurman under 3 feet of ice chunks. According to Supervisor Evelyn Wood, the water receded by midday, leaving the ice chunks in the road. On Monday town highway crews using loaders and backhoes are expected to remove the ice from River Road.
A35: 2013-01-31 | B35: Dolgeville | C35: East Canada Creek | D35: Break-up | E35: 54.6 | F35: A midwinter thaw with record breaking temperatures and rain across central and northeastern states from 29-31 Jan 2013 has resulted in numerous breakup jams across the region. At 1114 AM EST Thu 31 Jan 2013, the National Weather Service in Albany NY issued a Flood Advisory. Spotters had reported an ice jam on the East Canada Creek at 1109 AM which was causing Minor Flooding on Dolge Ave in Dolgeville NY. The Minor Flooding was forecast to subside later in the day as the water levels dropped following the snowmelt and rainfall which resulted in the breakup jam.
... A42: 2011-02-18 | B42: Canajoharie | C42: Canajoharie Creek | D42: ? | E42: 37.7 | F42: USGS Water Resources Data for New York WY 2011 reported an annual maximum peak discharge of 2000cfs on 18-FEB-2011 due to an ice jam at USGS gaging station 01349150 Canajoharie, NY. The gage height was not reported.
A43: 2011-01-25 | B43: Ilion | C43: Steele Creek | D43: Freeze-up | E43: 61.5
A44: 2010-02-26 | B44: Niskayuna | C44: Lisha Kill | D44: ? | E44: 20.7 | F44: USGS Water Resources Data for New York WY 2010 reported an annual maximum gage height of 4.93ft on 26-FEB-2010 due to an ice jam at USGS gaging station 01356190 Niskayuna, NY. The average daily discharge was not reported.
A45: 2010-01-30 | B45: Delhi | C45: Little Delaware River | D45: Freeze-up | E45: 47.4 | F45: USGS Water Resources Data for New York WY 2010 reported a gage height of 6.79ft on 30-JAN-2010 due to an ice jam at USGS gaging station 01422500 Delhi, NY. The average daily discharge was 182cfs.
A46: 2010-01-26 | B46: Schenectady | C46: Mohawk River | D46: Break-up | E46: 23.1 | F46: The National Weather Service in Albany NY issued a Flood Warning for northeastern Schenectady County in east central New York at 924am EST Tue 26 Jan 2010. A January thaw with heavy rain throughout north central and northeast regions of the US was responsible for ice jams and flooding in those areas. At 917am EST, a large ice jam was located on the Mohawk River near the interstate 890 bridge, causing flooding upstream through Rotterdam Junction, according to Schenectady County Emergency Management officials. Route 5S was closed due to flooding. At 1035am, the NWS reported the river stage to be at the Flood Stage of 223 ft, and the jam was moving through Schenectady and the Rexford Gorge, causing rapid river level fluctuations. The Flood Warning was canceled by 1pm, as the jam had moved downstream and the stage had dropped to 219 ft, with levels continuing to fall.
A47: 2010-01-25 | B47: Livingstonville | C47: Lake Creek | D47: Break-up | E47: 11.5 | F47: In a Preliminary Local Storm Report Summary issued by the National Weather Service in Albany NY, an Emergency Manager in Schoharie NY reported a Flash Flood due to an ice jam which had threatened a house on Lake Creek at 1:15pm 25 Jan 2010. The Fire Department evacuated the house. A January thaw from the North Central to Northeastern parts of the US was resulting in river flooding and ice jamming across the region.
A48: 2010-01-25 | B48: Dolgeville | C48: East Canada Creek | D48: Break-up | E48: 54.6 | F48: The National Weather Service in Albany NY issued a Flood Warning at 1138pm EST Mon 25 Jan 2010 for southern Herkimer County in eastern NY. At 1130 pm Herkimer County Emergency Management officials reported a large ice jam on the East Canada Creek in Dolgeville with the ice from the jam reaching up to the route 29 bridge, causing flooding of Main Street and requiring 25 - 35 people to be evacuated, according to multiple news articles accompanying this report. At 110am Tue 26 Jan Herkimer County Emergency Management officials reported that a second jam had come from upstream, merging into the first jam (a freezeup jam, frozen in place since 8 Jan; see entry), lodging against and up onto the bridge, causing it to be closed, and resulting in the flooding of some homes. At 126am, Herkimer County Emergency Management officials reported that the jam had released and jammed again near the hydro plant on the south side of the Dolgeville. The bridge remained closed, as large chunks of ice remained on the bridge as well as on both sides of the creek. At 350am Tue 26 Jan the Fulton County Emergency Management Office reported that portions of Dolgeville on the Fulton County side of the creek had sustained damage as a result of the ice and water from the jam. The jam had moved downstream, leaving large shear walls of ice along the banks of East Canada Creek. At 944am Tue 26 Jan, NWS canceled the Flood Warning. Herkimer County Emergency Management officials reported the flooding had diminished and conditions had improved.
A49: 2010-01-25 | B49: Canajoharie | C49: Canajoharie Creek | D49: ? | E49: 37.7 | F49: USGS Water Resources Data for New York WY 2010 reported an annual maximum peak discharge of 2000cfs on 25-JAN-2010 due to an ice jam at USGS gaging station 01349150 Canajoharie, NY. The gage height was not reported.
A50: 2010-01-08 | B50: Dolgeville | C50: East Canada Creek | D50: Frozen in place | E50: 54.6 | F50: In a Winter/Spring Flood Potential Outlook published at 1141am EST Fri 8 Jan 2010, the National Weather Service in Albany NY a breakup ice jam on the East Canada Creek was reported to be located at Dolgeville NY. The ice moved out of the headwaters, jamming at Dolgeville and was reported to be frozen in place. *** Actual date of jam not specified in reference.
A51: 2009-03-09 | B51: Dolgeville | C51: East Canada Creek | D51: Break-up | E51: 54.9 | F51: In a Flood Statement issued by the Albany NY National Weather Service, it was reported that at 930 am Monday 9 March 2009, Herkimer County Emergency Management officials reported flooding near the power plant in the village of Dolgeville NY due to an ice jam on East Canada Creek. Water was reported to have backed up onto Dolge Avenue, flooding several homes. A Flood Warning will remain in effect until midnight EDT Wednesday 11 March. At 830 pm Sunday, local officials noted that a small channel had opened up through the jam, lowering the river level behind the jam, but flooding was still occurring on the east bank of the creek behind the jam. The rain which prompted ice movement ended Monday night and temperatures dropped, allowing for further recession of water levels, however, more rain is expected Tuesday night 10 March 2009.
A52: 2009-03-08 | B52: Schenectady | C52: Mohawk River | D52: Break-up | E52: 21.3 | F52: Flood Statements were released by the National Weather Service in Albany NY throughout the day on Monday 9 March 2009, reporting ice jam flooding of the Mohawk River in the Schenectady NY area. At 1100 am EST a jam was reported by emergency management officials, stretching from just west of Freemans Bridge westward to Lock 8. Locations affected by flood waters include areas around the Schenectady County Community College, an access road from route 5, and a portion of the bike path in Rotterdam, which had been closed. At 5 pm local officials reported that the jam had broken up around 430 pm, dropping the river level 2 feet from earlier in the day. The Flood Warning was canceled in a 734 pm Flood Statement.
A53: 2009-03-07 | B53: Danube | C53: Nowadaga Creek | D53: Break-up | E53: 50.6 | F53: The National Weather Service in Albany NY issued a Flood Warning at 842 pm EST Saturday 7 March 2009 for southern Herkimer County in eastern New York. Rainfall and snowmelt had caused ice to break up and jam, causing flooding. One jam on Nowadaga Creek was causing flooding in the town of Danube, NY. Flooding resulted in the closing of Broad Street in Frankfurt, and in the town of Little Falls, Southern Avenue near route 167 was flooded as a result of the barge canal overflowing its banks. The NWS Flood Warning is in effect until 530 pm Sunday 8 Mar 09.
A54: 2009-02-13 | B54: Eagle Bridge | C54: Hoosic River | D54: Break-up | E54: 44.7 | F54: The National Weather Service in Albany NY noted that an ice jam had been reported Friday 13 Feb 2009 on the Hoosic River near Buskirk. No flooding was reported. This breakup jam resulted from a rainy warm up over the last few days, from the midwest to the northeast. With colder weather in the forecast the jams will freeze in place.
A55: 2009-02-13 | B55: Gardiner | C55: Wallkill River | D55: Break-up | E55: 57.7 | F55: The National Weather Service in Albany NY noted that ice jams were reported on the Wallkill River just downstream from the USGS Gardiner gage, #01371500, on 13 Feb 2009. No flooding was reported. Numerous jams were reported throughout the area in response to runoff resulting from warm temperatures and rainfall which occurred from the midwest to the northeast over the past few days. Below freezing temperatures forecast will result in the jams freezing in place.
... A58: 2009-01-15 | B58: Tribes Hill | C58: Mohawk River Lock 12 | D58: Freeze-up | E58: 32.1 | F58: An ice jam was reported to be located at Lock 12 on the Mohawk River near Tribes Hill, New York, in a Hydrometeorological Data Report issued by the National Weather Service in Albany NY, 15 January 2009. At that time the upper lock was obstructed by rough ice and a jam was located directly across from the lock, but the river was open above and below. In another Hydrometeorological Data Report published on Monday 26 January, the upper gauge was reported to be obstructed by rough ice. The jam was still in place, with the river frozen 1/4 mile above lock, and completely frozen below lock.
A59: 2008-12-27 | B59: Schenectady | C59: Mohawk River | D59: Unknown | E59: 21.4
A60: 2008-02-13 | B60: Buskirk | C60: Hoosic River | D60: Freeze-up | E60: 43.5 | F60: At 847pm EST Wed 13 Feb 2008, the National Weather Service in Albany NY issued a Flood Warning for Rensselaer and Washington Counties in east central NY state. Rensselaer County Emergency Management officials reported that an ice jam on the Hoosic River was causing water to flow over the banks in the vicinity of Buskirk Bridge, with flooding also noted on route 103 in Rensselaer County and River Road in Washington County. New York District COE reported that the water had receded by the following morning and all roads had reopened, and that the jam was still in place, but water was flowing past.
A61: 2007-03-16 | B61: Troy | C61: Hudson River | D61: Released | E61: 24.3 | F61: The National Weather Service's River Forecast Center in Taunton MA, issued a Hydrometeorological Coordination Message at 702 MA EDT on Friday 16 Mar 2007. The message noted that the Hudson River, at Troy NY, was above flood stage due to a breakup jam. Days of above normal temperatures across the northeast ripened and melted much of the snow cover in the area. The snowmelt runoff, along with rain on the 14th, was sufficient enough to breakup numerous rivers across the region, with many jamming and causing flooding. -- Keywords: Hudson River at Troy, NY on Mar 16, 2007 [20070316142242]
A62: 2007-03-15 | B62: Canajoharie | C62: Mohawk River | D62: Released | E62: 38 | F62: At 836 PM EDT Thursday March 15 2007, the National Weather Service in Albany issued a Flood Statement for areas along the Mohawk River, NY. Ice jams had been reported on the Mohawk River at Fort Plain, Canajoharie, Sprakers, and Schenectady. Flooding had been reported with the Fort Plain ice jam. Days of above normal temperatures across the northeast ripened and melted much of the snow cover in the area. The snowmelt runoff, along with rain on the 14th, was sufficient enough to breakup numerous rivers across the region, with many jamming and causing flooding. -- Keywords: Mohawk River at Canajoharie, NY on Mar 15, 2007 [20070316163446]
A63: 2007-03-15 | B63: Fort Plain | C63: Mohawk River | D63: Released | E63: 41 | F63: At 836 PM EDT Thursday March 15 2007, the National Weather Service in Albany issued a Flood Statement for areas along the Mohawk River, NY. Ice jams had been reported on the Mohawk River at Fort Plain, Canajoharie, Sprakers, and Schenectady. Flooding had been reported with the Fort Plain ice jam. Days of above normal temperatures across the northeast ripened and melted much of the snow cover in the area. The snowmelt runoff, along with rain on the 14th, was sufficient enough to breakup numerous rivers across the region, with many jamming and causing flooding. -- Keywords: Mohawk River at Fort Plain, NY on Mar 15, 2007 [20070316163058]
